Workbook

Sheet Tela Inicial - Calendário
E2: ='Dados de Base'!G2 -> Claudinei Gasparoto
E3: ='Dados de Base'!G3 -> Planilha 37
C5: Semana | D5: Dias | E5: Acesso
C6: 1 | D6: ="De "&TEXT(G6,"dd/mm")&" a "&TEXT(G6+6,"dd/mm") -> De 12/01 a 18/01 | G6: =Montagem!$C$12 -> 46034
C7: 2 | D7: ="De "&TEXT(G7,"dd/mm")&" a "&TEXT(G7+6,"dd/mm") -> De 19/01 a 25/01 | G7: =Montagem!$C$62 -> 46041
C8: 3 | D8: ="De "&TEXT(G8,"dd/mm")&" a "&TEXT(G8+6,"dd/mm") -> De 26/01 a 01/02 | G8: =Montagem!$C$112 -> 46048
C9: 4 | D9: ="De "&TEXT(G9,"dd/mm")&" a "&TEXT(G9+6,"dd/mm") -> De 02/02 a 08/02 | G9: =Montagem!$C$162 -> 46055
C10: 5 | D10: ="De "&TEXT(G10,"dd/mm")&" a "&TEXT(G10+6,"dd/mm") -> De 09/02 a 15/02 | G10: =Montagem!$C$212 -> 46062
C11: Área do professor | E11: Versão 2.6.03

Sheet Semana 1
A1: ='Periodização Macrociclo'!$N$1 -> Claudinei Gasparoto | R1: =$A1 -> Claudinei Gasparoto | AI1: =$A1 -> Claudinei Gasparoto | AZ1: =$A1 -> Claudinei Gasparoto | BQ1: =$A1 -> Claudinei Gasparoto | CH1: =$A1 -> Claudinei Gasparoto | CY1: =$A1 -> Claudinei Gasparoto
A2: Meso | B2: =Montagem!C2 -> 8 | C2: Micro | D2: =Montagem!F2 -> 29 | E2: Sessões na semana | J2: =Montagem!B43 -> 6 | K2: =IF(L2=0,0,L2-2&" a "&L2) -> 0 a 2 | L2: =Montagem!O5 -> 2 | R2: Meso | S2: =B2 -> 8 | T2: Micro | U2: =D2 -> 29 | V2: Sessões na semana | AA2: =J2 -> 6 | AI2: Meso | AJ2: =B2 -> 8 | AK2: Micro | AL2: =D2 -> 29 | AM2: Sessões na semana | AR2: =J2 -> 6 | AZ2: Meso | BA2: =B2 -> 8 | BB2: Micro | BC2: =D2 -> 29 | BD2: Sessões na semana | BI2: =J2 -> 6 | BQ2: Meso | BR2: =B2 -> 8 | BS2: Micro | BT2: =D2 -> 29 | BU2: Sessões na semana | BZ2: =J2 -> 6 | CH2: Meso | CI2: =B2 -> 8 | CJ2: Micro | CK2: =D2 -> 29 | CL2: Sessões na semana | CQ2: =J2 -> 6 | CY2: Meso | CZ2: =B2 -> 8 | DA2: Micro | DB2: =D2 -> 29 | DC2: Sessões na semana | DH2: =J2 -> 6 | DP2: Volume Total de Treinamento (min) | DQ2: =IF(L80>0,G9,0)+IF(AC80>0,X9,0)+IF(AT80>0,AO9,0)+IF(BK80>0,BF9,0)+IF(CB80>0,BW9,0)+IF(CS80>0,CN9,0)+IF(DJ80>0,DE9,0) -> 0
A3: =Montagem!K8 -> 46034 | B3: =Montagem!K9 -> Segunda-Feira | K3: =DQ17-DQ18 -> 6 | R3: =Montagem!Z8 -> 46035 | S3: =Montagem!Z9 -> Terça-Feira | AI3: =Montagem!AO8 -> 46036 | AJ3: =Montagem!AO9 -> Quarta-Feira | AZ3: =Montagem!BD8 -> 46037 | BA3: =Montagem!BD9 -> Quinta Feira | BQ3: =Montagem!BS8 -> 46038 | BR3: =Montagem!BS9 -> Sexta-Feira | CH3: =Montagem!CH8 -> 46039 | CI3: =Montagem!CH9 -> Sábado | CY3: =Montagem!CW8 -> 46040 | CZ3: =Montagem!CW9 -> Domingo | DP3: Volume de Treinamento Cíclico (min) | DQ3: =IF(L80>0,IF(ISNUMBER(B82),B82,B6),0)+IF(AC80>0,IF(ISNUMBER(S82),S82,S6),0)+IF(AT80>0,IF(ISNUMBER(AJ82),AJ82,AJ6),0)+IF(BK80>0,IF(ISNUMBER(BA82),BA82,BA6),0)+IF(CB80>0,IF(ISNUMBER(BR82),BR82,BR6),0)+IF(CS80>0,IF(ISNUMBER(CI82),CI82,CI6),0)+IF(DJ80>0,IF(ISNUMBER(CZ82),CZ82,CZ6),0) -> 0
A4: Quao recuperado você esta se sentindo (PSR)? | D4: 10 - Totalmente Recuperado | K4: =IF(D4="","",LEFT(D4,2)+0) -> 10 | R4: Quao recuperado você esta se sentindo (PSR)? | AB4: =IF(U4="","",LEFT(U4,2)+0) | AI4: Quao recuperado você esta se sentindo (PSR)? | AS4: =IF(AL4="","",LEFT(AL4,2)+0) | AZ4: Quao recuperado você esta se sentindo (PSR)? | BJ4: =IF(BC4="","",LEFT(BC4,2)+0) | BQ4: Quao recuperado você esta se sentindo (PSR)? | CA4: =IF(BT4="","",LEFT(BT4,2)+0) | CH4: Quao recuperado você esta se sentindo (PSR)? | CR4: =IF(CK4="","",LEFT(CK4,2)+0) | CY4: Quao recuperado você esta se sentindo (PSR)? | DI4: =IF(DB4="","",LEFT(DB4,2)+0) | DP4: Volume de Treinamento Cíclico (km) | DQ4: =IF(L80>0,D82,0)+IF(AC80>0,U82,0)+IF(AT80>0,AL82,0)+IF(BK80>0,BC82,0)+IF(CB80>0,BT82,0)+IF(CS80>0,CK82,0)+IF(DJ80>0,DB82,0) -> 0
A5: =IF(G9=10,"Tenha um bom descanso!😉💤","TREINAMENTO CÍCLICO") -> TREINAMENTO CÍCLICO | R5: =IF(X9=10,"Tenha um bom descanso!😉💤","TREINAMENTO CÍCLICO") -> TREINAMENTO CÍCLICO | AI5: =IF(AO9=10,"Tenha um bom descanso!😉💤","TREINAMENTO CÍCLICO") -> TREINAMENTO CÍCLICO | AZ5: =IF(BF9=10,"Tenha um bom descanso!😉💤","TREINAMENTO CÍCLICO") -> TREINAMENTO CÍCLICO | BQ5: =IF(BW9=10,"Tenha um bom descanso!😉💤","TREINAMENTO CÍCLICO") -> TREINAMENTO CÍCLICO | CH5: =IF(CN9=10,"Tenha um bom descanso!😉💤","TREINAMENTO CÍCLICO") -> TREINAMENTO CÍCLICO | CY5: =IF(DE9=10,"Tenha um bom descanso!😉💤","TREINAMENTO CÍCLICO") -> Tenha um bom descanso!😉💤 | DP5: Volume de Treinamento Resistido (séries) | DQ5: =IF(L80>0,B8,0)+IF(AC80>0,S8,0)+IF(AT80>0,AJ8,0)+IF(BK80>0,BA8,0)+IF(CB80>0,BR8,0)+IF(CS80>0,CI8,0)+IF(DJ80>0,CZ8,0) -> 0
A6: Volume | B6: =Montagem!C15 -> 25 | C6: Método | D6: =Montagem!C17 -> CEXT | F6: KCAL est. | H6: =0.0175*IF(ISNUMBER(B82),B82,B6)*'Dados de Base'!$D$5*('Dados de Base'!$D$7*IF(ISNUMBER(G82),(G82-'Dados de Base'!$F$6)/('Dados de Base'!$E$20-'Dados de Base'!$F$6),Montagem!C27)) -> 248.61375 | R6: Volume | S6: =Montagem!D15 -> 5 | T6: Método | U6: =Montagem!D17 -> IINT | W6: KCAL est. | Y6: =0.0175*IF(ISNUMBER(S82),S82,S6)*'Dados de Base'!$D$5*('Dados de Base'!$D$7*IF(ISNUMBER(X82),(X82-'Dados de Base'!$F$6)/('Dados de Base'!$E$20-'Dados de Base'!$F$6),Montagem!D27)) -> 0 | AI6: Volume | AJ6: =Montagem!E15 | AK6: Método | AL6: =Montagem!E17 | AN6: KCAL est. | AP6: =0.0175*IF(ISNUMBER(AJ82),AJ82,AJ6)*'Dados de Base'!$D$5*('Dados de Base'!$D$7*IF(ISNUMBER(AO82),(AO82-'Dados de Base'!$F$6)/('Dados de Base'!$E$20-'Dados de Base'!$F$6),Montagem!E27)) -> 0 | AZ6: Volume | BA6: =Montagem!F15 -> 6 | BB6: Método | BC6: =Montagem!F17 -> IINT | BE6: KCAL est. | BG6: =0.0175*IF(ISNUMBER(BA82),BA82,BA6)*'Dados de Base'!$D$5*('Dados de Base'!$D$7*IF(ISNUMBER(BF82),(BF82-'Dados de Base'!$F$6)/('Dados de Base'!$E$20-'Dados de Base'!$F$6),Montagem!F27)) -> 0 | BQ6: Volume | BR6: =Montagem!G15 -> 35 | BS6: Método | BT6: =Montagem!G17 -> CEXT | BV6: KCAL est. | BX6: =0.0175*IF(ISNUMBER(BR82),BR82,BR6)*'Dados de Base'!$D$5*('Dados de Base'!$D$7*IF(ISNUMBER(BW82),(BW82-'Dados de Base'!$F$6)/('Dados de Base'!$E$20-'Dados de Base'!$F$6),Montagem!G27)) -> 348.05925 | CH6: Volume | CI6: =Montagem!H15 | CJ6: Método | CK6: =Montagem!H17 | CM6: KCAL est. | CO6: =0.0175*IF(ISNUMBER(CI82),CI82,CI6)*'Dados de Base'!$D$5*('Dados de Base'!$D$7*IF(ISNUMBER(CN82),(CN82-'Dados de Base'!$F$6)/('Dados de Base'!$E$20-'Dados de Base'!$F$6),Montagem!H27)) -> 0 | CY6: Volume | CZ6: =Montagem!I15 | DA6: Método | DB6: =Montagem!I17 | DD6: KCAL est. | DF6: =0.0175*IF(ISNUMBER(CZ82),CZ82,CZ6)*'Dados de Base'!$D$5*('Dados de Base'!$D$7*IF(ISNUMBER(DE82),(DE82-'Dados de Base'!$F$6)/('Dados de Base'!$E$20-'Dados de Base'!$F$6),Montagem!I27)) -> 0 | DP6: Numero de Repetições | DQ6: =IF(L80>0,E8,0)+IF(AC80>0,V8,0)+IF(AT80>0,AM8,0)+IF(BK80>0,BD8,0)+IF(CB80>0,BU8,0)+IF(CS80>0,CL8,0)+IF(DJ80>0,DC8,0) -> 0
A7: =IF(G9=10,"Se você tem treino programado nesta data, entre em contato com a equipe para atualizarmos a sessão!","TREINAMENTO RESISTIDO") -> TREINAMENTO RESISTIDO | R7: =IF(X9=10,"Se você tem treino programado nesta data, entre em contato com a equipe para atualizarmos a sessão!","TREINAMENTO RESISTIDO") -> TREINAMENTO RESISTIDO | AI7: =IF(AO9=10,"Se você tem treino programado nesta data, entre em contato com a equipe para atualizarmos a sessão!","TREINAMENTO RESISTIDO") -> TREINAMENTO RESISTIDO | AZ7: =IF(BF9=10,"Se você tem treino programado nesta data, entre em contato com a equipe para atualizarmos a sessão!","TREINAMENTO RESISTIDO") -> TREINAMENTO RESISTIDO | BQ7: =IF(BW9=10,"Se você tem treino programado nesta data, entre em contato com a equipe para atualizarmos a sessão!","TREINAMENTO RESISTIDO") -> TREINAMENTO RESISTIDO | CH7: =IF(CN9=10,"Se você tem treino programado nesta data, entre em contato com a equipe para atualizarmos a sessão!","TREINAMENTO RESISTIDO") -> TREINAMENTO RESISTIDO | CY7: =IF(DE9=10,"Se você tem treino programado nesta data, entre em contato com a equipe para atualizarmos a sessão!","TREINAMENTO RESISTIDO") -> Se você tem treino programado nesta data, entre em contato com a equipe para atualizarmos a sessão! | DP7: Volume de Treinamento Resistido (t) | DQ7: =E83+V83+AM83+BD83+BU83+CL83+DC83 -> 0
A8: N. Séries | B8: =SUM(E16,E18,E20,E22,E26,E28,E30,E32,E34,E36,E38,E40,E42,E44,E46,E48,E50,E52,E54,E56,E58,E60,E62,E64,E68,E70,E72) -> 46 | C8: N. repetições | E8: =SUM(E16*F16,E18*F18,E20*F20,E22*F22,E26*F26,E28*F28,E30*F30,E32*F32,E34*F34,E36*F36,E38*F38,E40*F40,E42*F42,E44*F44,E46*F46,E48*F48,E50*F50,E52*F52,E54*F54,E56*F56,E58*F58,E60*F60,E62*F62,E64*F64,E68*F68,E70*F70,E72*F72) -> 460 | F8: KCAL est. | H8: =0.0175*'Dados de Base'!$D$5*D89*5 -> 119.4375 | R8: N. Séries | S8: =SUM(V16,V18,V20,V22,V26,V28,V30,V32,V34,V36,V38,V40,V42,V44,V46,V48,V50,V52,V54,V56,V58,V60,V62,V64,V68,V70,V72) -> 42 | T8: N. repetições | V8: =SUM(V16*W16,V18*W18,V20*W20,V22*W22,V26*W26,V28*W28,V30*W30,V32*W32,V34*W34,V36*W36,V38*W38,V40*W40,V42*W42,V44*W44,V46*W46,V48*W48,V50*W50,V52*W52,V54*W54,V56*W56,V58*W58,V60*W60,V62*W62,V64*W64,V68*W68,V70*W70,V72*W72) -> 525 | W8: KCAL est. | Y8: =0.0175*'Dados de Base'!$D$5*U89*5 -> 114.38438 | AI8: N. Séries | AJ8: =SUM(AM16,AM18,AM20,AM22,AM26,AM28,AM30,AM32,AM34,AM36,AM38,AM40,AM42,AM44,AM46,AM48,AM50,AM52,AM54,AM56,AM58,AM60,AM62,AM64,AM68,AM70,AM72) -> 5 | AK8: N. repetições | AM8: =SUM(AM16*AN16,AM18*AN18,AM20*AN20,AM22*AN22,AM26*AN26,AM28*AN28,AM30*AN30,AM32*AN32,AM34*AN34,AM36*AN36,AM38*AN38,AM40*AN40,AM42*AN42,AM44*AN44,AM46*AN46,AM48*AN48,AM50*AN50,AM52*AN52,AM54*AN54,AM56*AN56,AM58*AN58,AM60*AN60,AM62*AN62,AM64*AN64,AM68*AN68,AM70*AN70,AM72*AN72) -> 90 | AN8: KCAL est. | AP8: =0.0175*'Dados de Base'!$D$5*AL89*5 -> 11.94375 | AZ8: N. Séries | BA8: =SUM(BD16,BD18,BD20,BD22,BD26,BD28,BD30,BD32,BD34,BD36,BD38,BD40,BD42,BD44,BD46,BD48,BD50,BD52,BD54,BD56,BD58,BD60,BD62,BD64,BD68,BD70,BD72) -> 40 | BB8: N. repetições | BD8: =SUM(BD16*BE16,BD18*BE18,BD20*BE20,BD22*BE22,BD26*BE26,BD28*BE28,BD30*BE30,BD32*BE32,BD34*BE34,BD36*BE36,BD38*BE38,BD40*BE40,BD42*BE42,BD44*BE44,BD46*BE46,BD48*BE48,BD50*BE50,BD52*BE52,BD54*BE54,BD56*BE56,BD58*BE58,BD60*BE60,BD62*BE62,BD64*BE64,BD68*BE68,BD70*BE70,BD72*BE72) -> 410 | BE8: KCAL est. | BG8: =0.0175*'Dados de Base'!$D$5*BC89*5 -> 107.49375 | BQ8: N. Séries | BR8: =SUM(BU16,BU18,BU20,BU22,BU26,BU28,BU30,BU32,BU34,BU36,BU38,BU40,BU42,BU44,BU46,BU48,BU50,BU52,BU54,BU56,BU58,BU60,BU62,BU64,BU68,BU70,BU72) -> 46 | BS8: N. repetições | BU8: =SUM(BU16*BV16,BU18*BV18,BU20*BV20,BU22*BV22,BU26*BV26,BU28*BV28,BU30*BV30,BU32*BV32,BU34*BV34,BU36*BV36,BU38*BV38,BU40*BV40,BU42*BV42,BU44*BV44,BU46*BV46,BU48*BV48,BU50*BV50,BU52*BV52,BU54*BV54,BU56*BV56,BU58*BV58,BU60*BV60,BU62*BV62,BU64*BV64,BU68*BV68,BU70*BV70,BU72*BV72) -> 460 | BV8: KCAL est. | BX8: =0.0175*'Dados de Base'!$D$5*BT89*5 -> 119.4375 | CH8: N. Séries | CI8: =SUM(CL16,CL18,CL20,CL22,CL26,CL28,CL30,CL32,CL34,CL36,CL38,CL40,CL42,CL44,CL46,CL48,CL50,CL52,CL54,CL56,CL58,CL60,CL62,CL64,CL68,CL70,CL72) -> 6 | CJ8: N. repetições | CL8: =SUM(CL16*CM16,CL18*CM18,CL20*CM20,CL22*CM22,CL26*CM26,CL28*CM28,CL30*CM30,CL32*CM32,CL34*CM34,CL36*CM36,CL38*CM38,CL40*CM40,CL42*CM42,CL44*CM44,CL46*CM46,CL48*CM48,CL50*CM50,CL52*CM52,CL54*CM54,CL56*CM56,CL58*CM58,CL60*CM60,CL62*CM62,CL64*CM64,CL68*CM68,CL70*CM70,CL72*CM72) -> 100 | CM8: KCAL est. | CO8: =0.0175*'Dados de Base'!$D$5*CK89*5 -> 9.1875 | CY8: N. Séries | CZ8: =SUM(DC16,DC18,DC20,DC22,DC26,DC28,DC30,DC32,DC34,DC36,DC38,DC40,DC42,DC44,DC46,DC48,DC50,DC52,DC54,DC56,DC58,DC60,DC62,DC64,DC68,DC70,DC72) -> 0 | DA8: N. repetições | DC8: =SUM(DC16*DD16,DC18*DD18,DC20*DD20,DC22*DD22,DC26*DD26,DC28*DD28,DC30*DD30,DC32*DD32,DC34*DD34,DC36*DD36,DC38*DD38,DC40*DD40,DC42*DD42,DC44*DD44,DC46*DD46,DC48*DD48,DC50*DD50,DC52*DD52,DC54*DD54,DC56*DD56,DC58*DD58,DC60*DD60,DC62*DD62,DC64*DD64,DC68*DD68,DC70*DD70,DC72*DD72) -> 0 | DD8: KCAL est. | DF8: =0.0175*'Dados de Base'!$D$5*DB89*5 -> 0 | DP8: Tempo sob Tensão (min) | DQ8: =IF(L80>0,D89,0)+IF(AC80>0,U89,0)+IF(AT80>0,AL89,0)+IF(BK80>0,BC89,0)+IF(CB80>0,BT89,0)+IF(CS80>0,CK89,0)+IF(DJ80>0,DB89,0) -> 0
A9: TEMPO ESTIMADO PARA A SESSÃO (min) | G9: =((D89+K89+IF(ISNUMBER(B82),B82,B6))*Montagem!AS3)+10 -> 73.25 | R9: TEMPO ESTIMADO PARA A SESSÃO (min) | X9: =((U89+AB89+IF(ISNUMBER(S82),S82,S6))*Montagem!AS3)+10 -> 51.25 | AI9: TEMPO ESTIMADO PARA A SESSÃO (min) | AO9: =((AL89+AS89+IF(ISNUMBER(AJ82),AJ82,AJ6))*Montagem!AS3)+10 -> 13.833333 | AZ9: TEMPO ESTIMADO PARA A SESSÃO (min) | BF9: =((BC89+BJ89+IF(ISNUMBER(BA82),BA82,BA6))*Montagem!AS3)+10 -> 51 | BQ9: TEMPO ESTIMADO PARA A SESSÃO (min) | BW9: =((BT89+CA89+IF(ISNUMBER(BR82),BR82,BR6))*Montagem!AS3)+10 -> 83.25 | CH9: TEMPO ESTIMADO PARA A SESSÃO (min) | CN9: =((CK89+CR89+IF(ISNUMBER(CI82),CI82,CI6))*Montagem!AS3)+10 -> 13.333333 | CY9: TEMPO ESTIMADO PARA A SESSÃO (min) | DE9: =((DB89+DI89+IF(ISNUMBER(CZ82),CZ82,CZ6))*Montagem!AS3)+10 -> 10 | DP9: Gasto Energético (kcal) | DQ9: =IF(L80>0,H8+H6,0)+IF(AC80>0,Y8+Y6,0)+IF(AT80>0,AP8+AP6,0)+IF(BK80>0,BG8+BG6,0)+IF(CB80>0,BX8+BX6,0)+IF(CS80>0,CO8+CO6,0)+IF(DJ80>0,DF8+DF6,0) -> 0
A10: ORIENTAÇÕES GERAIS | R10: ORIENTAÇÕES GERAIS | AI10: ORIENTAÇÕES GERAIS | AZ10: ORIENTAÇÕES GERAIS | BQ10: ORIENTAÇÕES GERAIS | CH10: ORIENTAÇÕES GERAIS | CY10: ORIENTAÇÕES GERAIS | DP10: Gasto Energético Média/dia (kcal) | DQ10: =DQ9/7 -> 0
A11: =Montagem!K12 | R11: =Montagem!Z12 | AI11: =Montagem!AO12 | AZ11: =Montagem!BD12 | BQ11: =Montagem!BS12 | CH11: =Montagem!CH12 | CY11: =Montagem!CW12 | DP11: Carga Interna de Treinamento (ua) | DQ11: =SUM(D90,U90,AL90,BC90,BT90,CK90,DB90) -> 0
A12: =Montagem!K13 | R12: =Montagem!Z13 | AI12: =Montagem!AO13 | AZ12: =Montagem!BD13 | BQ12: =Montagem!BS13 | CH12: =Montagem!CH13 | CY12: =Montagem!CW13 | DP12: Carga Interna de Treinamento Média da Sessão | DQ12: =IF(DQ18=0,0,DQ11/DQ18) -> 0
A13: =IFS(L2=4,"Semana de Adaptação",L2=2,"Semana Ordinária",L2=0,"Semana de Choque") -> Semana Ordinária | R13: =IFS(L2=4,"Semana de Adaptação",L2=2,"Semana Ordinária",L2=0,"Semana de Choque") -> Semana Ordinária | AI13: =IFS(L2=4,"Semana de Adaptação",L2=2,"Semana Ordinária",L2=0,"Semana de Choque") -> Semana Ordinária | AZ13: =IFS(L2=4,"Semana de Adaptação",L2=2,"Semana Ordinária",L2=0,"Semana de Choque") -> Semana Ordinária | BQ13: =IFS(L2=4,"Semana de Adaptação",L2=2,"Semana Ordinária",L2=0,"Semana de Choque") -> Semana Ordinária | CH13: =IFS(L2=4,"Semana de Adaptação",L2=2,"Semana Ordinária",L2=0,"Semana de Choque") -> Semana Ordinária | CY13: =IFS(L2=4,"Semana de Adaptação",L2=2,"Semana Ordinária",L2=0,"Semana de Choque") -> Semana Ordinária | DP13: Carga Interna de Treinamento Média Diária | DQ13: =DQ11/7 -> 0
A14: MOBILIDADE | AQUECIMENTO | ATIVAÇÃO | TÉCNICO | R14: MOBILIDADE | AQUECIMENTO | ATIVAÇÃO | TÉCNICO | AI14: MOBILIDADE | AQUECIMENTO | ATIVAÇÃO | TÉCNICO | AZ14: MOBILIDADE | AQUECIMENTO | ATIVAÇÃO | TÉCNICO | BQ14: MOBILIDADE | AQUECIMENTO | ATIVAÇÃO | TÉCNICO | CH14: MOBILIDADE | AQUECIMENTO | ATIVAÇÃO | TÉCNICO | CY14: MOBILIDADE | AQUECIMENTO | ATIVAÇÃO | TÉCNICO | DP14: Carga Interna de Treinamento - Desvio Padrão | DQ14: =STDEVPA(D90,U90,AL90,BC90,BT90,CK90,DB90) -> 0
A15: Exercício | D15: Sistema | E15: Séries | F15: Reps | G15: Int | H15: C | I15: E | J15: Carga | R15: Exercício | U15: Sistema | V15: Séries | W15: Reps | X15: Int | Y15: C | Z15: E | AA15: Carga | AI15: Exercício | AL15: Sistema | AM15: Séries | AN15: Reps | AO15: Int | AP15: C | AQ15: E | AR15: Carga | AZ15: Exercício | BC15: Sistema | BD15: Séries | BE15: Reps | BF15: Int | BG15: C | BH15: E | BI15: Carga | BQ15: Exercício | BT15: Sistema | BU15: Séries | BV15: Reps | BW15: Int | BX15: C | BY15: E | BZ15: Carga | CH15: Exercício | CK15: Sistema | CL15: Séries | CM15: Reps | CN15: Int | CO15: C | CP15: E | CQ15: Carga | CY15: Exercício | DB15: Sistema | DC15: Séries | DD15: Reps | DE15: Int | DF15: C | DG15: E | DH15: Carga | DP15: PSR Média | DQ15: =IF(ISERR(AVERAGE(K4,AB4,AS4,BJ4,CA4,CR4,DI4)),0,AVERAGE(K4,AB4,AS4,BJ4,CA4,CR4,DI4)) -> 10
A16: =IF(M16="","",HYPERLINK(OFFSET(Biblioteca!$B$2,MATCH(M16,Biblioteca!$A$3:$A$200,0),0),M16)) -> Mobilidade de Quadril - Iliopsoas | D16: =Montagem!Q16 -> Seriado | E16: =Montagem!R16 -> 2 | F16: =Montagem!S16 -> 10 | G16: =Montagem!T16 -> 10 | H16: =Montagem!U16 -> 1 | I16: =Montagem!V16 -> 1 | J16: 10 | K16: =Montagem!K16 -> 1 | L16: =Montagem!W16 -> 0 | M16: =Montagem!L16 -> Mobilidade de Quadril - Iliopsoas | N16: =Montagem!X16 | O16: =IF(N16="",L16,N16) -> 0 | P16: =IF(L17="C",'Dados de Base'!$D$5*0.1,IF(L17="E",5,IF(J16="",O16,J16))) -> 6.3 | R16: =IF(AD16="","",HYPERLINK(OFFSET(Biblioteca!$B$2,MATCH(AD16,Biblioteca!$A$3:$A$200,0),0),AD16)) -> Mobilidade de Quadril em S | U16: =Montagem!AF16 -> Seriado | V16: =Montagem!AG16 -> 2 | W16: =Montagem!AH16 -> 10 | X16: =Montagem!AI16 -> 10 | Y16: =Montagem!AJ16 -> 1 | Z16: =Montagem!AK16 -> 1 | AB16: =Montagem!Z16 -> 1 | AC16: =Montagem!AL16 -> 0 | AD16: =Montagem!AA16 -> Mobilidade de Quadril em S | AE16: =Montagem!AM16 | AF16: =IF(AE16="",AC16,AE16) -> 0 | AG16: =IF(AC17="C",'Dados de Base'!$D$5*0.1,IF(AC17="E",5,IF(AA16="",AF16,AA16))) -> 6.3 | AI16: =IF(AU16="","",HYPERLINK(OFFSET(Biblioteca!$B$2,MATCH(AU16,Biblioteca!$A$3:$A$200,0),0),AU16)) -> Mobilidade de Quadril - Cócoras | AL16: =Montagem!AU16 -> Seriado | AM16: =Montagem!AV16 -> 2 | AN16: =Montagem!AW16 -> 10 | AO16: =Montagem!AX16 -> 10 | AP16: =Montagem!AY16 -> 1 | AQ16: =Montagem!AZ16 -> 1 | AS16: =Montagem!AO16 -> 1 | AT16: =Montagem!BA16 -> 0 | AU16: =Montagem!AP16 -> Mobilidade de Quadril - Cócoras | AV16: =Montagem!BB16 | AW16: =IF(AV16="",AT16,AV16) -> 0 | AX16: =IF(AT17="C",'Dados de Base'!$D$5*0.1,IF(AT17="E",5,IF(AR16="",AW16,AR16))) -> 6.3 | AZ16: =IF(BL16="","",HYPERLINK(OFFSET(Biblioteca!$B$2,MATCH(BL16,Biblioteca!$A$3:$A$200,0),0),BL16)) -> Mobilidade Torácica na Parede | BC16: =Montagem!BJ16 -> Seriado | BD16: =Montagem!BK16 -> 2 | BE16: =Montagem!BL16 -> 10 | BF16: =Montagem!BM16 -> 10 | BG16: =Montagem!BN16 -> 1 | BH16: =Montagem!BO16 -> 1 | BJ16: =Montagem!BD16 -> 1 | BK16: =Montagem!BP16 -> 0 | BL16: =Montagem!BE16 -> Mobilidade Torácica na Parede | BM16: =Montagem!BQ16 | BN16: =IF(BM16="",BK16,BM16) -> 0 | BO16: =IF(BK17="C",'Dados de Base'!$D$5*0.1,IF(BK17="E",5,IF(BI16="",BN16,BI16))) -> 6.3 | BQ16: =IF(CC16="","",HYPERLINK(OFFSET(Biblioteca!$B$2,MATCH(CC16,Biblioteca!$A$3:$A$200,0),0),CC16)) -> Mobilidade de Pelve no solo | BT16: =Montagem!BY16 -> Seriado | BU16: =Montagem!BZ16 -> 2 | BV16: =Montagem!CA16 -> 10 | BW16: =Montagem!CB16 -> 10 | BX16: =Montagem!CC16 -> 1 | BY16: =Montagem!CD16 -> 1 | CA16: =Montagem!BS16 -> 1 | CB16: =Montagem!CE16 -> 0 | CC16: =Montagem!BT16 -> Mobilidade de Pelve no solo | CD16: =Montagem!CF16 | CE16: =IF(CD16="",CB16,CD16) -> 0 | CF16: =IF(CB17="C",'Dados de Base'!$D$5*0.1,IF(CB17="E",5,IF(BZ16="",CE16,BZ16))) -> 6.3 | CH16: =IF(CT16="","",HYPERLINK(OFFSET(Biblioteca!$B$2,MATCH(CT16,Biblioteca!$A$3:$A$200,0),0),CT16)) -> Mobilidade de tornozelo | CK16: =Montagem!CN16 -> Seriado | CL16: =Montagem!CO16 -> 2 | CM16: =Montagem!CP16 -> 10 | CN16: =Montagem!CQ16 -> 10 | CO16: =Montagem!CR16 -> 0 | CP16: =Montagem!CS16 -> 1 | CR16: =Montagem!CH16 -> 1 | CS16: =Montagem!CT16 -> 0 | CT16: =Montagem!CI16 -> Mobilidade de tornozelo | CU16: =Montagem!CU16 | CV16: =IF(CU16="",CS16,CU16) -> 0 | CW16: =IF(CS17="C",'Dados de Base'!$D$5*0.1,IF(CS17="E",5,IF(CQ16="",CV16,CQ16))) -> 6.3 | CY16: =IF(DK16="","",HYPERLINK(OFFSET(Biblioteca!$B$2,MATCH(DK16,Biblioteca!$A$3:$A$200,0),0),DK16)) | DB16: =Montagem!DC16 | DC16: =Montagem!DD16 | DD16: =Montagem!DE16 | DE16: =Montagem!DF16 | DF16: =Montagem!DG16 | DG16: =Montagem!DH16 | DI16: =Montagem!CW16 -> 1 | DJ16: =Montagem!DI16 | DK16: =Montagem!CX16 | DL16: =Montagem!DJ16 | DM16: =IF(DL16="",DJ16,DL16) | DN16: =IF(DJ17="C",'Dados de Base'!$D$5*0.1,IF(DJ17="E",5,IF(DH16="",DM16,DH16))) | DP16: PSE Média | DQ16: =IF(DQ18=0,0,(L80+AC80+AT80+BK80+CB80+CS80+DJ80)/DQ18) -> 0
A17: =IF(A16="","",IFS(L17="A",Montagem!$C$30,N17="T","Realizar a maior quantidade de repetições por "&F16&" segundos | ",N17="I",IF(M17="U","Manter a posição por "&F16&" segundos de um lado e trocar para o outro na sequência | ","Manter a posição por "&F16&" segundos | "),M17="A","Realizar alternadamente "&F16&" repetições cada lado | ",M17="U","Realizar "&F16&" repetições de um lado e trocar para o outro na sequência | ",L17="P",OFFSET(Biblioteca!$H$2,MATCH(M16,Biblioteca!$A$3:$A$200,0),0),TRUE,"")) | E17: =IF(A16="","",IFS(L17="H","Carga Sugerida: "&ROUNDUP(O16/2,0)&" kg de cada lado (Total: "&ROUNDUP(O16/2,0)*2&" kg)",L17="C","Este exercício usa o Peso Corporal como carga",L17="E","Este exercício usa a resistência da banda elástica como carga",L17="O","Carga Sugerida: "&INT(O16)&" kg",TRUE,"")) -> Este exercício usa o Peso Corporal como carga | K17: =K16 -> 1 | L17: =LEFT(O17) -> C | M17: =MID(O17,2,1) -> O | N17: =RIGHT(O17) -> R | O17: =IF(M16="","",OFFSET(Biblioteca!$I$2,MATCH(M16,Biblioteca!$A$3:$A$200,0),0)) -> COR | R17: =IF(R16="","",IFS(AC17="A",Montagem!$D$30,AE17="T","Realizar a maior quantidade de repetições por "&W16&" segundos | ",AE17="I",IF(AD17="U","Manter a posição por "&W16&" segundos de um lado e trocar para o outro na sequência | ","Manter a posição por "&W16&" segundos | "),AD17="A","Realizar alternadamente "&W16&" repetições cada lado | ",AD17="U","Realizar "&W16&" repetições de um lado e trocar para o outro na sequência | ",AC17="P",OFFSET(Biblioteca!$H$2,MATCH(AD16,Biblioteca!$A$3:$A$200,0),0),TRUE,"")) -> Realizar 10 repetições de um lado e trocar para o outro na sequência | | V17: =IF(R16="","",IFS(AC17="H","Carga Sugerida: "&ROUNDUP(AF16/2,0)&" kg de cada lado (Total: "&ROUNDUP(AF16/2,0)*2&" kg)",AC17="C","Este exercício usa o Peso Corporal como carga",AC17="E","Este exercício usa a resistência da banda elástica como carga",AC17="O","Carga Sugerida: "&INT(AF16)&" kg",TRUE,"")) -> Este exercício usa o Peso Corporal como carga | AB17: =AB16 -> 1 | AC17: =LEFT(AF17) -> C | AD17: =MID(AF17,2,1) -> U | AE17: =RIGHT(AF17) -> R | AF17: =IF(AD16="","",OFFSET(Biblioteca!$I$2,MATCH(AD16,Biblioteca!$A$3:$A$200,0),0)) -> CUR | AI17: =IF(AI16="","",IFS(AT17="A",Montagem!$E$30,AV17="T","Realizar a maior quantidade de repetições por "&AN16&" segundos | ",AV17="I",IF(AU17="U","Manter a posição por "&AN16&" segundos de um lado e trocar para o outro na sequência | ","Manter a posição por "&AN16&" segundos | "),AU17="A","Realizar alternadamente "&AN16&" repetições cada lado | ",AU17="U","Realizar "&AN16&" repetições de um lado e trocar para o outro na sequência | ",AT17="P",OFFSET(Biblioteca!$H$2,MATCH(AU16,Biblioteca!$A$3:$A$200,0),0),TRUE,"")) -> Manter a posição por 10 segundos | | AM17: =IF(AI16="","",IFS(AT17="H","Carga Sugerida: "&ROUNDUP(AW16/2,0)&" kg de cada lado (Total: "&ROUNDUP(AW16/2,0)*2&" kg)",AT17="C","Este exercício usa o Peso Corporal como carga",AT17="E","Este exercício usa a resistência da banda elástica como carga",AT17="O","Carga Sugerida: "&INT(AW16)&" kg",TRUE,"")) -> Este exercício usa o Peso Corporal como carga | AS17: =AS16 -> 1 | AT17: =LEFT(AW17) -> C | AU17: =MID(AW17,2,1) -> O | AV17: =RIGHT(AW17) -> I | AW17: =IF(AU16="","",OFFSET(Biblioteca!$I$2,MATCH(AU16,Biblioteca!$A$3:$A$200,0),0)) -> COI | AZ17: =IF(AZ16="","",IFS(BK17="A",Montagem!$F$30,BM17="T","Realizar a maior quantidade de repetições por "&BE16&" segundos | ",BM17="I",IF(BL17="U","Manter a posição por "&BE16&" segundos de um lado e trocar para o outro na sequência | ","Manter a posição por "&BE16&" segundos | "),BL17="A","Realizar alternadamente "&BE16&" repetições cada lado | ",BL17="U","Realizar "&BE16&" repetições de um lado e trocar para o outro na sequência | ",BK17="P",OFFSET(Biblioteca!$H$2,MATCH(BL16,Biblioteca!$A$3:$A$200,0),0),TRUE,"")) -> Realizar 10 repetições de um lado e trocar para o outro na sequência | | BD17: =IF(AZ16="","",IFS(BK17="H","Carga Sugerida: "&ROUNDUP(BN16/2,0)&" kg de cada lado (Total: "&ROUNDUP(BN16/2,0)*2&" kg)",BK17="C","Este exercício usa o Peso Corporal como carga",BK17="E","Este exercício usa a resistência da banda elástica como carga",BK17="O","Carga Sugerida: "&INT(BN16)&" kg",TRUE,"")) -> Este exercício usa o Peso Corporal como carga | BJ17: =BJ16 -> 1 | BK17: =LEFT(BN17) -> C | BL17: =MID(BN17,2,1) -> U | BM17: =RIGHT(BN17) -> R | BN17: =IF(BL16="","",OFFSET(Biblioteca!$I$2,MATCH(BL16,Biblioteca!$A$3:$A$200,0),0)) -> CUR | BQ17: =IF(BQ16="","",IFS(CB17="A",Montagem!$G$30,CD17="T","Realizar a maior quantidade de repetições por "&BV16&" segundos | ",CD17="I",IF(CC17="U","Manter a posição por "&BV16&" segundos de um lado e trocar para o outro na sequência | ","Manter a posição por "&BV16&" segundos | "),CC17="A","Realizar alternadamente "&BV16&" repetições cada lado | ",CC17="U","Realizar "&BV16&" repetições de um lado e trocar para o outro na sequência | ",CB17="P",OFFSET(Biblioteca!$H$2,MATCH(CC16,Biblioteca!$A$3:$A$200,0),0),TRUE,"")) | BU17: =IF(BQ16="","",IFS(CB17="H","Carga Sugerida: "&ROUNDUP(CE16/2,0)&" kg de cada lado (Total: "&ROUNDUP(CE16/2,0)*2&" kg)",CB17="C","Este exercício usa o Peso Corporal como carga",CB17="E","Este exercício usa a resistência da banda elástica como carga",CB17="O","Carga Sugerida: "&INT(CE16)&" kg",TRUE,"")) -> Este exercício usa o Peso Corporal como carga | CA17: =CA16 -> 1 | CB17: =LEFT(CE17) -> C | CC17: =MID(CE17,2,1) -> O | CD17: =RIGHT(CE17) -> R | CE17: =IF(CC16="","",OFFSET(Biblioteca!$I$2,MATCH(CC16,Biblioteca!$A$3:$A$200,0),0)) -> COR | CH17: =IF(CH16="","",IFS(CS17="A",Montagem!$H$30,CU17="T","Realizar a maior quantidade de repetições por "&CM16&" segundos | ",CU17="I",IF(CT17="U","Manter a posição por "&CM16&" segundos de um lado e trocar para o outro na sequência | ","Manter a posição por "&CM16&" segundos | "),CT17="A","Realizar alternadamente "&CM16&" repetições cada lado | ",CT17="U","Realizar "&CM16&" repetições de um lado e trocar para o outro na sequência | ",CS17="P",OFFSET(Biblioteca!$H$2,MATCH(CT16,Biblioteca!$A$3:$A$200,0),0),TRUE,"")) -> Realizar 10 repetições de um lado e trocar para o outro na sequência | | CL17: =IF(CH16="","",IFS(CS17="H","Carga Sugerida: "&ROUNDUP(CV16/2,0)&" kg de cada lado (Total: "&ROUNDUP(CV16/2,0)*2&" kg)",CS17="C","Este exercício usa o Peso Corporal como carga",CS17="E","Este exercício usa a resistência da banda elástica como carga",CS17="O","Carga Sugerida: "&INT(CV16)&" kg",TRUE,"")) -> Este exercício usa o Peso Corporal como carga | CR17: =CR16 -> 1 | CS17: =LEFT(CV17) -> C | CT17: =MID(CV17,2,1) -> U | CU17: =RIGHT(CV17) -> R | CV17: =IF(CT16="","",OFFSET(Biblioteca!$I$2,MATCH(CT16,Biblioteca!$A$3:$A$200,0),0)) -> CUR | CY17: =IF(CY16="","",IFS(DJ17="A",Montagem!$I$30,DL17="T","Realizar a maior quantidade de repetições por "&DD16&" segundos | ",DL17="I",IF(DK17="U","Manter a posição por "&DD16&" segundos de um lado e trocar para o outro na sequência | ","Manter a posição por "&DD16&" segundos | "),DK17="A","Realizar alternadamente "&DD16&" repetições cada lado | ",DK17="U","Realizar "&DD16&" repetições de um lado e trocar para o outro na sequência | ",DJ17="P",OFFSET(Biblioteca!$H$2,MATCH(DK16,Biblioteca!$A$3:$A$200,0),0),TRUE,"")) | DC17: =IF(CY16="","",IFS(DJ17="H","Carga Sugerida: "&ROUNDUP(DM16/2,0)&" kg de cada lado (Total: "&ROUNDUP(DM16/2,0)*2&" kg)",DJ17="C","Este exercício usa o Peso Corporal como carga",DJ17="E","Este exercício usa a resistência da banda elástica como carga",DJ17="O","Carga Sugerida: "&INT(DM16)&" kg",TRUE,"")) | DI17: =DI16 -> 1 | DJ17: =LEFT(DM17) | DK17: =MID(DM17,2,1) | DL17: =RIGHT(DM17) | DM17: =IF(DK16="","",OFFSET(Biblioteca!$I$2,MATCH(DK16,Biblioteca!$A$3:$A$200,0),0)) | DP17: Sessões na Semana | DQ17: =J2 -> 6
A18: =IF(M18="","",HYPERLINK(OFFSET(Biblioteca!$B$2,MATCH(M18,Biblioteca!$A$3:$A$200,0),0),M18)) -> Mobilidade de Pelve no solo | D18: =Montagem!Q17 -> Seriado | E18: =Montagem!R17 -> 2 | F18: =Montagem!S17 -> 10 | G18: =Montagem!T17 -> 10 | H18: =Montagem!U17 -> 1 | I18: =Montagem!V17 -> 1 | K18: =Montagem!K17 -> 2 | L18: =Montagem!W17 -> 0 | M18: =Montagem!L17 -> Mobilidade de Pelve no solo | N18: =Montagem!X17 | O18: =IF(N18="",L18,N18) -> 0 | P18: =IF(L19="C",'Dados de Base'!$D$5*0.1,IF(L19="E",5,IF(J18="",O18,J18))) -> 6.3 | R18: =IF(AD18="","",HYPERLINK(OFFSET(Biblioteca!$B$2,MATCH(AD18,Biblioteca!$A$3:$A$200,0),0),AD18)) -> Mobilidade Posterior de Coxa | U18: =Montagem!AF17 -> Seriado | V18: =Montagem!AG17 -> 2 | W18: =Montagem!AH17 -> 10 | X18: =Montagem!AI17 -> 10 | Y18: =Montagem!AJ17 -> 1 | Z18: =Montagem!AK17 -> 1 | AB18: =Montagem!Z17 -> 2 | AC18: =Montagem!AL17 -> 0 | AD18: =Montagem!AA17 -> Mobilidade Posterior de Coxa | AE18: =Montagem!AM17 | AF18: =IF(AE18="",AC18,AE18) -> 0 | AG18: =IF(AC19="C",'Dados de Base'!$D$5*0.1,IF(AC19="E",5,IF(AA18="",AF18,AA18))) -> 6.3 | AI18: =IF(AU18="","",HYPERLINK(OFFSET(Biblioteca!$B$2,MATCH(AU18,Biblioteca!$A$3:$A$200,0),0),AU18)) -> Mobilidade de tornozelo | AL18: =Montagem!AU17 -> Seriado | AM18: =Montagem!AV17 -> 2 | AN18: =Montagem!AW17 -> 10 | AO18: =Montagem!AX17 -> 10 | AP18: =Montagem!AY17 -> 1 | AQ18: =Montagem!AZ17 -> 1 | AS18: =Montagem!AO17 -> 2 | AT18: =Montagem!BA17 -> 0 | AU18: =Montagem!AP17 -> Mobilidade de tornozelo | AV18: =Montagem!BB17 | AW18: =IF(AV18="",AT18,AV18) -> 0 | AX18: =IF(AT19="C",'Dados de Base'!$D$5*0.1,IF(AT19="E",5,IF(AR18="",AW18,AR18))) -> 6.3 | AZ18: =IF(BL18="","",HYPERLINK(OFFSET(Biblioteca!$B$2,MATCH(BL18,Biblioteca!$A$3:$A$200,0),0),BL18)) -> Alongamento Iliotibial III | BC18: =Montagem!BJ17 -> Seriado | BD18: =Montagem!BK17 -> 2 | BE18: =Montagem!BL17 -> 10 | BF18: =Montagem!BM17 -> 10 | BG18: =Montagem!BN17 -> 1 | BH18: =Montagem!BO17 -> 1 | BJ18: =Montagem!BD17 -> 2 | BK18: =Montagem!BP17 -> 0 | BL18: =Montagem!BE17 -> Alongamento Iliotibial III | BM18: =Montagem!BQ17 | BN18: =IF(BM18="",BK18,BM18) -> 0 | BO18: =IF(BK19="C",'Dados de Base'!$D$5*0.1,IF(BK19="E",5,IF(BI18="",BN18,BI18))) -> 6.3 | BQ18: =IF(CC18="","",HYPERLINK(OFFSET(Biblioteca!$B$2,MATCH(CC18,Biblioteca!$A$3:$A$200,0),0),CC18)) -> Mobilidade de Pelve na bola | BT18: =Montagem!BY17 -> Seriado | BU18: =Montagem!BZ17 -> 2 | BV18: =Montagem!CA17 -> 10 | BW18: =Montagem!CB17 -> 10 | BX18: =Montagem!CC17 -> 1 | BY18: =Montagem!CD17 -> 1 | CA18: =Montagem!BS17 -> 2 | CB18: =Montagem!CE17 -> 0 | CC18: =Montagem!BT17 -> Mobilidade de Pelve na bola | CD18: =Montagem!CF17 | CE18: =IF(CD18="",CB18,CD18) -> 0 | CF18: =IF(CB19="C",'Dados de Base'!$D$5*0.1,IF(CB19="E",5,IF(BZ18="",CE18,BZ18))) -> 6.3 | CH18: =IF(CT18="","",HYPERLINK(OFFSET(Biblioteca!$B$2,MATCH(CT18,Biblioteca!$A$3:$A$200,0),0),CT18)) -> Mobilidade de Quadril - Iliopsoas | CK18: =Montagem!CN17 -> Seriado | CL18: =Montagem!CO17 -> 2 | CM18: =Montagem!CP17 -> 10 | CN18: =Montagem!CQ17 -> 10 | CO18: =Montagem!CR17 -> 0 | CP18: =Montagem!CS17 -> 1 | CR18: =Montagem!CH17 -> 2 | CS18: =Montagem!CT17 -> 0 | CT18: =Montagem!CI17 -> Mobilidade de Quadril - Iliopsoas | CU18: =Montagem!CU17 | CV18: =IF(CU18="",CS18,CU18) -> 0 | CW18: =IF(CS19="C",'Dados de Base'!$D$5*0.1,IF(CS19="E",5,IF(CQ18="",CV18,CQ18))) -> 6.3 | CY18: =IF(DK18="","",HYPERLINK(OFFSET(Biblioteca!$B$2,MATCH(DK18,Biblioteca!$A$3:$A$200,0),0),DK18)) | DB18: =Montagem!DC17 | DC18: =Montagem!DD17 | DD18: =Montagem!DE17 | DE18: =Montagem!DF17 | DF18: =Montagem!DG17 | DG18: =Montagem!DH17 | DI18: =Montagem!CW17 -> 1 | DJ18: =Montagem!DI17 | DK18: =Montagem!CX17 | DL18: =Montagem!DJ17 | DM18: =IF(DL18="",DJ18,DL18) | DN18: =IF(DJ19="C",'Dados de Base'!$D$5*0.1,IF(DJ19="E",5,IF(DH18="",DM18,DH18))) | DP18: Realizadas | DQ18: =IF(L80=0,0,1)+IF(AC80=0,0,1)+IF(AT80=0,0,1)+IF(BK80=0,0,1)+IF(CB80=0,0,1)+IF(CS80=0,0,1)+IF(DJ80=0,0,1) -> 0
A19: =IF(A18="","",IFS(L19="A",Montagem!$C$30,N19="T","Realizar a maior quantidade de repetições por "&F18&" segundos | ",N19="I",IF(M19="U","Manter a posição por "&F18&" segundos de um lado e trocar para o outro na sequência | ","Manter a posição por "&F18&" segundos | "),M19="A","Realizar alternadamente "&F18&" repetições cada lado | ",M19="U","Realizar "&F18&" repetições de um lado e trocar para o outro na sequência | ",L19="P",OFFSET(Biblioteca!$H$2,MATCH(M18,Biblioteca!$A$3:$A$200,0),0),TRUE,"")) | E19: =IF(A18="","",IFS(L19="H","Carga Sugerida: "&ROUNDUP(O18/2,0)&" kg de cada lado (Total: "&ROUNDUP(O18/2,0)*2&" kg)",L19="C","Este exercício usa o Peso Corporal como carga",L19="E","Este exercício usa a resistência da banda elástica como carga",L19="O","Carga Sugerida: "&INT(O18)&" kg",TRUE,"")) -> Este exercício usa o Peso Corporal como carga | K19: =K18 -> 2 | L19: =LEFT(O19) -> C | M19: =MID(O19,2,1) -> O | N19: =RIGHT(O19) -> R | O19: =IF(M18="","",OFFSET(Biblioteca!$I$2,MATCH(M18,Biblioteca!$A$3:$A$200,0),0)) -> COR | R19: =IF(R18="","",IFS(AC19="A",Montagem!$D$30,AE19="T","Realizar a maior quantidade de repetições por "&W18&" segundos | ",AE19="I",IF(AD19="U","Manter a posição por "&W18&" segundos de um lado e trocar para o outro na sequência | ","Manter a posição por "&W18&" segundos | "),AD19="A","Realizar alternadamente "&W18&" repetições cada lado | ",AD19="U","Realizar "&W18&" repetições de um lado e trocar para o outro na sequência | ",AC19="P",OFFSET(Biblioteca!$H$2,MATCH(AD18,Biblioteca!$A$3:$A$200,0),0),TRUE,"")) | V19: =IF(R18="","",IFS(AC19="H","Carga Sugerida: "&ROUNDUP(AF18/2,0)&" kg de cada lado (Total: "&ROUNDUP(AF18/2,0)*2&" kg)",AC19="C","Este exercício usa o Peso Corporal como carga",AC19="E","Este exercício usa a resistência da banda elástica como carga",AC19="O","Carga Sugerida: "&INT(AF18)&" kg",TRUE,"")) -> Este exercício usa o Peso Corporal como carga | AB19: =AB18 -> 2 | AC19: =LEFT(AF19) -> C | AD19: =MID(AF19,2,1) -> O | AE19: =RIGHT(AF19) -> R | AF19: =IF(AD18="","",OFFSET(Biblioteca!$I$2,MATCH(AD18,Biblioteca!$A$3:$A$200,0),0)) -> COR | AI19: =IF(AI18="","",IFS(AT19="A",Montagem!$E$30,AV19="T","Realizar a maior quantidade de repetições por "&AN18&" segundos | ",AV19="I",IF(AU19="U","Manter a posição por "&AN18&" segundos de um lado e trocar para o outro na sequência | ","Manter a posição por "&AN18&" segundos | "),AU19="A","Realizar alternadamente "&AN18&" repetições cada lado | ",AU19="U","Realizar "&AN18&" repetições de um lado e trocar para o outro na sequência | ",AT19="P",OFFSET(Biblioteca!$H$2,MATCH(AU18,Biblioteca!$A$3:$A$200,0),0),TRUE,"")) -> Realizar 10 repetições de um lado e trocar para o outro na sequência | | AM19: =IF(AI18="","",IFS(AT19="H","Carga Sugerida: "&ROUNDUP(AW18/2,0)&" kg de cada lado (Total: "&ROUNDUP(AW18/2,0)*2&" kg)",AT19="C","Este exercício usa o Peso Corporal como carga",AT19="E","Este exercício usa a resistência da banda elástica como carga",AT19="O","Carga Sugerida: "&INT(AW18)&" kg",TRUE,"")) -> Este exercício usa o Peso Corporal como carga | AS19: =AS18 -> 2 | AT19: =LEFT(AW19) -> C | AU19: =MID(AW19,2,1) -> U | AV19: =RIGHT(AW19) -> R | AW19: =IF(AU18="","",OFFSET(Biblioteca!$I$2,MATCH(AU18,Biblioteca!$A$3:$A$200,0),0)) -> CUR | AZ19: =IF(AZ18="","",IFS(BK19="A",Montagem!$F$30,BM19="T","Realizar a maior quantidade de repetições por "&BE18&" segundos | ",BM19="I",IF(BL19="U","Manter a posição por "&BE18&" segundos de um lado e trocar para o outro na sequência | ","Manter a posição por "&BE18&" segundos | "),BL19="A","Realizar alternadamente "&BE18&" repetições cada lado | ",BL19="U","Realizar "&BE18&" repetições de um lado e trocar para o outro na sequência | ",BK19="P",OFFSET(Biblioteca!$H$2,MATCH(BL18,Biblioteca!$A$3:$A$200,0),0),TRUE,"")) -> Realizar 10 repetições de um lado e trocar para o outro na sequência | | BD19: =IF(AZ18="","",IFS(BK19="H","Carga Sugerida: "&ROUNDUP(BN18/2,0)&" kg de cada lado (Total: "&ROUNDUP(BN18/2,0)*2&" kg)",BK19="C","Este exercício usa o Peso Corporal como carga",BK19="E","Este exercício usa a resistência da banda elástica como carga",BK19="O","Carga Sugerida: "&INT(BN18)&" kg",TRUE,"")) -> Este exercício usa o Peso Corporal como carga | BJ19: =BJ18 -> 2 | BK19: =LEFT(BN19) -> C | BL19: =MID(BN19,2,1) -> U | BM19: =RIGHT(BN19) -> R | BN19: =IF(BL18="","",OFFSET(Biblioteca!$I$2,MATCH(BL18,Biblioteca!$A$3:$A$200,0),0)) -> CUR | BQ19: =IF(BQ18="","",IFS(CB19="A",Montagem!$G$30,CD19="T","Realizar a maior quantidade de repetições por "&BV18&" segundos | ",CD19="I",IF(CC19="U","Manter a posição por "&BV18&" segundos de um lado e trocar para o outro na sequência | ","Manter a posição por "&BV18&" segundos | "),CC19="A","Realizar alternadamente "&BV18&" repetições cada lado | ",CC19="U","Realizar "&BV18&" repetições de um lado e trocar para o outro na sequência | ",CB19="P",OFFSET(Biblioteca!$H$2,MATCH(CC18,Biblioteca!$A$3:$A$200,0),0),TRUE,"")) | BU19: =IF(BQ18="","",IFS(CB19="H","Carga Sugerida: "&ROUNDUP(CE18/2,0)&" kg de cada lado (Total: "&ROUNDUP(CE18/2,0)*2&" kg)",CB19="C","Este exercício usa o Peso Corporal como carga",CB19="E","Este exercício usa a resistência da banda elástica como carga",CB19="O","Carga Sugerida: "&INT(CE18)&" kg",TRUE,"")) -> Este exercício usa o Peso Corporal como carga | CA19: =CA18 -> 2 | CB19: =LEFT(CE19) -> C | CC19: =MID(CE19,2,1) -> O | CD19: =RIGHT(CE19) -> R | CE19: =IF(CC18="","",OFFSET(Biblioteca!$I$2,MATCH(CC18,Biblioteca!$A$3:$A$200,0),0)) -> COR | CH19: =IF(CH18="","",IFS(CS19="A",Montagem!$H$30,CU19="T","Realizar a maior quantidade de repetições por "&CM18&" segundos | ",CU19="I",IF(CT19="U","Manter a posição por "&CM18&" segundos de um lado e trocar para o outro na sequência | ","Manter a posição por "&CM18&" segundos | "),CT19="A","Realizar alternadamente "&CM18&" repetições cada lado | ",CT19="U","Realizar "&CM18&" repetições de um lado e trocar para o outro na sequência | ",CS19="P",OFFSET(Biblioteca!$H$2,MATCH(CT18,Biblioteca!$A$3:$A$200,0),0),TRUE,"")) | CL19: =IF(CH18="","",IFS(CS19="H","Carga Sugerida: "&ROUNDUP(CV18/2,0)&" kg de cada lado (Total: "&ROUNDUP(CV18/2,0)*2&" kg)",CS19="C","Este exercício usa o Peso Corporal como carga",CS19="E","Este exercício usa a resistência da banda elástica como carga",CS19="O","Carga Sugerida: "&INT(CV18)&" kg",TRUE,"")) -> Este exercício usa o Peso Corporal como carga | CR19: =CR18 -> 2 | CS19: =LEFT(CV19) -> C | CT19: =MID(CV19,2,1) -> O | CU19: =RIGHT(CV19) -> R | CV19: =IF(CT18="","",OFFSET(Biblioteca!$I$2,MATCH(CT18,Biblioteca!$A$3:$A$200,0),0)) -> COR | CY19: =IF(CY18="","",IFS(DJ19="A",Montagem!$I$30,DL19="T","Realizar a maior quantidade de repetições por "&DD18&" segundos | ",DL19="I",IF(DK19="U","Manter a posição por "&DD18&" segundos de um lado e trocar para o outro na sequência | ","Manter a posição por "&DD18&" segundos | "),DK19="A","Realizar alternadamente "&DD18&" repetições cada lado | ",DK19="U","Realizar "&DD18&" repetições de um lado e trocar para o outro na sequência | ",DJ19="P",OFFSET(Biblioteca!$H$2,MATCH(DK18,Biblioteca!$A$3:$A$200,0),0),TRUE,"")) | DC19: =IF(CY18="","",IFS(DJ19="H","Carga Sugerida: "&ROUNDUP(DM18/2,0)&" kg de cada lado (Total: "&ROUNDUP(DM18/2,0)*2&" kg)",DJ19="C","Este exercício usa o Peso Corporal como carga",DJ19="E","Este exercício usa a resistência da banda elástica como carga",DJ19="O","Carga Sugerida: "&INT(DM18)&" kg",TRUE,"")) | DI19: =DI18 -> 1 | DJ19: =LEFT(DM19) | DK19: =MID(DM19,2,1) | DL19: =RIGHT(DM19) | DM19: =IF(DK18="","",OFFSET(Biblioteca!$I$2,MATCH(DK18,Biblioteca!$A$3:$A$200,0),0)) | DP19: Constância | DQ19: =IF(DQ17=0,0,DQ18/DQ17) -> 0
A20: =IF(M20="","",HYPERLINK(OFFSET(Biblioteca!$B$2,MATCH(M20,Biblioteca!$A$3:$A$200,0),0),M20)) -> Mobilidade de Pelve na bola | D20: =Montagem!Q18 -> Seriado | E20: =Montagem!R18 -> 2 | F20: =Montagem!S18 -> 10 | G20: =Montagem!T18 -> 10 | H20: =Montagem!U18 -> 1 | I20: =Montagem!V18 -> 1 | K20: =Montagem!K18 -> 3 | L20: =Montagem!W18 -> 0 | M20: =Montagem!L18 -> Mobilidade de Pelve na bola | N20: =Montagem!X18 | O20: =IF(N20="",L20,N20) -> 0 | P20: =IF(L21="C",'Dados de Base'!$D$5*0.1,IF(L21="E",5,IF(J20="",O20,J20))) -> 6.3 | R20: =IF(AD20="","",HYPERLINK(OFFSET(Biblioteca!$B$2,MATCH(AD20,Biblioteca!$A$3:$A$200,0),0),AD20)) -> Mobilidade Quadril - Sumô | U20: =Montagem!AF18 -> Seriado | V20: =Montagem!AG18 -> 2 | W20: =Montagem!AH18 -> 10 | X20: =Montagem!AI18 -> 10 | Y20: =Montagem!AJ18 -> 1 | Z20: =Montagem!AK18 -> 1 | AB20: =Montagem!Z18 -> 3 | AC20: =Montagem!AL18 -> 0 | AD20: =Montagem!AA18 -> Mobilidade Quadril - Sumô | AE20: =Montagem!AM18 | AF20: =IF(AE20="",AC20,AE20) -> 0 | AG20: =IF(AC21="C",'Dados de Base'!$D$5*0.1,IF(AC21="E",5,IF(AA20="",AF20,AA20))) -> 6.3 | AI20: =IF(AU20="","",HYPERLINK(OFFSET(Biblioteca!$B$2,MATCH(AU20,Biblioteca!$A$3:$A$200,0),0),AU20)) -> Prancha | AL20: =Montagem!AU18 -> Seriado | AM20: =Montagem!AV18 -> 1 | AN20: =Montagem!AW18 -> 50 | AO20: =Montagem!AX18 -> 60 | AP20: =Montagem!AY18 -> 0 | AQ20: =Montagem!AZ18 -> 1 | AS20: =Montagem!AO18 -> 3 | AT20: =Montagem!BA18 -> 0 | AU20: =Montagem!AP18 -> Prancha | AV20: =Montagem!BB18 | AW20: =IF(AV20="",AT20,AV20) -> 0 | AX20: =IF(AT21="C",'Dados de Base'!$D$5*0.1,IF(AT21="E",5,IF(AR20="",AW20,AR20))) -> 6.3 | AZ20: =IF(BL20="","",HYPERLINK(OFFSET(Biblioteca!$B$2,MATCH(BL20,Biblioteca!$A$3:$A$200,0),0),BL20)) -> Alongamento piriforme com bola | BC20: =Montagem!BJ18 -> Seriado | BD20: =Montagem!BK18 -> 2 | BE20: =Montagem!BL18 -> 10 | BF20: =Montagem!BM18 -> 10 | BG20: =Montagem!BN18 -> 1 | BH20: =Montagem!BO18 -> 1 | BJ20: =Montagem!BD18 -> 3 | BK20: =Montagem!BP18 -> 0 | BL20: =Montagem!BE18 -> Alongamento piriforme com bola | BM20: =Montagem!BQ18 | BN20: =IF(BM20="",BK20,BM20) -> 0 | BO20: =IF(BK21="C",'Dados de Base'!$D$5*0.1,IF(BK21="E",5,IF(BI20="",BN20,BI20))) -> 6.3 | BQ20: =IF(CC20="","",HYPERLINK(OFFSET(Biblioteca!$B$2,MATCH(CC20,Biblioteca!$A$3:$A$200,0),0),CC20)) -> Mobilidade Quadril - Abdução/Adução | BT20: =Montagem!BY18 -> Seriado | BU20: =Montagem!BZ18 -> 2 | BV20: =Montagem!CA18 -> 10 | BW20: =Montagem!CB18 -> 10 | BX20: =Montagem!CC18 -> 1 | BY20: =Montagem!CD18 -> 1 | CA20: =Montagem!BS18 -> 3 | CB20: =Montagem!CE18 -> 0 | CC20: =Montagem!BT18 -> Mobilidade Quadril - Abdução/Adução | CD20: =Montagem!CF18 | CE20: =IF(CD20="",CB20,CD20) -> 0 | CF20: =IF(CB21="C",'Dados de Base'!$D$5*0.1,IF(CB21="E",5,IF(BZ20="",CE20,BZ20))) -> 6.3 | CH20: =IF(CT20="","",HYPERLINK(OFFSET(Biblioteca!$B$2,MATCH(CT20,Biblioteca!$A$3:$A$200,0),0),CT20)) -> Skipping Baixo | CK20: =Montagem!CN18 -> Seriado | CL20: =Montagem!CO18 -> 1 | CM20: =Montagem!CP18 -> 30 | CN20: =Montagem!CQ18 -> 30 | CO20: =Montagem!CR18 -> 0 | CP20: =Montagem!CS18 -> 1 | CR20: =Montagem!CH18 -> 3 | CS20: =Montagem!CT18 -> 0 | CT20: =Montagem!CI18 -> Skipping Baixo | CU20: =Montagem!CU18 | CV20: =IF(CU20="",CS20,CU20) -> 0 | CW20: =IF(CS21="C",'Dados de Base'!$D$5*0.1,IF(CS21="E",5,IF(CQ20="",CV20,CQ20))) -> 6.3 | CY20: =IF(DK20="","",HYPERLINK(OFFSET(Biblioteca!$B$2,MATCH(DK20,Biblioteca!$A$3:$A$200,0),0),DK20)) | DB20: =Montagem!DC18 | DC20: =Montagem!DD18 | DD20: =Montagem!DE18 | DE20: =Montagem!DF18 | DF20: =Montagem!DG18 | DG20: =Montagem!DH18 | DI20: =Montagem!CW18 -> 1 | DJ20: =Montagem!DI18 | DK20: =Montagem!CX18 | DL20: =Montagem!DJ18 | DM20: =IF(DL20="",DJ20,DL20) | DN20: =IF(DJ21="C",'Dados de Base'!$D$5*0.1,IF(DJ21="E",5,IF(DH20="",DM20,DH20))) | DP20: Monotonia | DQ20: =IF(DQ14=0,0,DQ13/DQ14) -> 0
A21: =IF(A20="","",IFS(L21="A",Montagem!$C$30,N21="T","Realizar a maior quantidade de repetições por "&F20&" segundos | ",N21="I",IF(M21="U","Manter a posição por "&F20&" segundos de um lado e trocar para o outro na sequência | ","Manter a posição por "&F20&" segundos | "),M21="A","Realizar alternadamente "&F20&" repetições cada lado | ",M21="U","Realizar "&F20&" repetições de um lado e trocar para o outro na sequência | ",L21="P",OFFSET(Biblioteca!$H$2,MATCH(M20,Biblioteca!$A$3:$A$200,0),0),TRUE,"")) | E21: =IF(A20="","",IFS(L21="H","Carga Sugerida: "&ROUNDUP(O20/2,0)&" kg de cada lado (Total: "&ROUNDUP(O20/2,0)*2&" kg)",L21="C","Este exercício usa o Peso Corporal como carga",L21="E","Este exercício usa a resistência da banda elástica como carga",L21="O","Carga Sugerida: "&INT(O20)&" kg",TRUE,"")) -> Este exercício usa o Peso Corporal como carga | K21: =K20 -> 3 | L21: =LEFT(O21) -> C | M21: =MID(O21,2,1) -> O | N21: =RIGHT(O21) -> R | O21: =IF(M20="","",OFFSET(Biblioteca!$I$2,MATCH(M20,Biblioteca!$A$3:$A$200,0),0)) -> COR | R21: =IF(R20="","",IFS(AC21="A",Montagem!$D$30,AE21="T","Realizar a maior quantidade de repetições por "&W20&" segundos | ",AE21="I",IF(AD21="U","Manter a posição por "&W20&" segundos de um lado e trocar para o outro na sequência | ","Manter a posição por "&W20&" segundos | "),AD21="A","Realizar alternadamente "&W20&" repetições cada lado | ",AD21="U","Realizar "&W20&" repetições de um lado e trocar para o outro na sequência | ",AC21="P",OFFSET(Biblioteca!$H$2,MATCH(AD20,Biblioteca!$A$3:$A$200,0),0),TRUE,"")) | V21: =IF(R20="","",IFS(AC21="H","Carga Sugerida: "&ROUNDUP(AF20/2,0)&" kg de cada lado (Total: "&ROUNDUP(AF20/2,0)*2&" kg)",AC21="C","Este exercício usa o Peso Corporal como carga",AC21="E","Este exercício usa a resistência da banda elástica como carga",AC21="O","Carga Sugerida: "&INT(AF20)&" kg",TRUE,"")) -> Este exercício usa o Peso Corporal como carga | AB21: =AB20 -> 3 | AC21: =LEFT(AF21) -> C | AD21: =MID(AF21,2,1) -> O | AE21: =RIGHT(AF21) -> R | AF21: =IF(AD20="","",OFFSET(Biblioteca!$I$2,MATCH(AD20,Biblioteca!$A$3:$A$200,0),0)) -> COR | AI21: =IF(AI20="","",IFS(AT21="A",Montagem!$E$30,AV21="T","Realizar a maior quantidade de repetições por "&AN20&" segundos | ",AV21="I",IF(AU21="U","Manter a posição por "&AN20&" segundos de um lado e trocar para o outro na sequência | ","Manter a posição por "&AN20&" segundos | "),AU21="A","Realizar alternadamente "&AN20&" repetições cada lado | ",AU21="U","Realizar "&AN20&" repetições de um lado e trocar para o outro na sequência | ",AT21="P",OFFSET(Biblioteca!$H$2,MATCH(AU20,Biblioteca!$A$3:$A$200,0),0),TRUE,"")) -> Manter a posição por 50 segundos | | AM21: =IF(AI20="","",IFS(AT21="H","Carga Sugerida: "&ROUNDUP(AW20/2,0)&" kg de cada lado (Total: "&ROUNDUP(AW20/2,0)*2&" kg)",AT21="C","Este exercício usa o Peso Corporal como carga",AT21="E","Este exercício usa a resistência da banda elástica como carga",AT21="O","Carga Sugerida: "&INT(AW20)&" kg",TRUE,"")) -> Este exercício usa o Peso Corporal como carga | AS21: =AS20 -> 3 | AT21: =LEFT(AW21) -> C | AU21: =MID(AW21,2,1) -> O | AV21: =RIGHT(AW21) -> I | AW21: =IF(AU20="","",OFFSET(Biblioteca!$I$2,MATCH(AU20,Biblioteca!$A$3:$A$200,0),0)) -> COI | AZ21: =IF(AZ20="","",IFS(BK21="A",Montagem!$F$30,BM21="T","Realizar a maior quantidade de repetições por "&BE20&" segundos | ",BM21="I",IF(BL21="U","Manter a posição por "&BE20&" segundos de um lado e trocar para o outro na sequência | ","Manter a posição por "&BE20&" segundos | "),BL21="A","Realizar alternadamente "&BE20&" repetições cada lado | ",BL21="U","Realizar "&BE20&" repetições de um lado e trocar para o outro na sequência | ",BK21="P",OFFSET(Biblioteca!$H$2,MATCH(BL20,Biblioteca!$A$3:$A$200,0),0),TRUE,"")) -> Realizar 10 repetições de um lado e trocar para o outro na sequência | | BD21: =IF(AZ20="","",IFS(BK21="H","Carga Sugerida: "&ROUNDUP(BN20/2,0)&" kg de cada lado (Total: "&ROUNDUP(BN20/2,0)*2&" kg)",BK21="C","Este exercício usa o Peso Corporal como carga",BK21="E","Este exercício usa a resistência da banda elástica como carga",BK21="O","Carga Sugerida: "&INT(BN20)&" kg",TRUE,"")) -> Este exercício usa o Peso Corporal como carga | BJ21: =BJ20 -> 3 | BK21: =LEFT(BN21) -> C | BL21: =MID(BN21,2,1) -> U | BM21: =RIGHT(BN21) -> R | BN21: =IF(BL20="","",OFFSET(Biblioteca!$I$2,MATCH(BL20,Biblioteca!$A$3:$A$200,0),0)) -> CUR | BQ21: =IF(BQ20="","",IFS(CB21="A",Montagem!$G$30,CD21="T","Realizar a maior quantidade de repetições por "&BV20&" segundos | ",CD21="I",IF(CC21="U","Manter a posição por "&BV20&" segundos de um lado e trocar para o outro na sequência | ","Manter a posição por "&BV20&" segundos | "),CC21="A","Realizar alternadamente "&BV20&" repetições cada lado | ",CC21="U","Realizar "&BV20&" repetições de um lado e trocar para o outro na sequência | ",CB21="P",OFFSET(Biblioteca!$H$2,MATCH(CC20,Biblioteca!$A$3:$A$200,0),0),TRUE,"")) -> Realizar 10 repetições de um lado e trocar para o outro na sequência | | BU21: =IF(BQ20="","",IFS(CB21="H","Carga Sugerida: "&ROUNDUP(CE20/2,0)&" kg de cada lado (Total: "&ROUNDUP(CE20/2,0)*2&" kg)",CB21="C","Este exercício usa o Peso Corporal como carga",CB21="E","Este exercício usa a resistência da banda elástica como carga",CB21="O","Carga Sugerida: "&INT(CE20)&" kg",TRUE,"")) -> Este exercício usa o Peso Corporal como carga | CA21: =CA20 -> 3 | CB21: =LEFT(CE21) -> C | CC21: =MID(CE21,2,1) -> U | CD21: =RIGHT(CE21) -> R | CE21: =IF(CC20="","",OFFSET(Biblioteca!$I$2,MATCH(CC20,Biblioteca!$A$3:$A$200,0),0)) -> CUR | CH21: =IF(CH20="","",IFS(CS21="A",Montagem!$H$30,CU21="T","Realizar a maior quantidade de repetições por "&CM20&" segundos | ",CU21="I",IF(CT21="U","Manter a posição por "&CM20&" segundos de um lado e trocar para o outro na sequência | ","Manter a posição por "&CM20&" segundos | "),CT21="A","Realizar alternadamente "&CM20&" repetições cada lado | ",CT21="U","Realizar "&CM20&" repetições de um lado e trocar para o outro na sequência | ",CS21="P",OFFSET(Biblioteca!$H$2,MATCH(CT20,Biblioteca!$A$3:$A$200,0),0),TRUE,"")) -> Realizar a maior quantidade de repetições por 30 segundos | | CL21: =IF(CH20="","",IFS(CS21="H","Carga Sugerida: "&ROUNDUP(CV20/2,0)&" kg de cada lado (Total: "&ROUNDUP(CV20/2,0)*2&" kg)",CS21="C","Este exercício usa o Peso Corporal como carga",CS21="E","Este exercício usa a resistência da banda elástica como carga",CS21="O","Carga Sugerida: "&INT(CV20)&" kg",TRUE,"")) -> Este exercício usa o Peso Corporal como carga | CR21: =CR20 -> 3 | CS21: =LEFT(CV21) -> C | CT21: =MID(CV21,2,1) -> O | CU21: =RIGHT(CV21) -> T | CV21: =IF(CT20="","",OFFSET(Biblioteca!$I$2,MATCH(CT20,Biblioteca!$A$3:$A$200,0),0)) -> COT | CY21: =IF(CY20="","",IFS(DJ21="A",Montagem!$I$30,DL21="T","Realizar a maior quantidade de repetições por "&DD20&" segundos | ",DL21="I",IF(DK21="U","Manter a posição por "&DD20&" segundos de um lado e trocar para o outro na sequência | ","Manter a posição por "&DD20&" segundos | "),DK21="A","Realizar alternadamente "&DD20&" repetições cada lado | ",DK21="U","Realizar "&DD20&" repetições de um lado e trocar para o outro na sequência | ",DJ21="P",OFFSET(Biblioteca!$H$2,MATCH(DK20,Biblioteca!$A$3:$A$200,0),0),TRUE,"")) | DC21: =IF(CY20="","",IFS(DJ21="H","Carga Sugerida: "&ROUNDUP(DM20/2,0)&" kg de cada lado (Total: "&ROUNDUP(DM20/2,0)*2&" kg)",DJ21="C","Este exercício usa o Peso Corporal como carga",DJ21="E","Este exercício usa a resistência da banda elástica como carga",DJ21="O","Carga Sugerida: "&INT(DM20)&" kg",TRUE,"")) | DI21: =DI20 -> 1 | DJ21: =LEFT(DM21) | DK21: =MID(DM21,2,1) | DL21: =RIGHT(DM21) | DM21: =IF(DK20="","",OFFSET(Biblioteca!$I$2,MATCH(DK20,Biblioteca!$A$3:$A$200,0),0)) | DP21: Strain | DQ21: =DQ20*DQ11 -> 0
A22: =IF(M22="","",HYPERLINK(OFFSET(Biblioteca!$B$2,MATCH(M22,Biblioteca!$A$3:$A$200,0),0),M22)) -> Mobilidade Quadril - Abdução/Adução | D22: =Montagem!Q19 -> Seriado | E22: =Montagem!R19 -> 2 | F22: =Montagem!S19 -> 10 | G22: =Montagem!T19 -> 10 | H22: =Montagem!U19 -> 1 | I22: =Montagem!V19 -> 1 | K22: =Montagem!K19 -> 4 | L22: =Montagem!W19 -> 0 | M22: =Montagem!L19 -> Mobilidade Quadril - Abdução/Adução | N22: =Montagem!X19 | O22: =IF(N22="",L22,N22) -> 0 | P22: =IF(L23="C",'Dados de Base'!$D$5*0.1,IF(L23="E",5,IF(J22="",O22,J22))) -> 6.3 | R22: =IF(AD22="","",HYPERLINK(OFFSET(Biblioteca!$B$2,MATCH(AD22,Biblioteca!$A$3:$A$200,0),0),AD22)) | U22: =Montagem!AF19 | V22: =Montagem!AG19 | W22: =Montagem!AH19 | X22: =Montagem!AI19 | Y22: =Montagem!AJ19 | Z22: =Montagem!AK19 | AB22: =Montagem!Z19 -> 4 | AC22: =Montagem!AL19 | AD22: =Montagem!AA19 | AE22: =Montagem!AM19 | AF22: =IF(AE22="",AC22,AE22) | AG22: =IF(AC23="C",'Dados de Base'!$D$5*0.1,IF(AC23="E",5,IF(AA22="",AF22,AA22))) | AI22: =IF(AU22="","",HYPERLINK(OFFSET(Biblioteca!$B$2,MATCH(AU22,Biblioteca!$A$3:$A$200,0),0),AU22)) | AL22: =Montagem!AU19 | AM22: =Montagem!AV19 | AN22: =Montagem!AW19 | AO22: =Montagem!AX19 | AP22: =Montagem!AY19 | AQ22: =Montagem!AZ19 | AS22: =Montagem!AO19 -> 4 | AT22: =Montagem!BA19 | AU22: =Montagem!AP19 | AV22: =Montagem!BB19 | AW22: =IF(AV22="",AT22,AV22) | AX22: =IF(AT23="C",'Dados de Base'!$D$5*0.1,IF(AT23="E",5,IF(AR22="",AW22,AR22))) | AZ22: =IF(BL22="","",HYPERLINK(OFFSET(Biblioteca!$B$2,MATCH(BL22,Biblioteca!$A$3:$A$200,0),0),BL22)) | BC22: =Montagem!BJ19 | BD22: =Montagem!BK19 | BE22: =Montagem!BL19 | BF22: =Montagem!BM19 | BG22: =Montagem!BN19 | BH22: =Montagem!BO19 | BJ22: =Montagem!BD19 -> 4 | BK22: =Montagem!BP19 | BL22: =Montagem!BE19 | BM22: =Montagem!BQ19 | BN22: =IF(BM22="",BK22,BM22) | BO22: =IF(BK23="C",'Dados de Base'!$D$5*0.1,IF(BK23="E",5,IF(BI22="",BN22,BI22))) | BQ22: =IF(CC22="","",HYPERLINK(OFFSET(Biblioteca!$B$2,MATCH(CC22,Biblioteca!$A$3:$A$200,0),0),CC22)) -> Alongamento Iliotibial III | BT22: =Montagem!BY19 -> Seriado | BU22: =Montagem!BZ19 -> 2 | BV22: =Montagem!CA19 -> 10 | BW22: =Montagem!CB19 -> 10 | BX22: =Montagem!CC19 -> 1 | BY22: =Montagem!CD19 -> 1 | CA22: =Montagem!BS19 -> 4 | CB22: =Montagem!CE19 -> 0 | CC22: =Montagem!BT19 -> Alongamento Iliotibial III | CD22: =Montagem!CF19 | CE22: =IF(CD22="",CB22,CD22) -> 0 | CF22: =IF(CB23="C",'Dados de Base'!$D$5*0.1,IF(CB23="E",5,IF(BZ22="",CE22,BZ22))) -> 6.3 | CH22: =IF(CT22="","",HYPERLINK(OFFSET(Biblioteca!$B$2,MATCH(CT22,Biblioteca!$A$3:$A$200,0),0),CT22)) -> Skipping Alto | CK22: =Montagem!CN19 -> Seriado | CL22: =Montagem!CO19 -> 1 | CM22: =Montagem!CP19 -> 30 | CN22: =Montagem!CQ19 -> 30 | CO22: =Montagem!CR19 -> 0 | CP22: =Montagem!CS19 -> 1 | CR22: =Montagem!CH19 -> 4 | CS22: =Montagem!CT19 -> 0 | CT22: =Montagem!CI19 -> Skipping Alto | CU22: =Montagem!CU19 | CV22: =IF(CU22="",CS22,CU22) -> 0 | CW22: =IF(CS23="C",'Dados de Base'!$D$5*0.1,IF(CS23="E",5,IF(CQ22="",CV22,CQ22))) -> 6.3 | CY22: =IF(DK22="","",HYPERLINK(OFFSET(Biblioteca!$B$2,MATCH(DK22,Biblioteca!$A$3:$A$200,0),0),DK22)) | DB22: =Montagem!DC19 | DC22: =Montagem!DD19 | DD22: =Montagem!DE19 | DE22: =Montagem!DF19 | DF22: =Montagem!DG19 | DG22: =Montagem!DH19 | DI22: =Montagem!CW19 -> 1 | DJ22: =Montagem!DI19 | DK22: =Montagem!CX19 | DL22: =Montagem!DJ19 | DM22: =IF(DL22="",DJ22,DL22) | DN22: =IF(DJ23="C",'Dados de Base'!$D$5*0.1,IF(DJ23="E",5,IF(DH22="",DM22,DH22))) | DP22: Notas do Treino | DQ22: =COUNTA(A75,R75,AI75,AZ75,BQ75,CH75,CY75) -> 0
A23: =IF(A22="","",IFS(L23="A",Montagem!$C$30,N23="T","Realizar a maior quantidade de repetições por "&F22&" segundos | ",N23="I",IF(M23="U","Manter a posição por "&F22&" segundos de um lado e trocar para o outro na sequência | ","Manter a posição por "&F22&" segundos | "),M23="A","Realizar alternadamente "&F22&" repetições cada lado | ",M23="U","Realizar "&F22&" repetições de um lado e trocar para o outro na sequência | ",L23="P",OFFSET(Biblioteca!$H$2,MATCH(M22,Biblioteca!$A$3:$A$200,0),0),TRUE,"")) -> Realizar 10 repetições de um lado e trocar para o outro na sequência | | E23: =IF(A22="","",IFS(L23="H","Carga Sugerida: "&ROUNDUP(O22/2,0)&" kg de cada lado (Total: "&ROUNDUP(O22/2,0)*2&" kg)",L23="C","Este exercício usa o Peso Corporal como carga",L23="E","Este exercício usa a resistência da banda elástica como carga",L23="O","Carga Sugerida: "&INT(O22)&" kg",TRUE,"")) -> Este exercício usa o Peso Corporal como carga | K23: =K22 -> 4 | L23: =LEFT(O23) -> C | M23: =MID(O23,2,1) -> U | N23: =RIGHT(O23) -> R | O23: =IF(M22="","",OFFSET(Biblioteca!$I$2,MATCH(M22,Biblioteca!$A$3:$A$200,0),0)) -> CUR | R23: =IF(R22="","",IFS(AC23="A",Montagem!$D$30,AE23="T","Realizar a maior quantidade de repetições por "&W22&" segundos | ",AE23="I",IF(AD23="U","Manter a posição por "&W22&" segundos de um lado e trocar para o outro na sequência | ","Manter a posição por "&W22&" segundos | "),AD23="A","Realizar alternadamente "&W22&" repetições cada lado | ",AD23="U","Realizar "&W22&" repetições de um lado e trocar para o outro na sequência | ",AC23="P",OFFSET(Biblioteca!$H$2,MATCH(AD22,Biblioteca!$A$3:$A$200,0),0),TRUE,"")) | V23: =IF(R22="","",IFS(AC23="H","Carga Sugerida: "&ROUNDUP(AF22/2,0)&" kg de cada lado (Total: "&ROUNDUP(AF22/2,0)*2&" kg)",AC23="C","Este exercício usa o Peso Corporal como carga",AC23="E","Este exercício usa a resistência da banda elástica como carga",AC23="O","Carga Sugerida: "&INT(AF22)&" kg",TRUE,"")) | AB23: =AB22 -> 4 | AC23: =LEFT(AF23) | AD23: =MID(AF23,2,1) | AE23: =RIGHT(AF23) | AF23: =IF(AD22="","",OFFSET(Biblioteca!$I$2,MATCH(AD22,Biblioteca!$A$3:$A$200,0),0)) | AI23: =IF(AI22="","",IFS(AT23="A",Montagem!$E$30,AV23="T","Realizar a maior quantidade de repetições por "&AN22&" segundos | ",AV23="I",IF(AU23="U","Manter a posição por "&AN22&" segundos de um lado e trocar para o outro na sequência | ","Manter a posição por "&AN22&" segundos | "),AU23="A","Realizar alternadamente "&AN22&" repetições cada lado | ",AU23="U","Realizar "&AN22&" repetições de um lado e trocar para o outro na sequência | ",AT23="P",OFFSET(Biblioteca!$H$2,MATCH(AU22,Biblioteca!$A$3:$A$200,0),0),TRUE,"")) | AM23: =IF(AI22="","",IFS(AT23="H","Carga Sugerida: "&ROUNDUP(AW22/2,0)&" kg de cada lado (Total: "&ROUNDUP(AW22/2,0)*2&" kg)",AT23="C","Este exercício usa o Peso Corporal como carga",AT23="E","Este exercício usa a resistência da banda elástica como carga",AT23="O","Carga Sugerida: "&INT(AW22)&" kg",TRUE,"")) | AS23: =AS22 -> 4 | AT23: =LEFT(AW23) | AU23: =MID(AW23,2,1) | AV23: =RIGHT(AW23) | AW23: =IF(AU22="","",OFFSET(Biblioteca!$I$2,MATCH(AU22,Biblioteca!$A$3:$A$200,0),0)) | AZ23: =IF(AZ22="","",IFS(BK23="A",Montagem!$F$30,BM23="T","Realizar a maior quantidade de repetições por "&BE22&" segundos | ",BM23="I",IF(BL23="U","Manter a posição por "&BE22&" segundos de um lado e trocar para o outro na sequência | ","Manter a posição por "&BE22&" segundos | "),BL23="A","Realizar alternadamente "&BE22&" repetições cada lado | ",BL23="U","Realizar "&BE22&" repetições de um lado e trocar para o outro na sequência | ",BK23="P",OFFSET(Biblioteca!$H$2,MATCH(BL22,Biblioteca!$A$3:$A$200,0),0),TRUE,"")) | BD23: =IF(AZ22="","",IFS(BK23="H","Carga Sugerida: "&ROUNDUP(BN22/2,0)&" kg de cada lado (Total: "&ROUNDUP(BN22/2,0)*2&" kg)",BK23="C","Este exercício usa o Peso Corporal como carga",BK23="E","Este exercício usa a resistência da banda elástica como carga",BK23="O","Carga Sugerida: "&INT(BN22)&" kg",TRUE,"")) | BJ23: =BJ22 -> 4 | BK23: =LEFT(BN23) | BL23: =MID(BN23,2,1) | BM23: =RIGHT(BN23) | BN23: =IF(BL22="","",OFFSET(Biblioteca!$I$2,MATCH(BL22,Biblioteca!$A$3:$A$200,0),0)) | BQ23: =IF(BQ22="","",IFS(CB23="A",Montagem!$G$30,CD23="T","Realizar a maior quantidade de repetições por "&BV22&" segundos | ",CD23="I",IF(CC23="U","Manter a posição por "&BV22&" segundos de um lado e trocar para o outro na sequência | ","Manter a posição por "&BV22&" segundos | "),CC23="A","Realizar alternadamente "&BV22&" repetições cada lado | ",CC23="U","Realizar "&BV22&" repetições de um lado e trocar para o outro na sequência | ",CB23="P",OFFSET(Biblioteca!$H$2,MATCH(CC22,Biblioteca!$A$3:$A$200,0),0),TRUE,"")) -> Realizar 10 repetições de um lado e trocar para o outro na sequência | | BU23: =IF(BQ22="","",IFS(CB23="H","Carga Sugerida: "&ROUNDUP(CE22/2,0)&" kg de cada lado (Total: "&ROUNDUP(CE22/2,0)*2&" kg)",CB23="C","Este exercício usa o Peso Corporal como carga",CB23="E","Este exercício usa a resistência da banda elástica como carga",CB23="O","Carga Sugerida: "&INT(CE22)&" kg",TRUE,"")) -> Este exercício usa o Peso Corporal como carga | CA23: =CA22 -> 4 | CB23: =LEFT(CE23) -> C | CC23: =MID(CE23,2,1) -> U | CD23: =RIGHT(CE23) -> R | CE23: =IF(CC22="","",OFFSET(Biblioteca!$I$2,MATCH(CC22,Biblioteca!$A$3:$A$200,0),0)) -> CUR | CH23: =IF(CH22="","",IFS(CS23="A",Montagem!$H$30,CU23="T","Realizar a maior quantidade de repetições por "&CM22&" segundos | ",CU23="I",IF(CT23="U","Manter a posição por "&CM22&" segundos de um lado e trocar para o outro na sequência | ","Manter a posição por "&CM22&" segundos | "),CT23="A","Realizar alternadamente "&CM22&" repetições cada lado | ",CT23="U","Realizar "&CM22&" repetições de um lado e trocar para o outro na sequência | ",CS23="P",OFFSET(Biblioteca!$H$2,MATCH(CT22,Biblioteca!$A$3:$A$200,0),0),TRUE,"")) -> Realizar a maior quantidade de repetições por 30 segundos | | CL23: =IF(CH22="","",IFS(CS23="H","Carga Sugerida: "&ROUNDUP(CV22/2,0)&" kg de cada lado (Total: "&ROUNDUP(CV22/2,0)*2&" kg)",CS23="C","Este exercício usa o Peso Corporal como carga",CS23="E","Este exercício usa a resistência da banda elástica como carga",CS23="O","Carga Sugerida: "&INT(CV22)&" kg",TRUE,"")) -> Este exercício usa o Peso Corporal como carga | CR23: =CR22 -> 4 | CS23: =LEFT(CV23) -> C | CT23: =MID(CV23,2,1) -> O | CU23: =RIGHT(CV23) -> T | CV23: =IF(CT22="","",OFFSET(Biblioteca!$I$2,MATCH(CT22,Biblioteca!$A$3:$A$200,0),0)) -> COT | CY23: =IF(CY22="","",IFS(DJ23="A",Montagem!$I$30,DL23="T","Realizar a maior quantidade de repetições por "&DD22&" segundos | ",DL23="I",IF(DK23="U","Manter a posição por "&DD22&" segundos de um lado e trocar para o outro na sequência | ","Manter a posição por "&DD22&" segundos | "),DK23="A","Realizar alternadamente "&DD22&" repetições cada lado | ",DK23="U","Realizar "&DD22&" repetições de um lado e trocar para o outro na sequência | ",DJ23="P",OFFSET(Biblioteca!$H$2,MATCH(DK22,Biblioteca!$A$3:$A$200,0),0),TRUE,"")) | DC23: =IF(CY22="","",IFS(DJ23="H","Carga Sugerida: "&ROUNDUP(DM22/2,0)&" kg de cada lado (Total: "&ROUNDUP(DM22/2,0)*2&" kg)",DJ23="C","Este exercício usa o Peso Corporal como carga",DJ23="E","Este exercício usa a resistência da banda elástica como carga",DJ23="O","Carga Sugerida: "&INT(DM22)&" kg",TRUE,"")) | DI23: =DI22 -> 1 | DJ23: =LEFT(DM23) | DK23: =MID(DM23,2,1) | DL23: =RIGHT(DM23) | DM23: =IF(DK22="","",OFFSET(Biblioteca!$I$2,MATCH(DK22,Biblioteca!$A$3:$A$200,0),0))
A24: SESSÃO | R24: SESSÃO | AI24: SESSÃO | AZ24: SESSÃO | BQ24: SESSÃO | CH24: SESSÃO | CY24: SESSÃO
A25: Exercício | D25: Sistema | E25: Séries | F25: Reps | G25: Int | H25: C | I25: E | J25: Carga | R25: Exercício | U25: Sistema | V25: Séries | W25: Reps | X25: Int | Y25: C | Z25: E | AA25: Carga | AI25: Exercício | AL25: Sistema | AM25: Séries | AN25: Reps | AO25: Int | AP25: C | AQ25: E | AR25: Carga | AZ25: Exercício | BC25: Sistema | BD25: Séries | BE25: Reps | BF25: Int | BG25: C | BH25: E | BI25: Carga | BQ25: Exercício | BT25: Sistema | BU25: Séries | BV25: Reps | BW25: Int | BX25: C | BY25: E | BZ25: Carga | CH25: Exercício | CK25: Sistema | CL25: Séries | CM25: Reps | CN25: Int | CO25: C | CP25: E | CQ25: Carga | CY25: Exercício | DB25: Sistema | DC25: Séries | DD25: Reps | DE25: Int | DF25: C | DG25: E | DH25: Carga
A26: =IF(M26="","",HYPERLINK(OFFSET(Biblioteca!$B$2,MATCH(M26,Biblioteca!$A$3:$A$200,0),0),M26)) -> Agachamento | D26: =Montagem!Q21 -> Bi-SET | E26: =Montagem!R21 -> 3 | F26: =Montagem!S21 -> 10 | G26: =Montagem!T21 | H26: =Montagem!U21 -> 1 | I26: =Montagem!V21 -> 2 | K26: =Montagem!K21 -> 1 | L26: =Montagem!W21 -> 90 | M26: =Montagem!L21 -> Agachamento | N26: =Montagem!X21 | O26: =IF(N26="",L26,N26) -> 90 | P26: =IF(L27="C",'Dados de Base'!$D$5*0.1,IF(L27="E",5,IF(J26="",O26,J26))) -> 90 | R26: =IF(AD26="","",HYPERLINK(OFFSET(Biblioteca!$B$2,MATCH(AD26,Biblioteca!$A$3:$A$200,0),0),AD26)) -> Stiff | U26: =Montagem!AF21 -> Bi-SET | V26: =Montagem!AG21 -> 3 | W26: =Montagem!AH21 -> 10 | X26: =Montagem!AI21 | Y26: =Montagem!AJ21 -> 1 | Z26: =Montagem!AK21 -> 2 | AB26: =Montagem!Z21 -> 1 | AC26: =Montagem!AL21 -> 100 | AD26: =Montagem!AA21 -> Stiff | AE26: =Montagem!AM21 | AF26: =IF(AE26="",AC26,AE26) -> 100 | AG26: =IF(AC27="C",'Dados de Base'!$D$5*0.1,IF(AC27="E",5,IF(AA26="",AF26,AA26))) -> 100 | AI26: =IF(AU26="","",HYPERLINK(OFFSET(Biblioteca!$B$2,MATCH(AU26,Biblioteca!$A$3:$A$200,0),0),AU26)) -> Pista | AL26: =Montagem!AU21 | AM26: =Montagem!AV21 | AN26: =Montagem!AW21 | AO26: =Montagem!AX21 | AP26: =Montagem!AY21 | AQ26: =Montagem!AZ21 | AS26: =Montagem!AO21 -> 1 | AT26: =Montagem!BA21 -> 0 | AU26: =Montagem!AP21 -> Pista | AV26: =Montagem!BB21 | AW26: =IF(AV26="",AT26,AV26) -> 0 | AX26: =IF(AT27="C",'Dados de Base'!$D$5*0.1,IF(AT27="E",5,IF(AR26="",AW26,AR26))) -> 0 | AZ26: =IF(BL26="","",HYPERLINK(OFFSET(Biblioteca!$B$2,MATCH(BL26,Biblioteca!$A$3:$A$200,0),0),BL26)) -> Corda | BC26: =Montagem!BJ21 | BD26: =Montagem!BK21 | BE26: =Montagem!BL21 | BF26: =Montagem!BM21 -> 60 | BG26: =Montagem!BN21 | BH26: =Montagem!BO21 | BJ26: =Montagem!BD21 -> 1 | BK26: =Montagem!BP21 -> 0 | BL26: =Montagem!BE21 -> Corda | BM26: =Montagem!BQ21 | BN26: =IF(BM26="",BK26,BM26) -> 0 | BO26: =IF(BK27="C",'Dados de Base'!$D$5*0.1,IF(BK27="E",5,IF(BI26="",BN26,BI26))) -> 0 | BQ26: =IF(CC26="","",HYPERLINK(OFFSET(Biblioteca!$B$2,MATCH(CC26,Biblioteca!$A$3:$A$200,0),0),CC26)) -> Agachamento Búlgaro | BT26: =Montagem!BY21 -> Bi-SET | BU26: =Montagem!BZ21 -> 3 | BV26: =Montagem!CA21 -> 10 | BW26: =Montagem!CB21 | BX26: =Montagem!CC21 -> 1 | BY26: =Montagem!CD21 -> 2 | CA26: =Montagem!BS21 -> 1 | CB26: =Montagem!CE21 -> 38 | CC26: =Montagem!BT21 -> Agachamento Búlgaro | CD26: =Montagem!CF21 | CE26: =IF(CD26="",CB26,CD26) -> 38 | CF26: =IF(CB27="C",'Dados de Base'!$D$5*0.1,IF(CB27="E",5,IF(BZ26="",CE26,BZ26))) -> 38 | CH26: =IF(CT26="","",HYPERLINK(OFFSET(Biblioteca!$B$2,MATCH(CT26,Biblioteca!$A$3:$A$200,0),0),CT26)) -> Pista | CK26: =Montagem!CN21 | CL26: =Montagem!CO21 | CM26: =Montagem!CP21 | CN26: =Montagem!CQ21 | CO26: =Montagem!CR21 | CP26: =Montagem!CS21 | CR26: =Montagem!CH21 -> 1 | CS26: =Montagem!CT21 -> 0 | CT26: =Montagem!CI21 -> Pista | CU26: =Montagem!CU21 | CV26: =IF(CU26="",CS26,CU26) -> 0 | CW26: =IF(CS27="C",'Dados de Base'!$D$5*0.1,IF(CS27="E",5,IF(CQ26="",CV26,CQ26))) -> 0 | CY26: =IF(DK26="","",HYPERLINK(OFFSET(Biblioteca!$B$2,MATCH(DK26,Biblioteca!$A$3:$A$200,0),0),DK26)) | DB26: =Montagem!DC21 | DC26: =Montagem!DD21 | DD26: =Montagem!DE21 | DE26: =Montagem!DF21 | DF26: =Montagem!DG21 | DG26: =Montagem!DH21 | DI26: =Montagem!CW21 -> 1 | DJ26: =Montagem!DI21 | DK26: =Montagem!CX21 | DL26: =Montagem!DJ21 | DM26: =IF(DL26="",DJ26,DL26) | DN26: =IF(DJ27="C",'Dados de Base'!$D$5*0.1,IF(DJ27="E",5,IF(DH26="",DM26,DH26)))
A27: =IF(A26="","",IFS(L27="A",Montagem!$C$30,N27="T","Realizar a maior quantidade de repetições por "&F26&" segundos | ",N27="I",IF(M27="U","Manter a posição por "&F26&" segundos de um lado e trocar para o outro na sequência | ","Manter a posição por "&F26&" segundos | "),M27="A","Realizar alternadamente "&F26&" repetições cada lado | ",M27="U","Realizar "&F26&" repetições de um lado e trocar para o outro na sequência | ",L27="P",OFFSET(Biblioteca!$H$2,MATCH(M26,Biblioteca!$A$3:$A$200,0),0),TRUE,"")&IF(N27="R","Ajuste a carga para que tenha "&$K$2&" repetições de reserva","")) -> Ajuste a carga para que tenha 0 a 2 repetições de reserva | E27: =IF(A26="","",IFS(L27="H","Carga Sugerida: "&ROUNDUP(O26/2,0)&" kg de cada lado (Total: "&ROUNDUP(O26/2,0)*2&" kg)",L27="C","Este exercício usa o Peso Corporal como carga",L27="E","Este exercício usa a resistência da banda elástica como carga",L27="O","Carga Sugerida: "&INT(O26)&" kg",TRUE,"")) -> Carga Sugerida: 90 kg | K27: =K26 -> 1 | L27: =LEFT(O27) -> O | M27: =MID(O27,2,1) -> O | N27: =RIGHT(O27) -> R | O27: =IF(M26="","",OFFSET(Biblioteca!$I$2,MATCH(M26,Biblioteca!$A$3:$A$200,0),0)) -> OOR | R27: =IF(R26="","",IFS(AC27="A",Montagem!$D$30,AE27="T","Realizar a maior quantidade de repetições por "&W26&" segundos | ",AE27="I",IF(AD27="U","Manter a posição por "&W26&" segundos de um lado e trocar para o outro na sequência | ","Manter a posição por "&W26&" segundos | "),AD27="A","Realizar alternadamente "&W26&" repetições cada lado | ",AD27="U","Realizar "&W26&" repetições de um lado e trocar para o outro na sequência | ",AC27="P",OFFSET(Biblioteca!$H$2,MATCH(AD26,Biblioteca!$A$3:$A$200,0),0),TRUE,"")&IF(AE27="R","Ajuste a carga para que tenha "&$K$2&" repetições de reserva","")) -> Ajuste a carga para que tenha 0 a 2 repetições de reserva | V27: =IF(R26="","",IFS(AC27="H","Carga Sugerida: "&ROUNDUP(AF26/2,0)&" kg de cada lado (Total: "&ROUNDUP(AF26/2,0)*2&" kg)",AC27="C","Este exercício usa o Peso Corporal como carga",AC27="E","Este exercício usa a resistência da banda elástica como carga",AC27="O","Carga Sugerida: "&INT(AF26)&" kg",TRUE,"")) -> Carga Sugerida: 100 kg | AB27: =AB26 -> 1 | AC27: =LEFT(AF27) -> O | AD27: =MID(AF27,2,1) -> O | AE27: =RIGHT(AF27) -> R | AF27: =IF(AD26="","",OFFSET(Biblioteca!$I$2,MATCH(AD26,Biblioteca!$A$3:$A$200,0),0)) -> OOR | AI27: =IF(AI26="","",IFS(AT27="A",Montagem!$E$30,AV27="T","Realizar a maior quantidade de repetições por "&AN26&" segundos | ",AV27="I",IF(AU27="U","Manter a posição por "&AN26&" segundos de um lado e trocar para o outro na sequência | ","Manter a posição por "&AN26&" segundos | "),AU27="A","Realizar alternadamente "&AN26&" repetições cada lado | ",AU27="U","Realizar "&AN26&" repetições de um lado e trocar para o outro na sequência | ",AT27="P",OFFSET(Biblioteca!$H$2,MATCH(AU26,Biblioteca!$A$3:$A$200,0),0),TRUE,"")&IF(AV27="R","Ajuste a carga para que tenha "&$K$2&" repetições de reserva","")) -> - Correr 15 km no menor tempo possível. | AM27: =IF(AI26="","",IFS(AT27="H","Carga Sugerida: "&ROUNDUP(AW26/2,0)&" kg de cada lado (Total: "&ROUNDUP(AW26/2,0)*2&" kg)",AT27="C","Este exercício usa o Peso Corporal como carga",AT27="E","Este exercício usa a resistência da banda elástica como carga",AT27="O","Carga Sugerida: "&INT(AW26)&" kg",TRUE,"")) | AS27: =AS26 -> 1 | AT27: =LEFT(AW27) -> A | AU27: =MID(AW27,2,1) -> - | AV27: =RIGHT(AW27) -> - | AW27: =IF(AU26="","",OFFSET(Biblioteca!$I$2,MATCH(AU26,Biblioteca!$A$3:$A$200,0),0)) -> A-- | AZ27: =IF(AZ26="","",IFS(BK27="A",Montagem!$F$30,BM27="T","Realizar a maior quantidade de repetições por "&BE26&" segundos | ",BM27="I",IF(BL27="U","Manter a posição por "&BE26&" segundos de um lado e trocar para o outro na sequência | ","Manter a posição por "&BE26&" segundos | "),BL27="A","Realizar alternadamente "&BE26&" repetições cada lado | ",BL27="U","Realizar "&BE26&" repetições de um lado e trocar para o outro na sequência | ",BK27="P",OFFSET(Biblioteca!$H$2,MATCH(BL26,Biblioteca!$A$3:$A$200,0),0),TRUE,"")&IF(BM27="R","Ajuste a carga para que tenha "&$K$2&" repetições de reserva","")) -> 1x (3m all out) | BD27: =IF(AZ26="","",IFS(BK27="H","Carga Sugerida: "&ROUNDUP(BN26/2,0)&" kg de cada lado (Total: "&ROUNDUP(BN26/2,0)*2&" kg)",BK27="C","Este exercício usa o Peso Corporal como carga",BK27="E","Este exercício usa a resistência da banda elástica como carga",BK27="O","Carga Sugerida: "&INT(BN26)&" kg",TRUE,"")) | BJ27: =BJ26 -> 1 | BK27: =LEFT(BN27) -> A | BL27: =MID(BN27,2,1) -> T | BM27: =RIGHT(BN27) -> T | BN27: =IF(BL26="","",OFFSET(Biblioteca!$I$2,MATCH(BL26,Biblioteca!$A$3:$A$200,0),0)) -> AT | BQ27: =IF(BQ26="","",IFS(CB27="A",Montagem!$G$30,CD27="T","Realizar a maior quantidade de repetições por "&BV26&" segundos | ",CD27="I",IF(CC27="U","Manter a posição por "&BV26&" segundos de um lado e trocar para o outro na sequência | ","Manter a posição por "&BV26&" segundos | "),CC27="A","Realizar alternadamente "&BV26&" repetições cada lado | ",CC27="U","Realizar "&BV26&" repetições de um lado e trocar para o outro na sequência | ",CB27="P",OFFSET(Biblioteca!$H$2,MATCH(CC26,Biblioteca!$A$3:$A$200,0),0),TRUE,"")&IF(CD27="R","Ajuste a carga para que tenha "&$K$2&" repetições de reserva","")) -> Realizar 10 repetições de um lado e trocar para o outro na sequência | Ajuste a carga para que tenha 0 a 2 repetições de reserva | BU27: =IF(BQ26="","",IFS(CB27="H","Carga Sugerida: "&ROUNDUP(CE26/2,0)&" kg de cada lado (Total: "&ROUNDUP(CE26/2,0)*2&" kg)",CB27="C","Este exercício usa o Peso Corporal como carga",CB27="E","Este exercício usa a resistência da banda elástica como carga",CB27="O","Carga Sugerida: "&INT(CE26)&" kg",TRUE,"")) -> Carga Sugerida: 19 kg de cada lado (Total: 38 kg) | CA27: =CA26 -> 1 | CB27: =LEFT(CE27) -> H | CC27: =MID(CE27,2,1) -> U | CD27: =RIGHT(CE27) -> R | CE27: =IF(CC26="","",OFFSET(Biblioteca!$I$2,MATCH(CC26,Biblioteca!$A$3:$A$200,0),0)) -> HUR | CH27: =IF(CH26="","",IFS(CS27="A",Montagem!$H$30,CU27="T","Realizar a maior quantidade de repetições por "&CM26&" segundos | ",CU27="I",IF(CT27="U","Manter a posição por "&CM26&" segundos de um lado e trocar para o outro na sequência | ","Manter a posição por "&CM26&" segundos | "),CT27="A","Realizar alternadamente "&CM26&" repetições cada lado | ",CT27="U","Realizar "&CM26&" repetições de um lado e trocar para o outro na sequência | ",CS27="P",OFFSET(Biblioteca!$H$2,MATCH(CT26,Biblioteca!$A$3:$A$200,0),0),TRUE,"")&IF(CU27="R","Ajuste a carga para que tenha "&$K$2&" repetições de reserva","")) -> ***TRAJETO*** - 2 km à 11,0km/h; - 25km à 12,5 km/h; - 2 km All out | CL27: =IF(CH26="","",IFS(CS27="H","Carga Sugerida: "&ROUNDUP(CV26/2,0)&" kg de cada lado (Total: "&ROUNDUP(CV26/2,0)*2&" kg)",CS27="C","Este exercício usa o Peso Corporal como carga",CS27="E","Este exercício usa a resistência da banda elástica como carga",CS27="O","Carga Sugerida: "&INT(CV26)&" kg",TRUE,"")) | CR27: =CR26 -> 1 | CS27: =LEFT(CV27) -> A | CT27: =MID(CV27,2,1) -> - | CU27: =RIGHT(CV27) -> - | CV27: =IF(CT26="","",OFFSET(Biblioteca!$I$2,MATCH(CT26,Biblioteca!$A$3:$A$200,0),0)) -> A-- | CY27: =IF(CY26="","",IFS(DJ27="A",Montagem!$I$30,DL27="T","Realizar a maior quantidade de repetições por "&DD26&" segundos | ",DL27="I",IF(DK27="U","Manter a posição por "&DD26&" segundos de um lado e trocar para o outro na sequência | ","Manter a posição por "&DD26&" segundos | "),DK27="A","Realizar alternadamente "&DD26&" repetições cada lado | ",DK27="U","Realizar "&DD26&" repetições de um lado e trocar para o outro na sequência | ",DJ27="P",OFFSET(Biblioteca!$H$2,MATCH(DK26,Biblioteca!$A$3:$A$200,0),0),TRUE,"")&IF(DL27="R","Ajuste a carga para que tenha "&$K$2&" repetições de reserva","")) | DC27: =IF(CY26="","",IFS(DJ27="H","Carga Sugerida: "&ROUNDUP(DM26/2,0)&" kg de cada lado (Total: "&ROUNDUP(DM26/2,0)*2&" kg)",DJ27="C","Este exercício usa o Peso Corporal como carga",DJ27="E","Este exercício usa a resistência da banda elástica como carga",DJ27="O","Carga Sugerida: "&INT(DM26)&" kg",TRUE,"")) | DI27: =DI26 -> 1 | DJ27: =LEFT(DM27) | DK27: =MID(DM27,2,1) | DL27: =RIGHT(DM27) | DM27: =IF(DK26="","",OFFSET(Biblioteca!$I$2,MATCH(DK26,Biblioteca!$A$3:$A$200,0),0))
A28: =IF(M28="","",HYPERLINK(OFFSET(Biblioteca!$B$2,MATCH(M28,Biblioteca!$A$3:$A$200,0),0),M28)) -> cão caçador com a bola | D28: =Montagem!Q22 -> Bi-SET | E28: =Montagem!R22 -> 3 | F28: =Montagem!S22 -> 10 | G28: =Montagem!T22 -> 45 | H28: =Montagem!U22 -> 1 | I28: =Montagem!V22 -> 2 | K28: =Montagem!K22 -> 1 | L28: =Montagem!W22 -> 0 | M28: =Montagem!L22 -> cão caçador com a bola | N28: =Montagem!X22 | O28: =IF(N28="",L28,N28) -> 0 | P28: =IF(L29="C",'Dados de Base'!$D$5*0.1,IF(L29="E",5,IF(J28="",O28,J28))) -> 6.3 | R28: =IF(AD28="","",HYPERLINK(OFFSET(Biblioteca!$B$2,MATCH(AD28,Biblioteca!$A$3:$A$200,0),0),AD28)) -> Prancha | U28: =Montagem!AF22 -> Bi-SET | V28: =Montagem!AG22 -> 3 | W28: =Montagem!AH22 -> 45 | X28: =Montagem!AI22 -> 45 | Y28: =Montagem!AJ22 -> 0 | Z28: =Montagem!AK22 -> 1 | AB28: =Montagem!Z22 -> 1 | AC28: =Montagem!AL22 -> 0 | AD28: =Montagem!AA22 -> Prancha | AE28: =Montagem!AM22 | AF28: =IF(AE28="",AC28,AE28) -> 0 | AG28: =IF(AC29="C",'Dados de Base'!$D$5*0.1,IF(AC29="E",5,IF(AA28="",AF28,AA28))) -> 6.3 | AI28: =IF(AU28="","",HYPERLINK(OFFSET(Biblioteca!$B$2,MATCH(AU28,Biblioteca!$A$3:$A$200,0),0),AU28)) | AL28: =Montagem!AU22 | AM28: =Montagem!AV22 | AN28: =Montagem!AW22 | AO28: =Montagem!AX22 | AP28: =Montagem!AY22 | AQ28: =Montagem!AZ22 | AS28: =Montagem!AO22 -> 1 | AT28: =Montagem!BA22 | AU28: =Montagem!AP22 | AV28: =Montagem!BB22 | AW28: =IF(AV28="",AT28,AV28) | AX28: =IF(AT29="C",'Dados de Base'!$D$5*0.1,IF(AT29="E",5,IF(AR28="",AW28,AR28))) | AZ28: =IF(BL28="","",HYPERLINK(OFFSET(Biblioteca!$B$2,MATCH(BL28,Biblioteca!$A$3:$A$200,0),0),BL28)) -> Levantamento Terra | BC28: =Montagem!BJ22 -> Bi-SET | BD28: =Montagem!BK22 -> 3 | BE28: =Montagem!BL22 -> 10 | BF28: =Montagem!BM22 | BG28: =Montagem!BN22 -> 1 | BH28: =Montagem!BO22 -> 2 | BJ28: =Montagem!BD22 -> 2 | BK28: =Montagem!BP22 -> 78 | BL28: =Montagem!BE22 -> Levantamento Terra | BM28: =Montagem!BQ22 | BN28: =IF(BM28="",BK28,BM28) -> 78 | BO28: =IF(BK29="C",'Dados de Base'!$D$5*0.1,IF(BK29="E",5,IF(BI28="",BN28,BI28))) -> 78 | BQ28: =IF(CC28="","",HYPERLINK(OFFSET(Biblioteca!$B$2,MATCH(CC28,Biblioteca!$A$3:$A$200,0),0),CC28)) -> Elevação Pélvica | BT28: =Montagem!BY22 -> Bi-SET | BU28: =Montagem!BZ22 -> 3 | BV28: =Montagem!CA22 -> 10 | BW28: =Montagem!CB22 -> 45 | BX28: =Montagem!CC22 -> 1 | BY28: =Montagem!CD22 -> 2 | CA28: =Montagem!BS22 -> 1 | CB28: =Montagem!CE22 -> 110.25 | CC28: =Montagem!BT22 -> Elevação Pélvica | CD28: =Montagem!CF22 | CE28: =IF(CD28="",CB28,CD28) -> 110.25 | CF28: =IF(CB29="C",'Dados de Base'!$D$5*0.1,IF(CB29="E",5,IF(BZ28="",CE28,BZ28))) -> 110.25 | CH28: =IF(CT28="","",HYPERLINK(OFFSET(Biblioteca!$B$2,MATCH(CT28,Biblioteca!$A$3:$A$200,0),0),CT28)) | CK28: =Montagem!CN22 | CL28: =Montagem!CO22 | CM28: =Montagem!CP22 | CN28: =Montagem!CQ22 | CO28: =Montagem!CR22 | CP28: =Montagem!CS22 | CR28: =Montagem!CH22 -> 1 | CS28: =Montagem!CT22 | CT28: =Montagem!CI22 | CU28: =Montagem!CU22 | CV28: =IF(CU28="",CS28,CU28) | CW28: =IF(CS29="C",'Dados de Base'!$D$5*0.1,IF(CS29="E",5,IF(CQ28="",CV28,CQ28))) | CY28: =IF(DK28="","",HYPERLINK(OFFSET(Biblioteca!$B$2,MATCH(DK28,Biblioteca!$A$3:$A$200,0),0),DK28)) | DB28: =Montagem!DC22 | DC28: =Montagem!DD22 | DD28: =Montagem!DE22 | DE28: =Montagem!DF22 | DF28: =Montagem!DG22 | DG28: =Montagem!DH22 | DI28: =Montagem!CW22 -> 1 | DJ28: =Montagem!DI22 | DK28: =Montagem!CX22 | DL28: =Montagem!DJ22 | DM28: =IF(DL28="",DJ28,DL28) | DN28: =IF(DJ29="C",'Dados de Base'!$D$5*0.1,IF(DJ29="E",5,IF(DH28="",DM28,DH28)))
A29: =IF(A28="","",IFS(L29="A",Montagem!$C$30,N29="T","Realizar a maior quantidade de repetições por "&F28&" segundos | ",N29="I",IF(M29="U","Manter a posição por "&F28&" segundos de um lado e trocar para o outro na sequência | ","Manter a posição por "&F28&" segundos | "),M29="A","Realizar alternadamente "&F28&" repetições cada lado | ",M29="U","Realizar "&F28&" repetições de um lado e trocar para o outro na sequência | ",L29="P",OFFSET(Biblioteca!$H$2,MATCH(M28,Biblioteca!$A$3:$A$200,0),0),TRUE,"")&IF(N29="R","Ajuste a carga para que tenha "&$K$2&" repetições de reserva","")) -> Realizar 10 repetições de um lado e trocar para o outro na sequência | Ajuste a carga para que tenha 0 a 2 repetições de reserva | E29: =IF(A28="","",IFS(L29="H","Carga Sugerida: "&ROUNDUP(O28/2,0)&" kg de cada lado (Total: "&ROUNDUP(O28/2,0)*2&" kg)",L29="C","Este exercício usa o Peso Corporal como carga",L29="E","Este exercício usa a resistência da banda elástica como carga",L29="O","Carga Sugerida: "&INT(O28)&" kg",TRUE,"")) -> Este exercício usa o Peso Corporal como carga | K29: =K28 -> 1 | L29: =LEFT(O29) -> C | M29: =MID(O29,2,1) -> U | N29: =RIGHT(O29) -> R | O29: =IF(M28="","",OFFSET(Biblioteca!$I$2,MATCH(M28,Biblioteca!$A$3:$A$200,0),0)) -> CUR | R29: =IF(R28="","",IFS(AC29="A",Montagem!$D$30,AE29="T","Realizar a maior quantidade de repetições por "&W28&" segundos | ",AE29="I",IF(AD29="U","Manter a posição por "&W28&" segundos de um lado e trocar para o outro na sequência | ","Manter a posição por "&W28&" segundos | "),AD29="A","Realizar alternadamente "&W28&" repetições cada lado | ",AD29="U","Realizar "&W28&" repetições de um lado e trocar para o outro na sequência | ",AC29="P",OFFSET(Biblioteca!$H$2,MATCH(AD28,Biblioteca!$A$3:$A$200,0),0),TRUE,"")&IF(AE29="R","Ajuste a carga para que tenha "&$K$2&" repetições de reserva","")) -> Manter a posição por 45 segundos | | V29: =IF(R28="","",IFS(AC29="H","Carga Sugerida: "&ROUNDUP(AF28/2,0)&" kg de cada lado (Total: "&ROUNDUP(AF28/2,0)*2&" kg)",AC29="C","Este exercício usa o Peso Corporal como carga",AC29="E","Este exercício usa a resistência da banda elástica como carga",AC29="O","Carga Sugerida: "&INT(AF28)&" kg",TRUE,"")) -> Este exercício usa o Peso Corporal como carga | AB29: =AB28 -> 1 | AC29: =LEFT(AF29) -> C | AD29: =MID(AF29,2,1) -> O | AE29: =RIGHT(AF29) -> I | AF29: =IF(AD28="","",OFFSET(Biblioteca!$I$2,MATCH(AD28,Biblioteca!$A$3:$A$200,0),0)) -> COI | AI29: =IF(AI28="","",IFS(AT29="A",Montagem!$E$30,AV29="T","Realizar a maior quantidade de repetições por "&AN28&" segundos | ",AV29="I",IF(AU29="U","Manter a posição por "&AN28&" segundos de um lado e trocar para o outro na sequência | ","Manter a posição por "&AN28&" segundos | "),AU29="A","Realizar alternadamente "&AN28&" repetições cada lado | ",AU29="U","Realizar "&AN28&" repetições de um lado e trocar para o outro na sequência | ",AT29="P",OFFSET(Biblioteca!$H$2,MATCH(AU28,Biblioteca!$A$3:$A$200,0),0),TRUE,"")&IF(AV29="R","Ajuste a carga para que tenha "&$K$2&" repetições de reserva","")) | AM29: =IF(AI28="","",IFS(AT29="H","Carga Sugerida: "&ROUNDUP(AW28/2,0)&" kg de cada lado (Total: "&ROUNDUP(AW28/2,0)*2&" kg)",AT29="C","Este exercício usa o Peso Corporal como carga",AT29="E","Este exercício usa a resistência da banda elástica como carga",AT29="O","Carga Sugerida: "&INT(AW28)&" kg",TRUE,"")) | AS29: =AS28 -> 1 | AT29: =LEFT(AW29) | AU29: =MID(AW29,2,1) | AV29: =RIGHT(AW29) | AW29: =IF(AU28="","",OFFSET(Biblioteca!$I$2,MATCH(AU28,Biblioteca!$A$3:$A$200,0),0)) | AZ29: =IF(AZ28="","",IFS(BK29="A",Montagem!$F$30,BM29="T","Realizar a maior quantidade de repetições por "&BE28&" segundos | ",BM29="I",IF(BL29="U","Manter a posição por "&BE28&" segundos de um lado e trocar para o outro na sequência | ","Manter a posição por "&BE28&" segundos | "),BL29="A","Realizar alternadamente "&BE28&" repetições cada lado | ",BL29="U","Realizar "&BE28&" repetições de um lado e trocar para o outro na sequência | ",BK29="P",OFFSET(Biblioteca!$H$2,MATCH(BL28,Biblioteca!$A$3:$A$200,0),0),TRUE,"")&IF(BM29="R","Ajuste a carga para que tenha "&$K$2&" repetições de reserva","")) -> Ajuste a carga para que tenha 0 a 2 repetições de reserva | BD29: =IF(AZ28="","",IFS(BK29="H","Carga Sugerida: "&ROUNDUP(BN28/2,0)&" kg de cada lado (Total: "&ROUNDUP(BN28/2,0)*2&" kg)",BK29="C","Este exercício usa o Peso Corporal como carga",BK29="E","Este exercício usa a resistência da banda elástica como carga",BK29="O","Carga Sugerida: "&INT(BN28)&" kg",TRUE,"")) -> Carga Sugerida: 78 kg | BJ29: =BJ28 -> 2 | BK29: =LEFT(BN29) -> O | BL29: =MID(BN29,2,1) -> O | BM29: =RIGHT(BN29) -> R | BN29: =IF(BL28="","",OFFSET(Biblioteca!$I$2,MATCH(BL28,Biblioteca!$A$3:$A$200,0),0)) -> OOR | BQ29: =IF(BQ28="","",IFS(CB29="A",Montagem!$G$30,CD29="T","Realizar a maior quantidade de repetições por "&BV28&" segundos | ",CD29="I",IF(CC29="U","Manter a posição por "&BV28&" segundos de um lado e trocar para o outro na sequência | ","Manter a posição por "&BV28&" segundos | "),CC29="A","Realizar alternadamente "&BV28&" repetições cada lado | ",CC29="U","Realizar "&BV28&" repetições de um lado e trocar para o outro na sequência | ",CB29="P",OFFSET(Biblioteca!$H$2,MATCH(CC28,Biblioteca!$A$3:$A$200,0),0),TRUE,"")&IF(CD29="R","Ajuste a carga para que tenha "&$K$2&" repetições de reserva","")) -> Ajuste a carga para que tenha 0 a 2 repetições de reserva | BU29: =IF(BQ28="","",IFS(CB29="H","Carga Sugerida: "&ROUNDUP(CE28/2,0)&" kg de cada lado (Total: "&ROUNDUP(CE28/2,0)*2&" kg)",CB29="C","Este exercício usa o Peso Corporal como carga",CB29="E","Este exercício usa a resistência da banda elástica como carga",CB29="O","Carga Sugerida: "&INT(CE28)&" kg",TRUE,"")) -> Carga Sugerida: 110 kg | CA29: =CA28 -> 1 | CB29: =LEFT(CE29) -> O | CC29: =MID(CE29,2,1) -> O | CD29: =RIGHT(CE29) -> R | CE29: =IF(CC28="","",OFFSET(Biblioteca!$I$2,MATCH(CC28,Biblioteca!$A$3:$A$200,0),0)) -> OOR | CH29: =IF(CH28="","",IFS(CS29="A",Montagem!$H$30,CU29="T","Realizar a maior quantidade de repetições por "&CM28&" segundos | ",CU29="I",IF(CT29="U","Manter a posição por "&CM28&" segundos de um lado e trocar para o outro na sequência | ","Manter a posição por "&CM28&" segundos | "),CT29="A","Realizar alternadamente "&CM28&" repetições cada lado | ",CT29="U","Realizar "&CM28&" repetições de um lado e trocar para o outro na sequência | ",CS29="P",OFFSET(Biblioteca!$H$2,MATCH(CT28,Biblioteca!$A$3:$A$200,0),0),TRUE,"")&IF(CU29="R","Ajuste a carga para que tenha "&$K$2&" repetições de reserva","")) | CL29: =IF(CH28="","",IFS(CS29="H","Carga Sugerida: "&ROUNDUP(CV28/2,0)&" kg de cada lado (Total: "&ROUNDUP(CV28/2,0)*2&" kg)",CS29="C","Este exercício usa o Peso Corporal como carga",CS29="E","Este exercício usa a resistência da banda elástica como carga",CS29="O","Carga Sugerida: "&INT(CV28)&" kg",TRUE,"")) | CR29: =CR28 -> 1 | CS29: =LEFT(CV29) | CT29: =MID(CV29,2,1) | CU29: =RIGHT(CV29) | CV29: =IF(CT28="","",OFFSET(Biblioteca!$I$2,MATCH(CT28,Biblioteca!$A$3:$A$200,0),0)) | CY29: =IF(CY28="","",IFS(DJ29="A",Montagem!$I$30,DL29="T","Realizar a maior quantidade de repetições por "&DD28&" segundos | ",DL29="I",IF(DK29="U","Manter a posição por "&DD28&" segundos de um lado e trocar para o outro na sequência | ","Manter a posição por "&DD28&" segundos | "),DK29="A","Realizar alternadamente "&DD28&" repetições cada lado | ",DK29="U","Realizar "&DD28&" repetições de um lado e trocar para o outro na sequência | ",DJ29="P",OFFSET(Biblioteca!$H$2,MATCH(DK28,Biblioteca!$A$3:$A$200,0),0),TRUE,"")&IF(DL29="R","Ajuste a carga para que tenha "&$K$2&" repetições de reserva","")) | DC29: =IF(CY28="","",IFS(DJ29="H","Carga Sugerida: "&ROUNDUP(DM28/2,0)&" kg de cada lado (Total: "&ROUNDUP(DM28/2,0)*2&" kg)",DJ29="C","Este exercício usa o Peso Corporal como carga",DJ29="E","Este exercício usa a resistência da banda elástica como carga",DJ29="O","Carga Sugerida: "&INT(DM28)&" kg",TRUE,"")) | DI29: =DI28 -> 1 | DJ29: =LEFT(DM29) | DK29: =MID(DM29,2,1) | DL29: =RIGHT(DM29) | DM29: =IF(DK28="","",OFFSET(Biblioteca!$I$2,MATCH(DK28,Biblioteca!$A$3:$A$200,0),0))
A30: =IF(M30="","",HYPERLINK(OFFSET(Biblioteca!$B$2,MATCH(M30,Biblioteca!$A$3:$A$200,0),0),M30)) -> Leg Press | D30: =Montagem!Q23 -> Bi-SET | E30: =Montagem!R23 -> 4 | F30: =Montagem!S23 -> 10 | G30: =Montagem!T23 | H30: =Montagem!U23 -> 1 | I30: =Montagem!V23 -> 2 | K30: =Montagem!K23 -> 2 | L30: =Montagem!W23 -> 170 | M30: =Montagem!L23 -> Leg Press | N30: =Montagem!X23 | O30: =IF(N30="",L30,N30) -> 170 | P30: =IF(L31="C",'Dados de Base'!$D$5*0.1,IF(L31="E",5,IF(J30="",O30,J30))) -> 170 | R30: =IF(AD30="","",HYPERLINK(OFFSET(Biblioteca!$B$2,MATCH(AD30,Biblioteca!$A$3:$A$200,0),0),AD30)) -> Cadeira Abdutora | U30: =Montagem!AF23 -> Bi-SET | V30: =Montagem!AG23 -> 3 | W30: =Montagem!AH23 -> 10 | X30: =Montagem!AI23 | Y30: =Montagem!AJ23 -> 1 | Z30: =Montagem!AK23 -> 2 | AB30: =Montagem!Z23 -> 2 | AC30: =Montagem!AL23 -> 5 | AD30: =Montagem!AA23 -> Cadeira Abdutora | AE30: =Montagem!AM23 | AF30: =IF(AE30="",AC30,AE30) -> 5 | AG30: =IF(AC31="C",'Dados de Base'!$D$5*0.1,IF(AC31="E",5,IF(AA30="",AF30,AA30))) -> 5 | AI30: =IF(AU30="","",HYPERLINK(OFFSET(Biblioteca!$B$2,MATCH(AU30,Biblioteca!$A$3:$A$200,0),0),AU30)) | AL30: =Montagem!AU23 | AM30: =Montagem!AV23 | AN30: =Montagem!AW23 | AO30: =Montagem!AX23 | AP30: =Montagem!AY23 | AQ30: =Montagem!AZ23 | AS30: =Montagem!AO23 -> 1 | AT30: =Montagem!BA23 | AU30: =Montagem!AP23 | AV30: =Montagem!BB23 | AW30: =IF(AV30="",AT30,AV30) | AX30: =IF(AT31="C",'Dados de Base'!$D$5*0.1,IF(AT31="E",5,IF(AR30="",AW30,AR30))) | AZ30: =IF(BL30="","",HYPERLINK(OFFSET(Biblioteca!$B$2,MATCH(BL30,Biblioteca!$A$3:$A$200,0),0),BL30)) -> Flexão Nórdica | BC30: =Montagem!BJ23 -> Bi-SET | BD30: =Montagem!BK23 -> 3 | BE30: =Montagem!BL23 -> 8 | BF30: =Montagem!BM23 -> 60 | BG30: =Montagem!BN23 -> 1 | BH30: =Montagem!BO23 -> 2 | BJ30: =Montagem!BD23 -> 2 | BK30: =Montagem!BP23 -> 0 | BL30: =Montagem!BE23 -> Flexão Nórdica | BM30: =Montagem!BQ23 | BN30: =IF(BM30="",BK30,BM30) -> 0 | BO30: =IF(BK31="C",'Dados de Base'!$D$5*0.1,IF(BK31="E",5,IF(BI30="",BN30,BI30))) -> 6.3 | BQ30: =IF(CC30="","",HYPERLINK(OFFSET(Biblioteca!$B$2,MATCH(CC30,Biblioteca!$A$3:$A$200,0),0),CC30)) -> Cadeira Extensora | BT30: =Montagem!BY23 -> Bi-SET | BU30: =Montagem!BZ23 -> 4 | BV30: =Montagem!CA23 -> 10 | BW30: =Montagem!CB23 | BX30: =Montagem!CC23 -> 1 | BY30: =Montagem!CD23 -> 2 | CA30: =Montagem!BS23 -> 2 | CB30: =Montagem!CE23 -> 15.435 | CC30: =Montagem!BT23 -> Cadeira Extensora | CD30: =Montagem!CF23 | CE30: =IF(CD30="",CB30,CD30) -> 15.435 | CF30: =IF(CB31="C",'Dados de Base'!$D$5*0.1,IF(CB31="E",5,IF(BZ30="",CE30,BZ30))) -> 15.435 | CH30: =IF(CT30="","",HYPERLINK(OFFSET(Biblioteca!$B$2,MATCH(CT30,Biblioteca!$A$3:$A$200,0),0),CT30)) | CK30: =Montagem!CN23 | CL30: =Montagem!CO23 | CM30: =Montagem!CP23 | CN30: =Montagem!CQ23 | CO30: =Montagem!CR23 | CP30: =Montagem!CS23 | CR30: =Montagem!CH23 -> 1 | CS30: =Montagem!CT23 | CT30: =Montagem!CI23 | CU30: =Montagem!CU23 | CV30: =IF(CU30="",CS30,CU30) | CW30: =IF(CS31="C",'Dados de Base'!$D$5*0.1,IF(CS31="E",5,IF(CQ30="",CV30,CQ30))) | CY30: =IF(DK30="","",HYPERLINK(OFFSET(Biblioteca!$B$2,MATCH(DK30,Biblioteca!$A$3:$A$200,0),0),DK30)) | DB30: =Montagem!DC23 | DC30: =Montagem!DD23 | DD30: =Montagem!DE23 | DE30: =Montagem!DF23 | DF30: =Montagem!DG23 | DG30: =Montagem!DH23 | DI30: =Montagem!CW23 -> 1 | DJ30: =Montagem!DI23 | DK30: =Montagem!CX23 | DL30: =Montagem!DJ23 | DM30: =IF(DL30="",DJ30,DL30) | DN30: =IF(DJ31="C",'Dados de Base'!$D$5*0.1,IF(DJ31="E",5,IF(DH30="",DM30,DH30)))
A31: =IF(A30="","",IFS(L31="A",Montagem!$C$30,N31="T","Realizar a maior quantidade de repetições por "&F30&" segundos | ",N31="I",IF(M31="U","Manter a posição por "&F30&" segundos de um lado e trocar para o outro na sequência | ","Manter a posição por "&F30&" segundos | "),M31="A","Realizar alternadamente "&F30&" repetições cada lado | ",M31="U","Realizar "&F30&" repetições de um lado e trocar para o outro na sequência | ",L31="P",OFFSET(Biblioteca!$H$2,MATCH(M30,Biblioteca!$A$3:$A$200,0),0),TRUE,"")&IF(N31="R","Ajuste a carga para que tenha "&$K$2&" repetições de reserva","")) -> Ajuste a carga para que tenha 0 a 2 repetições de reserva | E31: =IF(A30="","",IFS(L31="H","Carga Sugerida: "&ROUNDUP(O30/2,0)&" kg de cada lado (Total: "&ROUNDUP(O30/2,0)*2&" kg)",L31="C","Este exercício usa o Peso Corporal como carga",L31="E","Este exercício usa a resistência da banda elástica como carga",L31="O","Carga Sugerida: "&INT(O30)&" kg",TRUE,"")) -> Carga Sugerida: 170 kg | K31: =K30 -> 2 | L31: =LEFT(O31) -> O | M31: =MID(O31,2,1) -> O | N31: =RIGHT(O31) -> R | O31: =IF(M30="","",OFFSET(Biblioteca!$I$2,MATCH(M30,Biblioteca!$A$3:$A$200,0),0)) -> OOR | R31: =IF(R30="","",IFS(AC31="A",Montagem!$D$30,AE31="T","Realizar a maior quantidade de repetições por "&W30&" segundos | ",AE31="I",IF(AD31="U","Manter a posição por "&W30&" segundos de um lado e trocar para o outro na sequência | ","Manter a posição por "&W30&" segundos | "),AD31="A","Realizar alternadamente "&W30&" repetições cada lado | ",AD31="U","Realizar "&W30&" repetições de um lado e trocar para o outro na sequência | ",AC31="P",OFFSET(Biblioteca!$H$2,MATCH(AD30,Biblioteca!$A$3:$A$200,0),0),TRUE,"")&IF(AE31="R","Ajuste a carga para que tenha "&$K$2&" repetições de reserva","")) -> Ajuste a carga para que tenha 0 a 2 repetições de reserva | V31: =IF(R30="","",IFS(AC31="H","Carga Sugerida: "&ROUNDUP(AF30/2,0)&" kg de cada lado (Total: "&ROUNDUP(AF30/2,0)*2&" kg)",AC31="C","Este exercício usa o Peso Corporal como carga",AC31="E","Este exercício usa a resistência da banda elástica como carga",AC31="O","Carga Sugerida: "&INT(AF30)&" kg",TRUE,"")) -> Carga Sugerida: 5 kg | AB31: =AB30 -> 2 | AC31: =LEFT(AF31) -> O | AD31: =MID(AF31,2,1) -> O | AE31: =RIGHT(AF31) -> R | AF31: =IF(AD30="","",OFFSET(Biblioteca!$I$2,MATCH(AD30,Biblioteca!$A$3:$A$200,0),0)) -> OOR | AI31: =IF(AI30="","",IFS(AT31="A",Montagem!$E$30,AV31="T","Realizar a maior quantidade de repetições por "&AN30&" segundos | ",AV31="I",IF(AU31="U","Manter a posição por "&AN30&" segundos de um lado e trocar para o outro na sequência | ","Manter a posição por "&AN30&" segundos | "),AU31="A","Realizar alternadamente "&AN30&" repetições cada lado | ",AU31="U","Realizar "&AN30&" repetições de um lado e trocar para o outro na sequência | ",AT31="P",OFFSET(Biblioteca!$H$2,MATCH(AU30,Biblioteca!$A$3:$A$200,0),0),TRUE,"")&IF(AV31="R","Ajuste a carga para que tenha "&$K$2&" repetições de reserva","")) | AM31: =IF(AI30="","",IFS(AT31="H","Carga Sugerida: "&ROUNDUP(AW30/2,0)&" kg de cada lado (Total: "&ROUNDUP(AW30/2,0)*2&" kg)",AT31="C","Este exercício usa o Peso Corporal como carga",AT31="E","Este exercício usa a resistência da banda elástica como carga",AT31="O","Carga Sugerida: "&INT(AW30)&" kg",TRUE,"")) | AS31: =AS30 -> 1 | AT31: =LEFT(AW31) | AU31: =MID(AW31,2,1) | AV31: =RIGHT(AW31) | AW31: =IF(AU30="","",OFFSET(Biblioteca!$I$2,MATCH(AU30,Biblioteca!$A$3:$A$200,0),0)) | AZ31: =IF(AZ30="","",IFS(BK31="A",Montagem!$F$30,BM31="T","Realizar a maior quantidade de repetições por "&BE30&" segundos | ",BM31="I",IF(BL31="U","Manter a posição por "&BE30&" segundos de um lado e trocar para o outro na sequência | ","Manter a posição por "&BE30&" segundos | "),BL31="A","Realizar alternadamente "&BE30&" repetições cada lado | ",BL31="U","Realizar "&BE30&" repetições de um lado e trocar para o outro na sequência | ",BK31="P",OFFSET(Biblioteca!$H$2,MATCH(BL30,Biblioteca!$A$3:$A$200,0),0),TRUE,"")&IF(BM31="R","Ajuste a carga para que tenha "&$K$2&" repetições de reserva","")) -> Ajuste a carga para que tenha 0 a 2 repetições de reserva | BD31: =IF(AZ30="","",IFS(BK31="H","Carga Sugerida: "&ROUNDUP(BN30/2,0)&" kg de cada lado (Total: "&ROUNDUP(BN30/2,0)*2&" kg)",BK31="C","Este exercício usa o Peso Corporal como carga",BK31="E","Este exercício usa a resistência da banda elástica como carga",BK31="O","Carga Sugerida: "&INT(BN30)&" kg",TRUE,"")) -> Este exercício usa o Peso Corporal como carga | BJ31: =BJ30 -> 2 | BK31: =LEFT(BN31) -> C | BL31: =MID(BN31,2,1) -> O | BM31: =RIGHT(BN31) -> R | BN31: =IF(BL30="","",OFFSET(Biblioteca!$I$2,MATCH(BL30,Biblioteca!$A$3:$A$200,0),0)) -> COR | BQ31: =IF(BQ30="","",IFS(CB31="A",Montagem!$G$30,CD31="T","Realizar a maior quantidade de repetições por "&BV30&" segundos | ",CD31="I",IF(CC31="U","Manter a posição por "&BV30&" segundos de um lado e trocar para o outro na sequência | ","Manter a posição por "&BV30&" segundos | "),CC31="A","Realizar alternadamente "&BV30&" repetições cada lado | ",CC31="U","Realizar "&BV30&" repetições de um lado e trocar para o outro na sequência | ",CB31="P",OFFSET(Biblioteca!$H$2,MATCH(CC30,Biblioteca!$A$3:$A$200,0),0),TRUE,"")&IF(CD31="R","Ajuste a carga para que tenha "&$K$2&" repetições de reserva","")) -> Ajuste a carga para que tenha 0 a 2 repetições de reserva | BU31: =IF(BQ30="","",IFS(CB31="H","Carga Sugerida: "&ROUNDUP(CE30/2,0)&" kg de cada lado (Total: "&ROUNDUP(CE30/2,0)*2&" kg)",CB31="C","Este exercício usa o Peso Corporal como carga",CB31="E","Este exercício usa a resistência da banda elástica como carga",CB31="O","Carga Sugerida: "&INT(CE30)&" kg",TRUE,"")) -> Carga Sugerida: 15 kg | CA31: =CA30 -> 2 | CB31: =LEFT(CE31) -> O | CC31: =MID(CE31,2,1) -> O | CD31: =RIGHT(CE31) -> R | CE31: =IF(CC30="","",OFFSET(Biblioteca!$I$2,MATCH(CC30,Biblioteca!$A$3:$A$200,0),0)) -> OOR | CH31: =IF(CH30="","",IFS(CS31="A",Montagem!$H$30,CU31="T","Realizar a maior quantidade de repetições por "&CM30&" segundos | ",CU31="I",IF(CT31="U","Manter a posição por "&CM30&" segundos de um lado e trocar para o outro na sequência | ","Manter a posição por "&CM30&" segundos | "),CT31="A","Realizar alternadamente "&CM30&" repetições cada lado | ",CT31="U","Realizar "&CM30&" repetições de um lado e trocar para o outro na sequência | ",CS31="P",OFFSET(Biblioteca!$H$2,MATCH(CT30,Biblioteca!$A$3:$A$200,0),0),TRUE,"")&IF(CU31="R","Ajuste a carga para que tenha "&$K$2&" repetições de reserva","")) | CL31: =IF(CH30="","",IFS(CS31="H","Carga Sugerida: "&ROUNDUP(CV30/2,0)&" kg de cada lado (Total: "&ROUNDUP(CV30/2,0)*2&" kg)",CS31="C","Este exercício usa o Peso Corporal como carga",CS31="E","Este exercício usa a resistência da banda elástica como carga",CS31="O","Carga Sugerida: "&INT(CV30)&" kg",TRUE,"")) | CR31: =CR30 -> 1 | CS31: =LEFT(CV31) | CT31: =MID(CV31,2,1) | CU31: =RIGHT(CV31) | CV31: =IF(CT30="","",OFFSET(Biblioteca!$I$2,MATCH(CT30,Biblioteca!$A$3:$A$200,0),0)) | CY31: =IF(CY30="","",IFS(DJ31="A",Montagem!$I$30,DL31="T","Realizar a maior quantidade de repetições por "&DD30&" segundos | ",DL31="I",IF(DK31="U","Manter a posição por "&DD30&" segundos de um lado e trocar para o outro na sequência | ","Manter a posição por "&DD30&" segundos | "),DK31="A","Realizar alternadamente "&DD30&" repetições cada lado | ",DK31="U","Realizar "&DD30&" repetições de um lado e trocar para o outro na sequência | ",DJ31="P",OFFSET(Biblioteca!$H$2,MATCH(DK30,Biblioteca!$A$3:$A$200,0),0),TRUE,"")&IF(DL31="R","Ajuste a carga para que tenha "&$K$2&" repetições de reserva","")) | DC31: =IF(CY30="","",IFS(DJ31="H","Carga Sugerida: "&ROUNDUP(DM30/2,0)&" kg de cada lado (Total: "&ROUNDUP(DM30/2,0)*2&" kg)",DJ31="C","Este exercício usa o Peso Corporal como carga",DJ31="E","Este exercício usa a resistência da banda elástica como carga",DJ31="O","Carga Sugerida: "&INT(DM30)&" kg",TRUE,"")) | DI31: =DI30 -> 1 | DJ31: =LEFT(DM31) | DK31: =MID(DM31,2,1) | DL31: =RIGHT(DM31) | DM31: =IF(DK30="","",OFFSET(Biblioteca!$I$2,MATCH(DK30,Biblioteca!$A$3:$A$200,0),0))
A32: =IF(M32="","",HYPERLINK(OFFSET(Biblioteca!$B$2,MATCH(M32,Biblioteca!$A$3:$A$200,0),0),M32)) -> Panturrilha Leg Press | D32: =Montagem!Q24 -> Bi-SET | E32: =Montagem!R24 -> 4 | F32: =Montagem!S24 -> 10 | G32: =Montagem!T24 -> 45 | H32: =Montagem!U24 -> 1 | I32: =Montagem!V24 -> 2 | K32: =Montagem!K24 -> 2 | L32: =Montagem!W24 -> 220.5 | M32: =Montagem!L24 -> Panturrilha Leg Press | N32: =Montagem!X24 | O32: =IF(N32="",L32,N32) -> 220.5 | P32: =IF(L33="C",'Dados de Base'!$D$5*0.1,IF(L33="E",5,IF(J32="",O32,J32))) -> 220.5 | R32: =IF(AD32="","",HYPERLINK(OFFSET(Biblioteca!$B$2,MATCH(AD32,Biblioteca!$A$3:$A$200,0),0),AD32)) -> Extensão de quadril com elástico | U32: =Montagem!AF24 -> Bi-SET | V32: =Montagem!AG24 -> 3 | W32: =Montagem!AH24 -> 10 | X32: =Montagem!AI24 -> 45 | Y32: =Montagem!AJ24 -> 1 | Z32: =Montagem!AK24 -> 2 | AB32: =Montagem!Z24 -> 2 | AC32: =Montagem!AL24 -> 0 | AD32: =Montagem!AA24 -> Extensão de quadril com elástico | AE32: =Montagem!AM24 | AF32: =IF(AE32="",AC32,AE32) -> 0 | AG32: =IF(AC33="C",'Dados de Base'!$D$5*0.1,IF(AC33="E",5,IF(AA32="",AF32,AA32))) -> 5 | AI32: =IF(AU32="","",HYPERLINK(OFFSET(Biblioteca!$B$2,MATCH(AU32,Biblioteca!$A$3:$A$200,0),0),AU32)) | AL32: =Montagem!AU24 | AM32: =Montagem!AV24 | AN32: =Montagem!AW24 | AO32: =Montagem!AX24 | AP32: =Montagem!AY24 | AQ32: =Montagem!AZ24 | AS32: =Montagem!AO24 -> 1 | AT32: =Montagem!BA24 | AU32: =Montagem!AP24 | AV32: =Montagem!BB24 | AW32: =IF(AV32="",AT32,AV32) | AX32: =IF(AT33="C",'Dados de Base'!$D$5*0.1,IF(AT33="E",5,IF(AR32="",AW32,AR32))) | AZ32: =IF(BL32="","",HYPERLINK(OFFSET(Biblioteca!$B$2,MATCH(BL32,Biblioteca!$A$3:$A$200,0),0),BL32)) -> Cadeira Flexora | BC32: =Montagem!BJ24 -> Bi-SET | BD32: =Montagem!BK24 -> 2 | BE32: =Montagem!BL24 -> 10 | BF32: =Montagem!BM24 | BG32: =Montagem!BN24 -> 1 | BH32: =Montagem!BO24 -> 2 | BJ32: =Montagem!BD24 -> 3 | BK32: =Montagem!BP24 -> 15.435 | BL32: =Montagem!BE24 -> Cadeira Flexora | BM32: =Montagem!BQ24 | BN32: =IF(BM32="",BK32,BM32) -> 15.435 | BO32: =IF(BK33="C",'Dados de Base'!$D$5*0.1,IF(BK33="E",5,IF(BI32="",BN32,BI32))) -> 15.435 | BQ32: =IF(CC32="","",HYPERLINK(OFFSET(Biblioteca!$B$2,MATCH(CC32,Biblioteca!$A$3:$A$200,0),0),CC32)) -> Panturrilha Leg Press | BT32: =Montagem!BY24 -> Bi-SET | BU32: =Montagem!BZ24 -> 4 | BV32: =Montagem!CA24 -> 10 | BW32: =Montagem!CB24 -> 45 | BX32: =Montagem!CC24 -> 1 | BY32: =Montagem!CD24 -> 2 | CA32: =Montagem!BS24 -> 2 | CB32: =Montagem!CE24 -> 220.5 | CC32: =Montagem!BT24 -> Panturrilha Leg Press | CD32: =Montagem!CF24 | CE32: =IF(CD32="",CB32,CD32) -> 220.5 | CF32: =IF(CB33="C",'Dados de Base'!$D$5*0.1,IF(CB33="E",5,IF(BZ32="",CE32,BZ32))) -> 220.5 | CH32: =IF(CT32="","",HYPERLINK(OFFSET(Biblioteca!$B$2,MATCH(CT32,Biblioteca!$A$3:$A$200,0),0),CT32)) | CK32: =Montagem!CN24 | CL32: =Montagem!CO24 | CM32: =Montagem!CP24 | CN32: =Montagem!CQ24 | CO32: =Montagem!CR24 | CP32: =Montagem!CS24 | CR32: =Montagem!CH24 -> 1 | CS32: =Montagem!CT24 | CT32: =Montagem!CI24 | CU32: =Montagem!CU24 | CV32: =IF(CU32="",CS32,CU32) | CW32: =IF(CS33="C",'Dados de Base'!$D$5*0.1,IF(CS33="E",5,IF(CQ32="",CV32,CQ32))) | CY32: =IF(DK32="","",HYPERLINK(OFFSET(Biblioteca!$B$2,MATCH(DK32,Biblioteca!$A$3:$A$200,0),0),DK32)) | DB32: =Montagem!DC24 | DC32: =Montagem!DD24 | DD32: =Montagem!DE24 | DE32: =Montagem!DF24 | DF32: =Montagem!DG24 | DG32: =Montagem!DH24 | DI32: =Montagem!CW24 -> 1 | DJ32: =Montagem!DI24 | DK32: =Montagem!CX24 | DL32: =Montagem!DJ24 | DM32: =IF(DL32="",DJ32,DL32) | DN32: =IF(DJ33="C",'Dados de Base'!$D$5*0.1,IF(DJ33="E",5,IF(DH32="",DM32,DH32)))
A33: =IF(A32="","",IFS(L33="A",Montagem!$C$30,N33="T","Realizar a maior quantidade de repetições por "&F32&" segundos | ",N33="I",IF(M33="U","Manter a posição por "&F32&" segundos de um lado e trocar para o outro na sequência | ","Manter a posição por "&F32&" segundos | "),M33="A","Realizar alternadamente "&F32&" repetições cada lado | ",M33="U","Realizar "&F32&" repetições de um lado e trocar para o outro na sequência | ",L33="P",OFFSET(Biblioteca!$H$2,MATCH(M32,Biblioteca!$A$3:$A$200,0),0),TRUE,"")&IF(N33="R","Ajuste a carga para que tenha "&$K$2&" repetições de reserva","")) -> Ajuste a carga para que tenha 0 a 2 repetições de reserva | E33: =IF(A32="","",IFS(L33="H","Carga Sugerida: "&ROUNDUP(O32/2,0)&" kg de cada lado (Total: "&ROUNDUP(O32/2,0)*2&" kg)",L33="C","Este exercício usa o Peso Corporal como carga",L33="E","Este exercício usa a resistência da banda elástica como carga",L33="O","Carga Sugerida: "&INT(O32)&" kg",TRUE,"")) -> Carga Sugerida: 220 kg | K33: =K32 -> 2 | L33: =LEFT(O33) -> O | M33: =MID(O33,2,1) -> O | N33: =RIGHT(O33) -> R | O33: =IF(M32="","",OFFSET(Biblioteca!$I$2,MATCH(M32,Biblioteca!$A$3:$A$200,0),0)) -> OOR | R33: =IF(R32="","",IFS(AC33="A",Montagem!$D$30,AE33="T","Realizar a maior quantidade de repetições por "&W32&" segundos | ",AE33="I",IF(AD33="U","Manter a posição por "&W32&" segundos de um lado e trocar para o outro na sequência | ","Manter a posição por "&W32&" segundos | "),AD33="A","Realizar alternadamente "&W32&" repetições cada lado | ",AD33="U","Realizar "&W32&" repetições de um lado e trocar para o outro na sequência | ",AC33="P",OFFSET(Biblioteca!$H$2,MATCH(AD32,Biblioteca!$A$3:$A$200,0),0),TRUE,"")&IF(AE33="R","Ajuste a carga para que tenha "&$K$2&" repetições de reserva","")) -> Realizar 10 repetições de um lado e trocar para o outro na sequência | Ajuste a carga para que tenha 0 a 2 repetições de reserva | V33: =IF(R32="","",IFS(AC33="H","Carga Sugerida: "&ROUNDUP(AF32/2,0)&" kg de cada lado (Total: "&ROUNDUP(AF32/2,0)*2&" kg)",AC33="C","Este exercício usa o Peso Corporal como carga",AC33="E","Este exercício usa a resistência da banda elástica como carga",AC33="O","Carga Sugerida: "&INT(AF32)&" kg",TRUE,"")) -> Este exercício usa a resistência da banda elástica como carga | AB33: =AB32 -> 2 | AC33: =LEFT(AF33) -> E | AD33: =MID(AF33,2,1) -> U | AE33: =RIGHT(AF33) -> R | AF33: =IF(AD32="","",OFFSET(Biblioteca!$I$2,MATCH(AD32,Biblioteca!$A$3:$A$200,0),0)) -> EUR | AI33: =IF(AI32="","",IFS(AT33="A",Montagem!$E$30,AV33="T","Realizar a maior quantidade de repetições por "&AN32&" segundos | ",AV33="I",IF(AU33="U","Manter a posição por "&AN32&" segundos de um lado e trocar para o outro na sequência | ","Manter a posição por "&AN32&" segundos | "),AU33="A","Realizar alternadamente "&AN32&" repetições cada lado | ",AU33="U","Realizar "&AN32&" repetições de um lado e trocar para o outro na sequência | ",AT33="P",OFFSET(Biblioteca!$H$2,MATCH(AU32,Biblioteca!$A$3:$A$200,0),0),TRUE,"")&IF(AV33="R","Ajuste a carga para que tenha "&$K$2&" repetições de reserva","")) | AM33: =IF(AI32="","",IFS(AT33="H","Carga Sugerida: "&ROUNDUP(AW32/2,0)&" kg de cada lado (Total: "&ROUNDUP(AW32/2,0)*2&" kg)",AT33="C","Este exercício usa o Peso Corporal como carga",AT33="E","Este exercício usa a resistência da banda elástica como carga",AT33="O","Carga Sugerida: "&INT(AW32)&" kg",TRUE,"")) | AS33: =AS32 -> 1 | AT33: =LEFT(AW33) | AU33: =MID(AW33,2,1) | AV33: =RIGHT(AW33) | AW33: =IF(AU32="","",OFFSET(Biblioteca!$I$2,MATCH(AU32,Biblioteca!$A$3:$A$200,0),0)) | AZ33: =IF(AZ32="","",IFS(BK33="A",Montagem!$F$30,BM33="T","Realizar a maior quantidade de repetições por "&BE32&" segundos | ",BM33="I",IF(BL33="U","Manter a posição por "&BE32&" segundos de um lado e trocar para o outro na sequência | ","Manter a posição por "&BE32&" segundos | "),BL33="A","Realizar alternadamente "&BE32&" repetições cada lado | ",BL33="U","Realizar "&BE32&" repetições de um lado e trocar para o outro na sequência | ",BK33="P",OFFSET(Biblioteca!$H$2,MATCH(BL32,Biblioteca!$A$3:$A$200,0),0),TRUE,"")&IF(BM33="R","Ajuste a carga para que tenha "&$K$2&" repetições de reserva","")) -> Ajuste a carga para que tenha 0 a 2 repetições de reserva | BD33: =IF(AZ32="","",IFS(BK33="H","Carga Sugerida: "&ROUNDUP(BN32/2,0)&" kg de cada lado (Total: "&ROUNDUP(BN32/2,0)*2&" kg)",BK33="C","Este exercício usa o Peso Corporal como carga",BK33="E","Este exercício usa a resistência da banda elástica como carga",BK33="O","Carga Sugerida: "&INT(BN32)&" kg",TRUE,"")) -> Carga Sugerida: 15 kg | BJ33: =BJ32 -> 3 | BK33: =LEFT(BN33) -> O | BL33: =MID(BN33,2,1) -> O | BM33: =RIGHT(BN33) -> R | BN33: =IF(BL32="","",OFFSET(Biblioteca!$I$2,MATCH(BL32,Biblioteca!$A$3:$A$200,0),0)) -> OOR | BQ33: =IF(BQ32="","",IFS(CB33="A",Montagem!$G$30,CD33="T","Realizar a maior quantidade de repetições por "&BV32&" segundos | ",CD33="I",IF(CC33="U","Manter a posição por "&BV32&" segundos de um lado e trocar para o outro na sequência | ","Manter a posição por "&BV32&" segundos | "),CC33="A","Realizar alternadamente "&BV32&" repetições cada lado | ",CC33="U","Realizar "&BV32&" repetições de um lado e trocar para o outro na sequência | ",CB33="P",OFFSET(Biblioteca!$H$2,MATCH(CC32,Biblioteca!$A$3:$A$200,0),0),TRUE,"")&IF(CD33="R","Ajuste a carga para que tenha "&$K$2&" repetições de reserva","")) -> Ajuste a carga para que tenha 0 a 2 repetições de reserva | BU33: =IF(BQ32="","",IFS(CB33="H","Carga Sugerida: "&ROUNDUP(CE32/2,0)&" kg de cada lado (Total: "&ROUNDUP(CE32/2,0)*2&" kg)",CB33="C","Este exercício usa o Peso Corporal como carga",CB33="E","Este exercício usa a resistência da banda elástica como carga",CB33="O","Carga Sugerida: "&INT(CE32)&" kg",TRUE,"")) -> Carga Sugerida: 220 kg | CA33: =CA32 -> 2 | CB33: =LEFT(CE33) -> O | CC33: =MID(CE33,2,1) -> O | CD33: =RIGHT(CE33) -> R | CE33: =IF(CC32="","",OFFSET(Biblioteca!$I$2,MATCH(CC32,Biblioteca!$A$3:$A$200,0),0)) -> OOR | CH33: =IF(CH32="","",IFS(CS33="A",Montagem!$H$30,CU33="T","Realizar a maior quantidade de repetições por "&CM32&" segundos | ",CU33="I",IF(CT33="U","Manter a posição por "&CM32&" segundos de um lado e trocar para o outro na sequência | ","Manter a posição por "&CM32&" segundos | "),CT33="A","Realizar alternadamente "&CM32&" repetições cada lado | ",CT33="U","Realizar "&CM32&" repetições de um lado e trocar para o outro na sequência | ",CS33="P",OFFSET(Biblioteca!$H$2,MATCH(CT32,Biblioteca!$A$3:$A$200,0),0),TRUE,"")&IF(CU33="R","Ajuste a carga para que tenha "&$K$2&" repetições de reserva","")) | CL33: =IF(CH32="","",IFS(CS33="H","Carga Sugerida: "&ROUNDUP(CV32/2,0)&" kg de cada lado (Total: "&ROUNDUP(CV32/2,0)*2&" kg)",CS33="C","Este exercício usa o Peso Corporal como carga",CS33="E","Este exercício usa a resistência da banda elástica como carga",CS33="O","Carga Sugerida: "&INT(CV32)&" kg",TRUE,"")) | CR33: =CR32 -> 1 | CS33: =LEFT(CV33) | CT33: =MID(CV33,2,1) | CU33: =RIGHT(CV33) | CV33: =IF(CT32="","",OFFSET(Biblioteca!$I$2,MATCH(CT32,Biblioteca!$A$3:$A$200,0),0)) | CY33: =IF(CY32="","",IFS(DJ33="A",Montagem!$I$30,DL33="T","Realizar a maior quantidade de repetições por "&DD32&" segundos | ",DL33="I",IF(DK33="U","Manter a posição por "&DD32&" segundos de um lado e trocar para o outro na sequência | ","Manter a posição por "&DD32&" segundos | "),DK33="A","Realizar alternadamente "&DD32&" repetições cada lado | ",DK33="U","Realizar "&DD32&" repetições de um lado e trocar para o outro na sequência | ",DJ33="P",OFFSET(Biblioteca!$H$2,MATCH(DK32,Biblioteca!$A$3:$A$200,0),0),TRUE,"")&IF(DL33="R","Ajuste a carga para que tenha "&$K$2&" repetições de reserva","")) | DC33: =IF(CY32="","",IFS(DJ33="H","Carga Sugerida: "&ROUNDUP(DM32/2,0)&" kg de cada lado (Total: "&ROUNDUP(DM32/2,0)*2&" kg)",DJ33="C","Este exercício usa o Peso Corporal como carga",DJ33="E","Este exercício usa a resistência da banda elástica como carga",DJ33="O","Carga Sugerida: "&INT(DM32)&" kg",TRUE,"")) | DI33: =DI32 -> 1 | DJ33: =LEFT(DM33) | DK33: =MID(DM33,2,1) | DL33: =RIGHT(DM33) | DM33: =IF(DK32="","",OFFSET(Biblioteca!$I$2,MATCH(DK32,Biblioteca!$A$3:$A$200,0),0))
A34: =IF(M34="","",HYPERLINK(OFFSET(Biblioteca!$B$2,MATCH(M34,Biblioteca!$A$3:$A$200,0),0),M34)) -> Remada Frontal Máquina | D34: =Montagem!Q25 -> Bi-SET | E34: =Montagem!R25 -> 4 | F34: =Montagem!S25 -> 10 | G34: =Montagem!T25 | H34: =Montagem!U25 -> 1 | I34: =Montagem!V25 -> 2 | K34: =Montagem!K25 -> 3 | L34: =Montagem!W25 -> 68 | M34: =Montagem!L25 -> Remada Frontal Máquina | N34: =Montagem!X25 | O34: =IF(N34="",L34,N34) -> 68 | P34: =IF(L35="C",'Dados de Base'!$D$5*0.1,IF(L35="E",5,IF(J34="",O34,J34))) -> 68 | R34: =IF(AD34="","",HYPERLINK(OFFSET(Biblioteca!$B$2,MATCH(AD34,Biblioteca!$A$3:$A$200,0),0),AD34)) -> Supino | U34: =Montagem!AF25 -> Bi-SET | V34: =Montagem!AG25 -> 4 | W34: =Montagem!AH25 -> 10 | X34: =Montagem!AI25 | Y34: =Montagem!AJ25 -> 1 | Z34: =Montagem!AK25 -> 2 | AB34: =Montagem!Z25 -> 3 | AC34: =Montagem!AL25 -> 60 | AD34: =Montagem!AA25 -> Supino | AE34: =Montagem!AM25 | AF34: =IF(AE34="",AC34,AE34) -> 60 | AG34: =IF(AC35="C",'Dados de Base'!$D$5*0.1,IF(AC35="E",5,IF(AA34="",AF34,AA34))) -> 60 | AI34: =IF(AU34="","",HYPERLINK(OFFSET(Biblioteca!$B$2,MATCH(AU34,Biblioteca!$A$3:$A$200,0),0),AU34)) | AL34: =Montagem!AU25 | AM34: =Montagem!AV25 | AN34: =Montagem!AW25 | AO34: =Montagem!AX25 | AP34: =Montagem!AY25 | AQ34: =Montagem!AZ25 | AS34: =Montagem!AO25 -> 1 | AT34: =Montagem!BA25 | AU34: =Montagem!AP25 | AV34: =Montagem!BB25 | AW34: =IF(AV34="",AT34,AV34) | AX34: =IF(AT35="C",'Dados de Base'!$D$5*0.1,IF(AT35="E",5,IF(AR34="",AW34,AR34))) | AZ34: =IF(BL34="","",HYPERLINK(OFFSET(Biblioteca!$B$2,MATCH(BL34,Biblioteca!$A$3:$A$200,0),0),BL34)) -> Cadeira Extensora | BC34: =Montagem!BJ25 -> Bi-SET | BD34: =Montagem!BK25 -> 2 | BE34: =Montagem!BL25 -> 10 | BF34: =Montagem!BM25 -> 45 | BG34: =Montagem!BN25 -> 1 | BH34: =Montagem!BO25 -> 2 | BJ34: =Montagem!BD25 -> 3 | BK34: =Montagem!BP25 -> 15.435 | BL34: =Montagem!BE25 -> Cadeira Extensora | BM34: =Montagem!BQ25 | BN34: =IF(BM34="",BK34,BM34) -> 15.435 | BO34: =IF(BK35="C",'Dados de Base'!$D$5*0.1,IF(BK35="E",5,IF(BI34="",BN34,BI34))) -> 15.435 | BQ34: =IF(CC34="","",HYPERLINK(OFFSET(Biblioteca!$B$2,MATCH(CC34,Biblioteca!$A$3:$A$200,0),0),CC34)) -> Pulley com pegada Supinada | BT34: =Montagem!BY25 -> Bi-SET | BU34: =Montagem!BZ25 -> 4 | BV34: =Montagem!CA25 -> 10 | BW34: =Montagem!CB25 | BX34: =Montagem!CC25 -> 1 | BY34: =Montagem!CD25 -> 2 | CA34: =Montagem!BS25 -> 3 | CB34: =Montagem!CE25 -> 0 | CC34: =Montagem!BT25 -> Pulley com pegada Supinada | CD34: =Montagem!CF25 | CE34: =IF(CD34="",CB34,CD34) -> 0 | CF34: =IF(CB35="C",'Dados de Base'!$D$5*0.1,IF(CB35="E",5,IF(BZ34="",CE34,BZ34))) -> 0 | CH34: =IF(CT34="","",HYPERLINK(OFFSET(Biblioteca!$B$2,MATCH(CT34,Biblioteca!$A$3:$A$200,0),0),CT34)) | CK34: =Montagem!CN25 | CL34: =Montagem!CO25 | CM34: =Montagem!CP25 | CN34: =Montagem!CQ25 | CO34: =Montagem!CR25 | CP34: =Montagem!CS25 | CR34: =Montagem!CH25 -> 1 | CS34: =Montagem!CT25 | CT34: =Montagem!CI25 | CU34: =Montagem!CU25 | CV34: =IF(CU34="",CS34,CU34) | CW34: =IF(CS35="C",'Dados de Base'!$D$5*0.1,IF(CS35="E",5,IF(CQ34="",CV34,CQ34))) | CY34: =IF(DK34="","",HYPERLINK(OFFSET(Biblioteca!$B$2,MATCH(DK34,Biblioteca!$A$3:$A$200,0),0),DK34)) | DB34: =Montagem!DC25 | DC34: =Montagem!DD25 | DD34: =Montagem!DE25 | DE34: =Montagem!DF25 | DF34: =Montagem!DG25 | DG34: =Montagem!DH25 | DI34: =Montagem!CW25 -> 1 | DJ34: =Montagem!DI25 | DK34: =Montagem!CX25 | DL34: =Montagem!DJ25 | DM34: =IF(DL34="",DJ34,DL34) | DN34: =IF(DJ35="C",'Dados de Base'!$D$5*0.1,IF(DJ35="E",5,IF(DH34="",DM34,DH34)))
A35: =IF(A34="","",IFS(L35="A",Montagem!$C$30,N35="T","Realizar a maior quantidade de repetições por "&F34&" segundos | ",N35="I",IF(M35="U","Manter a posição por "&F34&" segundos de um lado e trocar para o outro na sequência | ","Manter a posição por "&F34&" segundos | "),M35="A","Realizar alternadamente "&F34&" repetições cada lado | ",M35="U","Realizar "&F34&" repetições de um lado e trocar para o outro na sequência | ",L35="P",OFFSET(Biblioteca!$H$2,MATCH(M34,Biblioteca!$A$3:$A$200,0),0),TRUE,"")&IF(N35="R","Ajuste a carga para que tenha "&$K$2&" repetições de reserva","")) -> Ajuste a carga para que tenha 0 a 2 repetições de reserva | E35: =IF(A34="","",IFS(L35="H","Carga Sugerida: "&ROUNDUP(O34/2,0)&" kg de cada lado (Total: "&ROUNDUP(O34/2,0)*2&" kg)",L35="C","Este exercício usa o Peso Corporal como carga",L35="E","Este exercício usa a resistência da banda elástica como carga",L35="O","Carga Sugerida: "&INT(O34)&" kg",TRUE,"")) -> Carga Sugerida: 68 kg | K35: =K34 -> 3 | L35: =LEFT(O35) -> O | M35: =MID(O35,2,1) -> O | N35: =RIGHT(O35) -> R | O35: =IF(M34="","",OFFSET(Biblioteca!$I$2,MATCH(M34,Biblioteca!$A$3:$A$200,0),0)) -> OOR | R35: =IF(R34="","",IFS(AC35="A",Montagem!$D$30,AE35="T","Realizar a maior quantidade de repetições por "&W34&" segundos | ",AE35="I",IF(AD35="U","Manter a posição por "&W34&" segundos de um lado e trocar para o outro na sequência | ","Manter a posição por "&W34&" segundos | "),AD35="A","Realizar alternadamente "&W34&" repetições cada lado | ",AD35="U","Realizar "&W34&" repetições de um lado e trocar para o outro na sequência | ",AC35="P",OFFSET(Biblioteca!$H$2,MATCH(AD34,Biblioteca!$A$3:$A$200,0),0),TRUE,"")&IF(AE35="R","Ajuste a carga para que tenha "&$K$2&" repetições de reserva","")) -> Ajuste a carga para que tenha 0 a 2 repetições de reserva | V35: =IF(R34="","",IFS(AC35="H","Carga Sugerida: "&ROUNDUP(AF34/2,0)&" kg de cada lado (Total: "&ROUNDUP(AF34/2,0)*2&" kg)",AC35="C","Este exercício usa o Peso Corporal como carga",AC35="E","Este exercício usa a resistência da banda elástica como carga",AC35="O","Carga Sugerida: "&INT(AF34)&" kg",TRUE,"")) -> Carga Sugerida: 60 kg | AB35: =AB34 -> 3 | AC35: =LEFT(AF35) -> O | AD35: =MID(AF35,2,1) -> O | AE35: =RIGHT(AF35) -> R | AF35: =IF(AD34="","",OFFSET(Biblioteca!$I$2,MATCH(AD34,Biblioteca!$A$3:$A$200,0),0)) -> OOR | AI35: =IF(AI34="","",IFS(AT35="A",Montagem!$E$30,AV35="T","Realizar a maior quantidade de repetições por "&AN34&" segundos | ",AV35="I",IF(AU35="U","Manter a posição por "&AN34&" segundos de um lado e trocar para o outro na sequência | ","Manter a posição por "&AN34&" segundos | "),AU35="A","Realizar alternadamente "&AN34&" repetições cada lado | ",AU35="U","Realizar "&AN34&" repetições de um lado e trocar para o outro na sequência | ",AT35="P",OFFSET(Biblioteca!$H$2,MATCH(AU34,Biblioteca!$A$3:$A$200,0),0),TRUE,"")&IF(AV35="R","Ajuste a carga para que tenha "&$K$2&" repetições de reserva","")) | AM35: =IF(AI34="","",IFS(AT35="H","Carga Sugerida: "&ROUNDUP(AW34/2,0)&" kg de cada lado (Total: "&ROUNDUP(AW34/2,0)*2&" kg)",AT35="C","Este exercício usa o Peso Corporal como carga",AT35="E","Este exercício usa a resistência da banda elástica como carga",AT35="O","Carga Sugerida: "&INT(AW34)&" kg",TRUE,"")) | AS35: =AS34 -> 1 | AT35: =LEFT(AW35) | AU35: =MID(AW35,2,1) | AV35: =RIGHT(AW35) | AW35: =IF(AU34="","",OFFSET(Biblioteca!$I$2,MATCH(AU34,Biblioteca!$A$3:$A$200,0),0)) | AZ35: =IF(AZ34="","",IFS(BK35="A",Montagem!$F$30,BM35="T","Realizar a maior quantidade de repetições por "&BE34&" segundos | ",BM35="I",IF(BL35="U","Manter a posição por "&BE34&" segundos de um lado e trocar para o outro na sequência | ","Manter a posição por "&BE34&" segundos | "),BL35="A","Realizar alternadamente "&BE34&" repetições cada lado | ",BL35="U","Realizar "&BE34&" repetições de um lado e trocar para o outro na sequência | ",BK35="P",OFFSET(Biblioteca!$H$2,MATCH(BL34,Biblioteca!$A$3:$A$200,0),0),TRUE,"")&IF(BM35="R","Ajuste a carga para que tenha "&$K$2&" repetições de reserva","")) -> Ajuste a carga para que tenha 0 a 2 repetições de reserva | BD35: =IF(AZ34="","",IFS(BK35="H","Carga Sugerida: "&ROUNDUP(BN34/2,0)&" kg de cada lado (Total: "&ROUNDUP(BN34/2,0)*2&" kg)",BK35="C","Este exercício usa o Peso Corporal como carga",BK35="E","Este exercício usa a resistência da banda elástica como carga",BK35="O","Carga Sugerida: "&INT(BN34)&" kg",TRUE,"")) -> Carga Sugerida: 15 kg | BJ35: =BJ34 -> 3 | BK35: =LEFT(BN35) -> O | BL35: =MID(BN35,2,1) -> O | BM35: =RIGHT(BN35) -> R | BN35: =IF(BL34="","",OFFSET(Biblioteca!$I$2,MATCH(BL34,Biblioteca!$A$3:$A$200,0),0)) -> OOR | BQ35: =IF(BQ34="","",IFS(CB35="A",Montagem!$G$30,CD35="T","Realizar a maior quantidade de repetições por "&BV34&" segundos | ",CD35="I",IF(CC35="U","Manter a posição por "&BV34&" segundos de um lado e trocar para o outro na sequência | ","Manter a posição por "&BV34&" segundos | "),CC35="A","Realizar alternadamente "&BV34&" repetições cada lado | ",CC35="U","Realizar "&BV34&" repetições de um lado e trocar para o outro na sequência | ",CB35="P",OFFSET(Biblioteca!$H$2,MATCH(CC34,Biblioteca!$A$3:$A$200,0),0),TRUE,"")&IF(CD35="R","Ajuste a carga para que tenha "&$K$2&" repetições de reserva","")) | BU35: =IF(BQ34="","",IFS(CB35="H","Carga Sugerida: "&ROUNDUP(CE34/2,0)&" kg de cada lado (Total: "&ROUNDUP(CE34/2,0)*2&" kg)",CB35="C","Este exercício usa o Peso Corporal como carga",CB35="E","Este exercício usa a resistência da banda elástica como carga",CB35="O","Carga Sugerida: "&INT(CE34)&" kg",TRUE,"")) | CA35: =CA34 -> 3 | CB35: =LEFT(CE35) | CC35: =MID(CE35,2,1) | CD35: =RIGHT(CE35) | CE35: =IF(CC34="","",OFFSET(Biblioteca!$I$2,MATCH(CC34,Biblioteca!$A$3:$A$200,0),0)) | CH35: =IF(CH34="","",IFS(CS35="A",Montagem!$H$30,CU35="T","Realizar a maior quantidade de repetições por "&CM34&" segundos | ",CU35="I",IF(CT35="U","Manter a posição por "&CM34&" segundos de um lado e trocar para o outro na sequência | ","Manter a posição por "&CM34&" segundos | "),CT35="A","Realizar alternadamente "&CM34&" repetições cada lado | ",CT35="U","Realizar "&CM34&" repetições de um lado e trocar para o outro na sequência | ",CS35="P",OFFSET(Biblioteca!$H$2,MATCH(CT34,Biblioteca!$A$3:$A$200,0),0),TRUE,"")&IF(CU35="R","Ajuste a carga para que tenha "&$K$2&" repetições de reserva","")) | CL35: =IF(CH34="","",IFS(CS35="H","Carga Sugerida: "&ROUNDUP(CV34/2,0)&" kg de cada lado (Total: "&ROUNDUP(CV34/2,0)*2&" kg)",CS35="C","Este exercício usa o Peso Corporal como carga",CS35="E","Este exercício usa a resistência da banda elástica como carga",CS35="O","Carga Sugerida: "&INT(CV34)&" kg",TRUE,"")) | CR35: =CR34 -> 1 | CS35: =LEFT(CV35) | CT35: =MID(CV35,2,1) | CU35: =RIGHT(CV35) | CV35: =IF(CT34="","",OFFSET(Biblioteca!$I$2,MATCH(CT34,Biblioteca!$A$3:$A$200,0),0)) | CY35: =IF(CY34="","",IFS(DJ35="A",Montagem!$I$30,DL35="T","Realizar a maior quantidade de repetições por "&DD34&" segundos | ",DL35="I",IF(DK35="U","Manter a posição por "&DD34&" segundos de um lado e trocar para o outro na sequência | ","Manter a posição por "&DD34&" segundos | "),DK35="A","Realizar alternadamente "&DD34&" repetições cada lado | ",DK35="U","Realizar "&DD34&" repetições de um lado e trocar para o outro na sequência | ",DJ35="P",OFFSET(Biblioteca!$H$2,MATCH(DK34,Biblioteca!$A$3:$A$200,0),0),TRUE,"")&IF(DL35="R","Ajuste a carga para que tenha "&$K$2&" repetições de reserva","")) | DC35: =IF(CY34="","",IFS(DJ35="H","Carga Sugerida: "&ROUNDUP(DM34/2,0)&" kg de cada lado (Total: "&ROUNDUP(DM34/2,0)*2&" kg)",DJ35="C","Este exercício usa o Peso Corporal como carga",DJ35="E","Este exercício usa a resistência da banda elástica como carga",DJ35="O","Carga Sugerida: "&INT(DM34)&" kg",TRUE,"")) | DI35: =DI34 -> 1 | DJ35: =LEFT(DM35) | DK35: =MID(DM35,2,1) | DL35: =RIGHT(DM35) | DM35: =IF(DK34="","",OFFSET(Biblioteca!$I$2,MATCH(DK34,Biblioteca!$A$3:$A$200,0),0))
A36: =IF(M36="","",HYPERLINK(OFFSET(Biblioteca!$B$2,MATCH(M36,Biblioteca!$A$3:$A$200,0),0),M36)) -> Abdominal Obliquo na polia média | D36: =Montagem!Q26 -> Bi-SET | E36: =Montagem!R26 -> 4 | F36: =Montagem!S26 -> 10 | G36: =Montagem!T26 -> 45 | H36: =Montagem!U26 -> 1 | I36: =Montagem!V26 -> 2 | K36: =Montagem!K26 -> 3 | L36: =Montagem!W26 -> 4 | M36: =Montagem!L26 -> Abdominal Obliquo na polia média | N36: =Montagem!X26 | O36: =IF(N36="",L36,N36) -> 4 | P36: =IF(L37="C",'Dados de Base'!$D$5*0.1,IF(L37="E",5,IF(J36="",O36,J36))) -> 4 | R36: =IF(AD36="","",HYPERLINK(OFFSET(Biblioteca!$B$2,MATCH(AD36,Biblioteca!$A$3:$A$200,0),0),AD36)) -> Banco Sóleo | U36: =Montagem!AF26 -> Bi-SET | V36: =Montagem!AG26 -> 4 | W36: =Montagem!AH26 -> 10 | X36: =Montagem!AI26 -> 45 | Y36: =Montagem!AJ26 -> 1 | Z36: =Montagem!AK26 -> 2 | AB36: =Montagem!Z26 -> 3 | AC36: =Montagem!AL26 -> 78 | AD36: =Montagem!AA26 -> Banco Sóleo | AE36: =Montagem!AM26 | AF36: =IF(AE36="",AC36,AE36) -> 78 | AG36: =IF(AC37="C",'Dados de Base'!$D$5*0.1,IF(AC37="E",5,IF(AA36="",AF36,AA36))) -> 78 | AI36: =IF(AU36="","",HYPERLINK(OFFSET(Biblioteca!$B$2,MATCH(AU36,Biblioteca!$A$3:$A$200,0),0),AU36)) | AL36: =Montagem!AU26 | AM36: =Montagem!AV26 | AN36: =Montagem!AW26 | AO36: =Montagem!AX26 | AP36: =Montagem!AY26 | AQ36: =Montagem!AZ26 | AS36: =Montagem!AO26 -> 1 | AT36: =Montagem!BA26 | AU36: =Montagem!AP26 | AV36: =Montagem!BB26 | AW36: =IF(AV36="",AT36,AV36) | AX36: =IF(AT37="C",'Dados de Base'!$D$5*0.1,IF(AT37="E",5,IF(AR36="",AW36,AR36))) | AZ36: =IF(BL36="","",HYPERLINK(OFFSET(Biblioteca!$B$2,MATCH(BL36,Biblioteca!$A$3:$A$200,0),0),BL36)) -> Fly no peck deck | BC36: =Montagem!BJ26 -> Bi-SET | BD36: =Montagem!BK26 -> 4 | BE36: =Montagem!BL26 -> 10 | BF36: =Montagem!BM26 | BG36: =Montagem!BN26 -> 1 | BH36: =Montagem!BO26 -> 2 | BJ36: =Montagem!BD26 -> 4 | BK36: =Montagem!BP26 -> 8 | BL36: =Montagem!BE26 -> Fly no peck deck | BM36: =Montagem!BQ26 | BN36: =IF(BM36="",BK36,BM36) -> 8 | BO36: =IF(BK37="C",'Dados de Base'!$D$5*0.1,IF(BK37="E",5,IF(BI36="",BN36,BI36))) -> 8 | BQ36: =IF(CC36="","",HYPERLINK(OFFSET(Biblioteca!$B$2,MATCH(CC36,Biblioteca!$A$3:$A$200,0),0),CC36)) -> Abdominal Obliquo na polia média | BT36: =Montagem!BY26 -> Bi-SET | BU36: =Montagem!BZ26 -> 4 | BV36: =Montagem!CA26 -> 10 | BW36: =Montagem!CB26 -> 45 | BX36: =Montagem!CC26 -> 1 | BY36: =Montagem!CD26 -> 2 | CA36: =Montagem!BS26 -> 3 | CB36: =Montagem!CE26 -> 4 | CC36: =Montagem!BT26 -> Abdominal Obliquo na polia média | CD36: =Montagem!CF26 | CE36: =IF(CD36="",CB36,CD36) -> 4 | CF36: =IF(CB37="C",'Dados de Base'!$D$5*0.1,IF(CB37="E",5,IF(BZ36="",CE36,BZ36))) -> 4 | CH36: =IF(CT36="","",HYPERLINK(OFFSET(Biblioteca!$B$2,MATCH(CT36,Biblioteca!$A$3:$A$200,0),0),CT36)) | CK36: =Montagem!CN26 | CL36: =Montagem!CO26 | CM36: =Montagem!CP26 | CN36: =Montagem!CQ26 | CO36: =Montagem!CR26 | CP36: =Montagem!CS26 | CR36: =Montagem!CH26 -> 1 | CS36: =Montagem!CT26 | CT36: =Montagem!CI26 | CU36: =Montagem!CU26 | CV36: =IF(CU36="",CS36,CU36) | CW36: =IF(CS37="C",'Dados de Base'!$D$5*0.1,IF(CS37="E",5,IF(CQ36="",CV36,CQ36))) | CY36: =IF(DK36="","",HYPERLINK(OFFSET(Biblioteca!$B$2,MATCH(DK36,Biblioteca!$A$3:$A$200,0),0),DK36)) | DB36: =Montagem!DC26 | DC36: =Montagem!DD26 | DD36: =Montagem!DE26 | DE36: =Montagem!DF26 | DF36: =Montagem!DG26 | DG36: =Montagem!DH26 | DI36: =Montagem!CW26 -> 1 | DJ36: =Montagem!DI26 | DK36: =Montagem!CX26 | DL36: =Montagem!DJ26 | DM36: =IF(DL36="",DJ36,DL36) | DN36: =IF(DJ37="C",'Dados de Base'!$D$5*0.1,IF(DJ37="E",5,IF(DH36="",DM36,DH36)))
A37: =IF(A36="","",IFS(L37="A",Montagem!$C$30,N37="T","Realizar a maior quantidade de repetições por "&F36&" segundos | ",N37="I",IF(M37="U","Manter a posição por "&F36&" segundos de um lado e trocar para o outro na sequência | ","Manter a posição por "&F36&" segundos | "),M37="A","Realizar alternadamente "&F36&" repetições cada lado | ",M37="U","Realizar "&F36&" repetições de um lado e trocar para o outro na sequência | ",L37="P",OFFSET(Biblioteca!$H$2,MATCH(M36,Biblioteca!$A$3:$A$200,0),0),TRUE,"")&IF(N37="R","Ajuste a carga para que tenha "&$K$2&" repetições de reserva","")) -> Ajuste a carga para que tenha 0 a 2 repetições de reserva | E37: =IF(A36="","",IFS(L37="H","Carga Sugerida: "&ROUNDUP(O36/2,0)&" kg de cada lado (Total: "&ROUNDUP(O36/2,0)*2&" kg)",L37="C","Este exercício usa o Peso Corporal como carga",L37="E","Este exercício usa a resistência da banda elástica como carga",L37="O","Carga Sugerida: "&INT(O36)&" kg",TRUE,"")) -> Carga Sugerida: 4 kg | K37: =K36 -> 3 | L37: =LEFT(O37) -> O | M37: =MID(O37,2,1) -> O | N37: =RIGHT(O37) -> R | O37: =IF(M36="","",OFFSET(Biblioteca!$I$2,MATCH(M36,Biblioteca!$A$3:$A$200,0),0)) -> OOR | R37: =IF(R36="","",IFS(AC37="A",Montagem!$D$30,AE37="T","Realizar a maior quantidade de repetições por "&W36&" segundos | ",AE37="I",IF(AD37="U","Manter a posição por "&W36&" segundos de um lado e trocar para o outro na sequência | ","Manter a posição por "&W36&" segundos | "),AD37="A","Realizar alternadamente "&W36&" repetições cada lado | ",AD37="U","Realizar "&W36&" repetições de um lado e trocar para o outro na sequência | ",AC37="P",OFFSET(Biblioteca!$H$2,MATCH(AD36,Biblioteca!$A$3:$A$200,0),0),TRUE,"")&IF(AE37="R","Ajuste a carga para que tenha "&$K$2&" repetições de reserva","")) -> Ajuste a carga para que tenha 0 a 2 repetições de reserva | V37: =IF(R36="","",IFS(AC37="H","Carga Sugerida: "&ROUNDUP(AF36/2,0)&" kg de cada lado (Total: "&ROUNDUP(AF36/2,0)*2&" kg)",AC37="C","Este exercício usa o Peso Corporal como carga",AC37="E","Este exercício usa a resistência da banda elástica como carga",AC37="O","Carga Sugerida: "&INT(AF36)&" kg",TRUE,"")) -> Carga Sugerida: 78 kg | AB37: =AB36 -> 3 | AC37: =LEFT(AF37) -> O | AD37: =MID(AF37,2,1) -> O | AE37: =RIGHT(AF37) -> R | AF37: =IF(AD36="","",OFFSET(Biblioteca!$I$2,MATCH(AD36,Biblioteca!$A$3:$A$200,0),0)) -> OOR | AI37: =IF(AI36="","",IFS(AT37="A",Montagem!$E$30,AV37="T","Realizar a maior quantidade de repetições por "&AN36&" segundos | ",AV37="I",IF(AU37="U","Manter a posição por "&AN36&" segundos de um lado e trocar para o outro na sequência | ","Manter a posição por "&AN36&" segundos | "),AU37="A","Realizar alternadamente "&AN36&" repetições cada lado | ",AU37="U","Realizar "&AN36&" repetições de um lado e trocar para o outro na sequência | ",AT37="P",OFFSET(Biblioteca!$H$2,MATCH(AU36,Biblioteca!$A$3:$A$200,0),0),TRUE,"")&IF(AV37="R","Ajuste a carga para que tenha "&$K$2&" repetições de reserva","")) | AM37: =IF(AI36="","",IFS(AT37="H","Carga Sugerida: "&ROUNDUP(AW36/2,0)&" kg de cada lado (Total: "&ROUNDUP(AW36/2,0)*2&" kg)",AT37="C","Este exercício usa o Peso Corporal como carga",AT37="E","Este exercício usa a resistência da banda elástica como carga",AT37="O","Carga Sugerida: "&INT(AW36)&" kg",TRUE,"")) | AS37: =AS36 -> 1 | AT37: =LEFT(AW37) | AU37: =MID(AW37,2,1) | AV37: =RIGHT(AW37) | AW37: =IF(AU36="","",OFFSET(Biblioteca!$I$2,MATCH(AU36,Biblioteca!$A$3:$A$200,0),0)) | AZ37: =IF(AZ36="","",IFS(BK37="A",Montagem!$F$30,BM37="T","Realizar a maior quantidade de repetições por "&BE36&" segundos | ",BM37="I",IF(BL37="U","Manter a posição por "&BE36&" segundos de um lado e trocar para o outro na sequência | ","Manter a posição por "&BE36&" segundos | "),BL37="A","Realizar alternadamente "&BE36&" repetições cada lado | ",BL37="U","Realizar "&BE36&" repetições de um lado e trocar para o outro na sequência | ",BK37="P",OFFSET(Biblioteca!$H$2,MATCH(BL36,Biblioteca!$A$3:$A$200,0),0),TRUE,"")&IF(BM37="R","Ajuste a carga para que tenha "&$K$2&" repetições de reserva","")) -> Ajuste a carga para que tenha 0 a 2 repetições de reserva | BD37: =IF(AZ36="","",IFS(BK37="H","Carga Sugerida: "&ROUNDUP(BN36/2,0)&" kg de cada lado (Total: "&ROUNDUP(BN36/2,0)*2&" kg)",BK37="C","Este exercício usa o Peso Corporal como carga",BK37="E","Este exercício usa a resistência da banda elástica como carga",BK37="O","Carga Sugerida: "&INT(BN36)&" kg",TRUE,"")) -> Carga Sugerida: 8 kg | BJ37: =BJ36 -> 4 | BK37: =LEFT(BN37) -> O | BL37: =MID(BN37,2,1) -> O | BM37: =RIGHT(BN37) -> R | BN37: =IF(BL36="","",OFFSET(Biblioteca!$I$2,MATCH(BL36,Biblioteca!$A$3:$A$200,0),0)) -> OOR | BQ37: =IF(BQ36="","",IFS(CB37="A",Montagem!$G$30,CD37="T","Realizar a maior quantidade de repetições por "&BV36&" segundos | ",CD37="I",IF(CC37="U","Manter a posição por "&BV36&" segundos de um lado e trocar para o outro na sequência | ","Manter a posição por "&BV36&" segundos | "),CC37="A","Realizar alternadamente "&BV36&" repetições cada lado | ",CC37="U","Realizar "&BV36&" repetições de um lado e trocar para o outro na sequência | ",CB37="P",OFFSET(Biblioteca!$H$2,MATCH(CC36,Biblioteca!$A$3:$A$200,0),0),TRUE,"")&IF(CD37="R","Ajuste a carga para que tenha "&$K$2&" repetições de reserva","")) -> Ajuste a carga para que tenha 0 a 2 repetições de reserva | BU37: =IF(BQ36="","",IFS(CB37="H","Carga Sugerida: "&ROUNDUP(CE36/2,0)&" kg de cada lado (Total: "&ROUNDUP(CE36/2,0)*2&" kg)",CB37="C","Este exercício usa o Peso Corporal como carga",CB37="E","Este exercício usa a resistência da banda elástica como carga",CB37="O","Carga Sugerida: "&INT(CE36)&" kg",TRUE,"")) -> Carga Sugerida: 4 kg | CA37: =CA36 -> 3 | CB37: =LEFT(CE37) -> O | CC37: =MID(CE37,2,1) -> O | CD37: =RIGHT(CE37) -> R | CE37: =IF(CC36="","",OFFSET(Biblioteca!$I$2,MATCH(CC36,Biblioteca!$A$3:$A$200,0),0)) -> OOR | CH37: =IF(CH36="","",IFS(CS37="A",Montagem!$H$30,CU37="T","Realizar a maior quantidade de repetições por "&CM36&" segundos | ",CU37="I",IF(CT37="U","Manter a posição por "&CM36&" segundos de um lado e trocar para o outro na sequência | ","Manter a posição por "&CM36&" segundos | "),CT37="A","Realizar alternadamente "&CM36&" repetições cada lado | ",CT37="U","Realizar "&CM36&" repetições de um lado e trocar para o outro na sequência | ",CS37="P",OFFSET(Biblioteca!$H$2,MATCH(CT36,Biblioteca!$A$3:$A$200,0),0),TRUE,"")&IF(CU37="R","Ajuste a carga para que tenha "&$K$2&" repetições de reserva","")) | CL37: =IF(CH36="","",IFS(CS37="H","Carga Sugerida: "&ROUNDUP(CV36/2,0)&" kg de cada lado (Total: "&ROUNDUP(CV36/2,0)*2&" kg)",CS37="C","Este exercício usa o Peso Corporal como carga",CS37="E","Este exercício usa a resistência da banda elástica como carga",CS37="O","Carga Sugerida: "&INT(CV36)&" kg",TRUE,"")) | CR37: =CR36 -> 1 | CS37: =LEFT(CV37) | CT37: =MID(CV37,2,1) | CU37: =RIGHT(CV37) | CV37: =IF(CT36="","",OFFSET(Biblioteca!$I$2,MATCH(CT36,Biblioteca!$A$3:$A$200,0),0)) | CY37: =IF(CY36="","",IFS(DJ37="A",Montagem!$I$30,DL37="T","Realizar a maior quantidade de repetições por "&DD36&" segundos | ",DL37="I",IF(DK37="U","Manter a posição por "&DD36&" segundos de um lado e trocar para o outro na sequência | ","Manter a posição por "&DD36&" segundos | "),DK37="A","Realizar alternadamente "&DD36&" repetições cada lado | ",DK37="U","Realizar "&DD36&" repetições de um lado e trocar para o outro na sequência | ",DJ37="P",OFFSET(Biblioteca!$H$2,MATCH(DK36,Biblioteca!$A$3:$A$200,0),0),TRUE,"")&IF(DL37="R","Ajuste a carga para que tenha "&$K$2&" repetições de reserva","")) | DC37: =IF(CY36="","",IFS(DJ37="H","Carga Sugerida: "&ROUNDUP(DM36/2,0)&" kg de cada lado (Total: "&ROUNDUP(DM36/2,0)*2&" kg)",DJ37="C","Este exercício usa o Peso Corporal como carga",DJ37="E","Este exercício usa a resistência da banda elástica como carga",DJ37="O","Carga Sugerida: "&INT(DM36)&" kg",TRUE,"")) | DI37: =DI36 -> 1 | DJ37: =LEFT(DM37) | DK37: =MID(DM37,2,1) | DL37: =RIGHT(DM37) | DM37: =IF(DK36="","",OFFSET(Biblioteca!$I$2,MATCH(DK36,Biblioteca!$A$3:$A$200,0),0))
A38: =IF(M38="","",HYPERLINK(OFFSET(Biblioteca!$B$2,MATCH(M38,Biblioteca!$A$3:$A$200,0),0),M38)) -> Pulley frente | D38: =Montagem!Q27 -> Bi-SET | E38: =Montagem!R27 -> 4 | F38: =Montagem!S27 -> 10 | G38: =Montagem!T27 | H38: =Montagem!U27 -> 1 | I38: =Montagem!V27 -> 2 | K38: =Montagem!K27 -> 4 | L38: =Montagem!W27 -> 9.426375 | M38: =Montagem!L27 -> Pulley frente | N38: =Montagem!X27 | O38: =IF(N38="",L38,N38) -> 9.426375 | P38: =IF(L39="C",'Dados de Base'!$D$5*0.1,IF(L39="E",5,IF(J38="",O38,J38))) -> 9.426375 | R38: =IF(AD38="","",HYPERLINK(OFFSET(Biblioteca!$B$2,MATCH(AD38,Biblioteca!$A$3:$A$200,0),0),AD38)) -> Supino Inclinado | U38: =Montagem!AF27 -> Bi-SET | V38: =Montagem!AG27 -> 4 | W38: =Montagem!AH27 -> 10 | X38: =Montagem!AI27 | Y38: =Montagem!AJ27 -> 1 | Z38: =Montagem!AK27 -> 2 | AB38: =Montagem!Z27 -> 4 | AC38: =Montagem!AL27 -> 50 | AD38: =Montagem!AA27 -> Supino Inclinado | AE38: =Montagem!AM27 | AF38: =IF(AE38="",AC38,AE38) -> 50 | AG38: =IF(AC39="C",'Dados de Base'!$D$5*0.1,IF(AC39="E",5,IF(AA38="",AF38,AA38))) -> 50 | AI38: =IF(AU38="","",HYPERLINK(OFFSET(Biblioteca!$B$2,MATCH(AU38,Biblioteca!$A$3:$A$200,0),0),AU38)) | AL38: =Montagem!AU27 | AM38: =Montagem!AV27 | AN38: =Montagem!AW27 | AO38: =Montagem!AX27 | AP38: =Montagem!AY27 | AQ38: =Montagem!AZ27 | AS38: =Montagem!AO27 -> 1 | AT38: =Montagem!BA27 | AU38: =Montagem!AP27 | AV38: =Montagem!BB27 | AW38: =IF(AV38="",AT38,AV38) | AX38: =IF(AT39="C",'Dados de Base'!$D$5*0.1,IF(AT39="E",5,IF(AR38="",AW38,AR38))) | AZ38: =IF(BL38="","",HYPERLINK(OFFSET(Biblioteca!$B$2,MATCH(BL38,Biblioteca!$A$3:$A$200,0),0),BL38)) -> Rosca Inclinado | BC38: =Montagem!BJ27 -> Bi-SET | BD38: =Montagem!BK27 -> 4 | BE38: =Montagem!BL27 -> 10 | BF38: =Montagem!BM27 -> 45 | BG38: =Montagem!BN27 -> 1 | BH38: =Montagem!BO27 -> 2 | BJ38: =Montagem!BD27 -> 4 | BK38: =Montagem!BP27 -> 13.3 | BL38: =Montagem!BE27 -> Rosca Inclinado | BM38: =Montagem!BQ27 | BN38: =IF(BM38="",BK38,BM38) -> 13.3 | BO38: =IF(BK39="C",'Dados de Base'!$D$5*0.1,IF(BK39="E",5,IF(BI38="",BN38,BI38))) -> 13.3 | BQ38: =IF(CC38="","",HYPERLINK(OFFSET(Biblioteca!$B$2,MATCH(CC38,Biblioteca!$A$3:$A$200,0),0),CC38)) -> Remada Alta na Polia | BT38: =Montagem!BY27 -> Bi-SET | BU38: =Montagem!BZ27 -> 4 | BV38: =Montagem!CA27 -> 10 | BW38: =Montagem!CB27 | BX38: =Montagem!CC27 -> 1 | BY38: =Montagem!CD27 -> 2 | CA38: =Montagem!BS27 -> 4 | CB38: =Montagem!CE27 -> 8.0819383 | CC38: =Montagem!BT27 -> Remada Alta na Polia | CD38: =Montagem!CF27 | CE38: =IF(CD38="",CB38,CD38) -> 8.0819383 | CF38: =IF(CB39="C",'Dados de Base'!$D$5*0.1,IF(CB39="E",5,IF(BZ38="",CE38,BZ38))) -> 8.0819383 | CH38: =IF(CT38="","",HYPERLINK(OFFSET(Biblioteca!$B$2,MATCH(CT38,Biblioteca!$A$3:$A$200,0),0),CT38)) | CK38: =Montagem!CN27 | CL38: =Montagem!CO27 | CM38: =Montagem!CP27 | CN38: =Montagem!CQ27 | CO38: =Montagem!CR27 | CP38: =Montagem!CS27 | CR38: =Montagem!CH27 -> 1 | CS38: =Montagem!CT27 | CT38: =Montagem!CI27 | CU38: =Montagem!CU27 | CV38: =IF(CU38="",CS38,CU38) | CW38: =IF(CS39="C",'Dados de Base'!$D$5*0.1,IF(CS39="E",5,IF(CQ38="",CV38,CQ38))) | CY38: =IF(DK38="","",HYPERLINK(OFFSET(Biblioteca!$B$2,MATCH(DK38,Biblioteca!$A$3:$A$200,0),0),DK38)) | DB38: =Montagem!DC27 | DC38: =Montagem!DD27 | DD38: =Montagem!DE27 | DE38: =Montagem!DF27 | DF38: =Montagem!DG27 | DG38: =Montagem!DH27 | DI38: =Montagem!CW27 -> 1 | DJ38: =Montagem!DI27 | DK38: =Montagem!CX27 | DL38: =Montagem!DJ27 | DM38: =IF(DL38="",DJ38,DL38) | DN38: =IF(DJ39="C",'Dados de Base'!$D$5*0.1,IF(DJ39="E",5,IF(DH38="",DM38,DH38)))
A39: =IF(A38="","",IFS(L39="A",Montagem!$C$30,N39="T","Realizar a maior quantidade de repetições por "&F38&" segundos | ",N39="I",IF(M39="U","Manter a posição por "&F38&" segundos de um lado e trocar para o outro na sequência | ","Manter a posição por "&F38&" segundos | "),M39="A","Realizar alternadamente "&F38&" repetições cada lado | ",M39="U","Realizar "&F38&" repetições de um lado e trocar para o outro na sequência | ",L39="P",OFFSET(Biblioteca!$H$2,MATCH(M38,Biblioteca!$A$3:$A$200,0),0),TRUE,"")&IF(N39="R","Ajuste a carga para que tenha "&$K$2&" repetições de reserva","")) -> Ajuste a carga para que tenha 0 a 2 repetições de reserva | E39: =IF(A38="","",IFS(L39="H","Carga Sugerida: "&ROUNDUP(O38/2,0)&" kg de cada lado (Total: "&ROUNDUP(O38/2,0)*2&" kg)",L39="C","Este exercício usa o Peso Corporal como carga",L39="E","Este exercício usa a resistência da banda elástica como carga",L39="O","Carga Sugerida: "&INT(O38)&" kg",TRUE,"")) -> Carga Sugerida: 9 kg | K39: =K38 -> 4 | L39: =LEFT(O39) -> O | M39: =MID(O39,2,1) -> O | N39: =RIGHT(O39) -> R | O39: =IF(M38="","",OFFSET(Biblioteca!$I$2,MATCH(M38,Biblioteca!$A$3:$A$200,0),0)) -> OOR | R39: =IF(R38="","",IFS(AC39="A",Montagem!$D$30,AE39="T","Realizar a maior quantidade de repetições por "&W38&" segundos | ",AE39="I",IF(AD39="U","Manter a posição por "&W38&" segundos de um lado e trocar para o outro na sequência | ","Manter a posição por "&W38&" segundos | "),AD39="A","Realizar alternadamente "&W38&" repetições cada lado | ",AD39="U","Realizar "&W38&" repetições de um lado e trocar para o outro na sequência | ",AC39="P",OFFSET(Biblioteca!$H$2,MATCH(AD38,Biblioteca!$A$3:$A$200,0),0),TRUE,"")&IF(AE39="R","Ajuste a carga para que tenha "&$K$2&" repetições de reserva","")) -> Ajuste a carga para que tenha 0 a 2 repetições de reserva | V39: =IF(R38="","",IFS(AC39="H","Carga Sugerida: "&ROUNDUP(AF38/2,0)&" kg de cada lado (Total: "&ROUNDUP(AF38/2,0)*2&" kg)",AC39="C","Este exercício usa o Peso Corporal como carga",AC39="E","Este exercício usa a resistência da banda elástica como carga",AC39="O","Carga Sugerida: "&INT(AF38)&" kg",TRUE,"")) -> Carga Sugerida: 50 kg | AB39: =AB38 -> 4 | AC39: =LEFT(AF39) -> O | AD39: =MID(AF39,2,1) -> O | AE39: =RIGHT(AF39) -> R | AF39: =IF(AD38="","",OFFSET(Biblioteca!$I$2,MATCH(AD38,Biblioteca!$A$3:$A$200,0),0)) -> OOR | AI39: =IF(AI38="","",IFS(AT39="A",Montagem!$E$30,AV39="T","Realizar a maior quantidade de repetições por "&AN38&" segundos | ",AV39="I",IF(AU39="U","Manter a posição por "&AN38&" segundos de um lado e trocar para o outro na sequência | ","Manter a posição por "&AN38&" segundos | "),AU39="A","Realizar alternadamente "&AN38&" repetições cada lado | ",AU39="U","Realizar "&AN38&" repetições de um lado e trocar para o outro na sequência | ",AT39="P",OFFSET(Biblioteca!$H$2,MATCH(AU38,Biblioteca!$A$3:$A$200,0),0),TRUE,"")&IF(AV39="R","Ajuste a carga para que tenha "&$K$2&" repetições de reserva","")) | AM39: =IF(AI38="","",IFS(AT39="H","Carga Sugerida: "&ROUNDUP(AW38/2,0)&" kg de cada lado (Total: "&ROUNDUP(AW38/2,0)*2&" kg)",AT39="C","Este exercício usa o Peso Corporal como carga",AT39="E","Este exercício usa a resistência da banda elástica como carga",AT39="O","Carga Sugerida: "&INT(AW38)&" kg",TRUE,"")) | AS39: =AS38 -> 1 | AT39: =LEFT(AW39) | AU39: =MID(AW39,2,1) | AV39: =RIGHT(AW39) | AW39: =IF(AU38="","",OFFSET(Biblioteca!$I$2,MATCH(AU38,Biblioteca!$A$3:$A$200,0),0)) | AZ39: =IF(AZ38="","",IFS(BK39="A",Montagem!$F$30,BM39="T","Realizar a maior quantidade de repetições por "&BE38&" segundos | ",BM39="I",IF(BL39="U","Manter a posição por "&BE38&" segundos de um lado e trocar para o outro na sequência | ","Manter a posição por "&BE38&" segundos | "),BL39="A","Realizar alternadamente "&BE38&" repetições cada lado | ",BL39="U","Realizar "&BE38&" repetições de um lado e trocar para o outro na sequência | ",BK39="P",OFFSET(Biblioteca!$H$2,MATCH(BL38,Biblioteca!$A$3:$A$200,0),0),TRUE,"")&IF(BM39="R","Ajuste a carga para que tenha "&$K$2&" repetições de reserva","")) -> Ajuste a carga para que tenha 0 a 2 repetições de reserva | BD39: =IF(AZ38="","",IFS(BK39="H","Carga Sugerida: "&ROUNDUP(BN38/2,0)&" kg de cada lado (Total: "&ROUNDUP(BN38/2,0)*2&" kg)",BK39="C","Este exercício usa o Peso Corporal como carga",BK39="E","Este exercício usa a resistência da banda elástica como carga",BK39="O","Carga Sugerida: "&INT(BN38)&" kg",TRUE,"")) -> Carga Sugerida: 7 kg de cada lado (Total: 14 kg) | BJ39: =BJ38 -> 4 | BK39: =LEFT(BN39) -> H | BL39: =MID(BN39,2,1) -> O | BM39: =RIGHT(BN39) -> R | BN39: =IF(BL38="","",OFFSET(Biblioteca!$I$2,MATCH(BL38,Biblioteca!$A$3:$A$200,0),0)) -> HOR | BQ39: =IF(BQ38="","",IFS(CB39="A",Montagem!$G$30,CD39="T","Realizar a maior quantidade de repetições por "&BV38&" segundos | ",CD39="I",IF(CC39="U","Manter a posição por "&BV38&" segundos de um lado e trocar para o outro na sequência | ","Manter a posição por "&BV38&" segundos | "),CC39="A","Realizar alternadamente "&BV38&" repetições cada lado | ",CC39="U","Realizar "&BV38&" repetições de um lado e trocar para o outro na sequência | ",CB39="P",OFFSET(Biblioteca!$H$2,MATCH(CC38,Biblioteca!$A$3:$A$200,0),0),TRUE,"")&IF(CD39="R","Ajuste a carga para que tenha "&$K$2&" repetições de reserva","")) -> Ajuste a carga para que tenha 0 a 2 repetições de reserva | BU39: =IF(BQ38="","",IFS(CB39="H","Carga Sugerida: "&ROUNDUP(CE38/2,0)&" kg de cada lado (Total: "&ROUNDUP(CE38/2,0)*2&" kg)",CB39="C","Este exercício usa o Peso Corporal como carga",CB39="E","Este exercício usa a resistência da banda elástica como carga",CB39="O","Carga Sugerida: "&INT(CE38)&" kg",TRUE,"")) -> Carga Sugerida: 8 kg | CA39: =CA38 -> 4 | CB39: =LEFT(CE39) -> O | CC39: =MID(CE39,2,1) -> O | CD39: =RIGHT(CE39) -> R | CE39: =IF(CC38="","",OFFSET(Biblioteca!$I$2,MATCH(CC38,Biblioteca!$A$3:$A$200,0),0)) -> OOR | CH39: =IF(CH38="","",IFS(CS39="A",Montagem!$H$30,CU39="T","Realizar a maior quantidade de repetições por "&CM38&" segundos | ",CU39="I",IF(CT39="U","Manter a posição por "&CM38&" segundos de um lado e trocar para o outro na sequência | ","Manter a posição por "&CM38&" segundos | "),CT39="A","Realizar alternadamente "&CM38&" repetições cada lado | ",CT39="U","Realizar "&CM38&" repetições de um lado e trocar para o outro na sequência | ",CS39="P",OFFSET(Biblioteca!$H$2,MATCH(CT38,Biblioteca!$A$3:$A$200,0),0),TRUE,"")&IF(CU39="R","Ajuste a carga para que tenha "&$K$2&" repetições de reserva","")) | CL39: =IF(CH38="","",IFS(CS39="H","Carga Sugerida: "&ROUNDUP(CV38/2,0)&" kg de cada lado (Total: "&ROUNDUP(CV38/2,0)*2&" kg)",CS39="C","Este exercício usa o Peso Corporal como carga",CS39="E","Este exercício usa a resistência da banda elástica como carga",CS39="O","Carga Sugerida: "&INT(CV38)&" kg",TRUE,"")) | CR39: =CR38 -> 1 | CS39: =LEFT(CV39) | CT39: =MID(CV39,2,1) | CU39: =RIGHT(CV39) | CV39: =IF(CT38="","",OFFSET(Biblioteca!$I$2,MATCH(CT38,Biblioteca!$A$3:$A$200,0),0)) | CY39: =IF(CY38="","",IFS(DJ39="A",Montagem!$I$30,DL39="T","Realizar a maior quantidade de repetições por "&DD38&" segundos | ",DL39="I",IF(DK39="U","Manter a posição por "&DD38&" segundos de um lado e trocar para o outro na sequência | ","Manter a posição por "&DD38&" segundos | "),DK39="A","Realizar alternadamente "&DD38&" repetições cada lado | ",DK39="U","Realizar "&DD38&" repetições de um lado e trocar para o outro na sequência | ",DJ39="P",OFFSET(Biblioteca!$H$2,MATCH(DK38,Biblioteca!$A$3:$A$200,0),0),TRUE,"")&IF(DL39="R","Ajuste a carga para que tenha "&$K$2&" repetições de reserva","")) | DC39: =IF(CY38="","",IFS(DJ39="H","Carga Sugerida: "&ROUNDUP(DM38/2,0)&" kg de cada lado (Total: "&ROUNDUP(DM38/2,0)*2&" kg)",DJ39="C","Este exercício usa o Peso Corporal como carga",DJ39="E","Este exercício usa a resistência da banda elástica como carga",DJ39="O","Carga Sugerida: "&INT(DM38)&" kg",TRUE,"")) | DI39: =DI38 -> 1 | DJ39: =LEFT(DM39) | DK39: =MID(DM39,2,1) | DL39: =RIGHT(DM39) | DM39: =IF(DK38="","",OFFSET(Biblioteca!$I$2,MATCH(DK38,Biblioteca!$A$3:$A$200,0),0))
A40: =IF(M40="","",HYPERLINK(OFFSET(Biblioteca!$B$2,MATCH(M40,Biblioteca!$A$3:$A$200,0),0),M40)) -> Abdominal Canoa | D40: =Montagem!Q28 -> Bi-SET | E40: =Montagem!R28 -> 4 | F40: =Montagem!S28 -> 10 | G40: =Montagem!T28 -> 45 | H40: =Montagem!U28 -> 1 | I40: =Montagem!V28 -> 2 | K40: =Montagem!K28 -> 4 | L40: =Montagem!W28 -> 0 | M40: =Montagem!L28 -> Abdominal Canoa | N40: =Montagem!X28 | O40: =IF(N40="",L40,N40) -> 0 | P40: =IF(L41="C",'Dados de Base'!$D$5*0.1,IF(L41="E",5,IF(J40="",O40,J40))) -> 6.3 | R40: =IF(AD40="","",HYPERLINK(OFFSET(Biblioteca!$B$2,MATCH(AD40,Biblioteca!$A$3:$A$200,0),0),AD40)) -> Abdominal roda | U40: =Montagem!AF28 -> Bi-SET | V40: =Montagem!AG28 -> 4 | W40: =Montagem!AH28 -> 10 | X40: =Montagem!AI28 -> 45 | Y40: =Montagem!AJ28 -> 1 | Z40: =Montagem!AK28 -> 2 | AB40: =Montagem!Z28 -> 4 | AC40: =Montagem!AL28 -> 0 | AD40: =Montagem!AA28 -> Abdominal roda | AE40: =Montagem!AM28 | AF40: =IF(AE40="",AC40,AE40) -> 0 | AG40: =IF(AC41="C",'Dados de Base'!$D$5*0.1,IF(AC41="E",5,IF(AA40="",AF40,AA40))) -> 6.3 | AI40: =IF(AU40="","",HYPERLINK(OFFSET(Biblioteca!$B$2,MATCH(AU40,Biblioteca!$A$3:$A$200,0),0),AU40)) | AL40: =Montagem!AU28 | AM40: =Montagem!AV28 | AN40: =Montagem!AW28 | AO40: =Montagem!AX28 | AP40: =Montagem!AY28 | AQ40: =Montagem!AZ28 | AS40: =Montagem!AO28 -> 1 | AT40: =Montagem!BA28 | AU40: =Montagem!AP28 | AV40: =Montagem!BB28 | AW40: =IF(AV40="",AT40,AV40) | AX40: =IF(AT41="C",'Dados de Base'!$D$5*0.1,IF(AT41="E",5,IF(AR40="",AW40,AR40))) | AZ40: =IF(BL40="","",HYPERLINK(OFFSET(Biblioteca!$B$2,MATCH(BL40,Biblioteca!$A$3:$A$200,0),0),BL40)) -> Fly Inverso | BC40: =Montagem!BJ28 -> Bi-SET | BD40: =Montagem!BK28 -> 4 | BE40: =Montagem!BL28 -> 10 | BF40: =Montagem!BM28 | BG40: =Montagem!BN28 -> 1 | BH40: =Montagem!BO28 -> 2 | BJ40: =Montagem!BD28 -> 5 | BK40: =Montagem!BP28 -> 8 | BL40: =Montagem!BE28 -> Fly Inverso | BM40: =Montagem!BQ28 | BN40: =IF(BM40="",BK40,BM40) -> 8 | BO40: =IF(BK41="C",'Dados de Base'!$D$5*0.1,IF(BK41="E",5,IF(BI40="",BN40,BI40))) -> 8 | BQ40: =IF(CC40="","",HYPERLINK(OFFSET(Biblioteca!$B$2,MATCH(CC40,Biblioteca!$A$3:$A$200,0),0),CC40)) -> Abdominal Canoa | BT40: =Montagem!BY28 -> Bi-SET | BU40: =Montagem!BZ28 -> 4 | BV40: =Montagem!CA28 -> 10 | BW40: =Montagem!CB28 -> 45 | BX40: =Montagem!CC28 -> 1 | BY40: =Montagem!CD28 -> 2 | CA40: =Montagem!BS28 -> 4 | CB40: =Montagem!CE28 -> 0 | CC40: =Montagem!BT28 -> Abdominal Canoa | CD40: =Montagem!CF28 | CE40: =IF(CD40="",CB40,CD40) -> 0 | CF40: =IF(CB41="C",'Dados de Base'!$D$5*0.1,IF(CB41="E",5,IF(BZ40="",CE40,BZ40))) -> 6.3 | CH40: =IF(CT40="","",HYPERLINK(OFFSET(Biblioteca!$B$2,MATCH(CT40,Biblioteca!$A$3:$A$200,0),0),CT40)) | CK40: =Montagem!CN28 | CL40: =Montagem!CO28 | CM40: =Montagem!CP28 | CN40: =Montagem!CQ28 | CO40: =Montagem!CR28 | CP40: =Montagem!CS28 | CR40: =Montagem!CH28 -> 1 | CS40: =Montagem!CT28 | CT40: =Montagem!CI28 | CU40: =Montagem!CU28 | CV40: =IF(CU40="",CS40,CU40) | CW40: =IF(CS41="C",'Dados de Base'!$D$5*0.1,IF(CS41="E",5,IF(CQ40="",CV40,CQ40))) | CY40: =IF(DK40="","",HYPERLINK(OFFSET(Biblioteca!$B$2,MATCH(DK40,Biblioteca!$A$3:$A$200,0),0),DK40)) | DB40: =Montagem!DC28 | DC40: =Montagem!DD28 | DD40: =Montagem!DE28 | DE40: =Montagem!DF28 | DF40: =Montagem!DG28 | DG40: =Montagem!DH28 | DI40: =Montagem!CW28 -> 1 | DJ40: =Montagem!DI28 | DK40: =Montagem!CX28 | DL40: =Montagem!DJ28 | DM40: =IF(DL40="",DJ40,DL40) | DN40: =IF(DJ41="C",'Dados de Base'!$D$5*0.1,IF(DJ41="E",5,IF(DH40="",DM40,DH40)))
A41: =IF(A40="","",IFS(L41="A",Montagem!$C$30,N41="T","Realizar a maior quantidade de repetições por "&F40&" segundos | ",N41="I",IF(M41="U","Manter a posição por "&F40&" segundos de um lado e trocar para o outro na sequência | ","Manter a posição por "&F40&" segundos | "),M41="A","Realizar alternadamente "&F40&" repetições cada lado | ",M41="U","Realizar "&F40&" repetições de um lado e trocar para o outro na sequência | ",L41="P",OFFSET(Biblioteca!$H$2,MATCH(M40,Biblioteca!$A$3:$A$200,0),0),TRUE,"")&IF(N41="R","Ajuste a carga para que tenha "&$K$2&" repetições de reserva","")) -> Ajuste a carga para que tenha 0 a 2 repetições de reserva | E41: =IF(A40="","",IFS(L41="H","Carga Sugerida: "&ROUNDUP(O40/2,0)&" kg de cada lado (Total: "&ROUNDUP(O40/2,0)*2&" kg)",L41="C","Este exercício usa o Peso Corporal como carga",L41="E","Este exercício usa a resistência da banda elástica como carga",L41="O","Carga Sugerida: "&INT(O40)&" kg",TRUE,"")) -> Este exercício usa o Peso Corporal como carga | K41: =K40 -> 4 | L41: =LEFT(O41) -> C | M41: =MID(O41,2,1) -> O | N41: =RIGHT(O41) -> R | O41: =IF(M40="","",OFFSET(Biblioteca!$I$2,MATCH(M40,Biblioteca!$A$3:$A$200,0),0)) -> COR | R41: =IF(R40="","",IFS(AC41="A",Montagem!$D$30,AE41="T","Realizar a maior quantidade de repetições por "&W40&" segundos | ",AE41="I",IF(AD41="U","Manter a posição por "&W40&" segundos de um lado e trocar para o outro na sequência | ","Manter a posição por "&W40&" segundos | "),AD41="A","Realizar alternadamente "&W40&" repetições cada lado | ",AD41="U","Realizar "&W40&" repetições de um lado e trocar para o outro na sequência | ",AC41="P",OFFSET(Biblioteca!$H$2,MATCH(AD40,Biblioteca!$A$3:$A$200,0),0),TRUE,"")&IF(AE41="R","Ajuste a carga para que tenha "&$K$2&" repetições de reserva","")) -> Ajuste a carga para que tenha 0 a 2 repetições de reserva | V41: =IF(R40="","",IFS(AC41="H","Carga Sugerida: "&ROUNDUP(AF40/2,0)&" kg de cada lado (Total: "&ROUNDUP(AF40/2,0)*2&" kg)",AC41="C","Este exercício usa o Peso Corporal como carga",AC41="E","Este exercício usa a resistência da banda elástica como carga",AC41="O","Carga Sugerida: "&INT(AF40)&" kg",TRUE,"")) -> Este exercício usa o Peso Corporal como carga | AB41: =AB40 -> 4 | AC41: =LEFT(AF41) -> C | AD41: =MID(AF41,2,1) -> O | AE41: =RIGHT(AF41) -> R | AF41: =IF(AD40="","",OFFSET(Biblioteca!$I$2,MATCH(AD40,Biblioteca!$A$3:$A$200,0),0)) -> COR | AI41: =IF(AI40="","",IFS(AT41="A",Montagem!$E$30,AV41="T","Realizar a maior quantidade de repetições por "&AN40&" segundos | ",AV41="I",IF(AU41="U","Manter a posição por "&AN40&" segundos de um lado e trocar para o outro na sequência | ","Manter a posição por "&AN40&" segundos | "),AU41="A","Realizar alternadamente "&AN40&" repetições cada lado | ",AU41="U","Realizar "&AN40&" repetições de um lado e trocar para o outro na sequência | ",AT41="P",OFFSET(Biblioteca!$H$2,MATCH(AU40,Biblioteca!$A$3:$A$200,0),0),TRUE,"")&IF(AV41="R","Ajuste a carga para que tenha "&$K$2&" repetições de reserva","")) | AM41: =IF(AI40="","",IFS(AT41="H","Carga Sugerida: "&ROUNDUP(AW40/2,0)&" kg de cada lado (Total: "&ROUNDUP(AW40/2,0)*2&" kg)",AT41="C","Este exercício usa o Peso Corporal como carga",AT41="E","Este exercício usa a resistência da banda elástica como carga",AT41="O","Carga Sugerida: "&INT(AW40)&" kg",TRUE,"")) | AS41: =AS40 -> 1 | AT41: =LEFT(AW41) | AU41: =MID(AW41,2,1) | AV41: =RIGHT(AW41) | AW41: =IF(AU40="","",OFFSET(Biblioteca!$I$2,MATCH(AU40,Biblioteca!$A$3:$A$200,0),0)) | AZ41: =IF(AZ40="","",IFS(BK41="A",Montagem!$F$30,BM41="T","Realizar a maior quantidade de repetições por "&BE40&" segundos | ",BM41="I",IF(BL41="U","Manter a posição por "&BE40&" segundos de um lado e trocar para o outro na sequência | ","Manter a posição por "&BE40&" segundos | "),BL41="A","Realizar alternadamente "&BE40&" repetições cada lado | ",BL41="U","Realizar "&BE40&" repetições de um lado e trocar para o outro na sequência | ",BK41="P",OFFSET(Biblioteca!$H$2,MATCH(BL40,Biblioteca!$A$3:$A$200,0),0),TRUE,"")&IF(BM41="R","Ajuste a carga para que tenha "&$K$2&" repetições de reserva","")) -> Ajuste a carga para que tenha 0 a 2 repetições de reserva | BD41: =IF(AZ40="","",IFS(BK41="H","Carga Sugerida: "&ROUNDUP(BN40/2,0)&" kg de cada lado (Total: "&ROUNDUP(BN40/2,0)*2&" kg)",BK41="C","Este exercício usa o Peso Corporal como carga",BK41="E","Este exercício usa a resistência da banda elástica como carga",BK41="O","Carga Sugerida: "&INT(BN40)&" kg",TRUE,"")) -> Carga Sugerida: 8 kg | BJ41: =BJ40 -> 5 | BK41: =LEFT(BN41) -> O | BL41: =MID(BN41,2,1) -> O | BM41: =RIGHT(BN41) -> R | BN41: =IF(BL40="","",OFFSET(Biblioteca!$I$2,MATCH(BL40,Biblioteca!$A$3:$A$200,0),0)) -> OOR | BQ41: =IF(BQ40="","",IFS(CB41="A",Montagem!$G$30,CD41="T","Realizar a maior quantidade de repetições por "&BV40&" segundos | ",CD41="I",IF(CC41="U","Manter a posição por "&BV40&" segundos de um lado e trocar para o outro na sequência | ","Manter a posição por "&BV40&" segundos | "),CC41="A","Realizar alternadamente "&BV40&" repetições cada lado | ",CC41="U","Realizar "&BV40&" repetições de um lado e trocar para o outro na sequência | ",CB41="P",OFFSET(Biblioteca!$H$2,MATCH(CC40,Biblioteca!$A$3:$A$200,0),0),TRUE,"")&IF(CD41="R","Ajuste a carga para que tenha "&$K$2&" repetições de reserva","")) -> Ajuste a carga para que tenha 0 a 2 repetições de reserva | BU41: =IF(BQ40="","",IFS(CB41="H","Carga Sugerida: "&ROUNDUP(CE40/2,0)&" kg de cada lado (Total: "&ROUNDUP(CE40/2,0)*2&" kg)",CB41="C","Este exercício usa o Peso Corporal como carga",CB41="E","Este exercício usa a resistência da banda elástica como carga",CB41="O","Carga Sugerida: "&INT(CE40)&" kg",TRUE,"")) -> Este exercício usa o Peso Corporal como carga | CA41: =CA40 -> 4 | CB41: =LEFT(CE41) -> C | CC41: =MID(CE41,2,1) -> O | CD41: =RIGHT(CE41) -> R | CE41: =IF(CC40="","",OFFSET(Biblioteca!$I$2,MATCH(CC40,Biblioteca!$A$3:$A$200,0),0)) -> COR | CH41: =IF(CH40="","",IFS(CS41="A",Montagem!$H$30,CU41="T","Realizar a maior quantidade de repetições por "&CM40&" segundos | ",CU41="I",IF(CT41="U","Manter a posição por "&CM40&" segundos de um lado e trocar para o outro na sequência | ","Manter a posição por "&CM40&" segundos | "),CT41="A","Realizar alternadamente "&CM40&" repetições cada lado | ",CT41="U","Realizar "&CM40&" repetições de um lado e trocar para o outro na sequência | ",CS41="P",OFFSET(Biblioteca!$H$2,MATCH(CT40,Biblioteca!$A$3:$A$200,0),0),TRUE,"")&IF(CU41="R","Ajuste a carga para que tenha "&$K$2&" repetições de reserva","")) | CL41: =IF(CH40="","",IFS(CS41="H","Carga Sugerida: "&ROUNDUP(CV40/2,0)&" kg de cada lado (Total: "&ROUNDUP(CV40/2,0)*2&" kg)",CS41="C","Este exercício usa o Peso Corporal como carga",CS41="E","Este exercício usa a resistência da banda elástica como carga",CS41="O","Carga Sugerida: "&INT(CV40)&" kg",TRUE,"")) | CR41: =CR40 -> 1 | CS41: =LEFT(CV41) | CT41: =MID(CV41,2,1) | CU41: =RIGHT(CV41) | CV41: =IF(CT40="","",OFFSET(Biblioteca!$I$2,MATCH(CT40,Biblioteca!$A$3:$A$200,0),0)) | CY41: =IF(CY40="","",IFS(DJ41="A",Montagem!$I$30,DL41="T","Realizar a maior quantidade de repetições por "&DD40&" segundos | ",DL41="I",IF(DK41="U","Manter a posição por "&DD40&" segundos de um lado e trocar para o outro na sequência | ","Manter a posição por "&DD40&" segundos | "),DK41="A","Realizar alternadamente "&DD40&" repetições cada lado | ",DK41="U","Realizar "&DD40&" repetições de um lado e trocar para o outro na sequência | ",DJ41="P",OFFSET(Biblioteca!$H$2,MATCH(DK40,Biblioteca!$A$3:$A$200,0),0),TRUE,"")&IF(DL41="R","Ajuste a carga para que tenha "&$K$2&" repetições de reserva","")) | DC41: =IF(CY40="","",IFS(DJ41="H","Carga Sugerida: "&ROUNDUP(DM40/2,0)&" kg de cada lado (Total: "&ROUNDUP(DM40/2,0)*2&" kg)",DJ41="C","Este exercício usa o Peso Corporal como carga",DJ41="E","Este exercício usa a resistência da banda elástica como carga",DJ41="O","Carga Sugerida: "&INT(DM40)&" kg",TRUE,"")) | DI41: =DI40 -> 1 | DJ41: =LEFT(DM41) | DK41: =MID(DM41,2,1) | DL41: =RIGHT(DM41) | DM41: =IF(DK40="","",OFFSET(Biblioteca!$I$2,MATCH(DK40,Biblioteca!$A$3:$A$200,0),0))
A42: =IF(M42="","",HYPERLINK(OFFSET(Biblioteca!$B$2,MATCH(M42,Biblioteca!$A$3:$A$200,0),0),M42)) -> Lat PullDown | D42: =Montagem!Q29 -> Bi-SET | E42: =Montagem!R29 -> 4 | F42: =Montagem!S29 -> 10 | G42: =Montagem!T29 | H42: =Montagem!U29 -> 1 | I42: =Montagem!V29 -> 2 | K42: =Montagem!K29 -> 5 | L42: =Montagem!W29 -> 8.379 | M42: =Montagem!L29 -> Lat PullDown | N42: =Montagem!X29 | O42: =IF(N42="",L42,N42) -> 8.379 | P42: =IF(L43="C",'Dados de Base'!$D$5*0.1,IF(L43="E",5,IF(J42="",O42,J42))) -> 8.379 | R42: =IF(AD42="","",HYPERLINK(OFFSET(Biblioteca!$B$2,MATCH(AD42,Biblioteca!$A$3:$A$200,0),0),AD42)) -> Crucifixo | U42: =Montagem!AF29 -> Bi-SET | V42: =Montagem!AG29 -> 4 | W42: =Montagem!AH29 -> 10 | X42: =Montagem!AI29 | Y42: =Montagem!AJ29 -> 1 | Z42: =Montagem!AK29 -> 2 | AB42: =Montagem!Z29 -> 5 | AC42: =Montagem!AL29 -> 19 | AD42: =Montagem!AA29 -> Crucifixo | AE42: =Montagem!AM29 | AF42: =IF(AE42="",AC42,AE42) -> 19 | AG42: =IF(AC43="C",'Dados de Base'!$D$5*0.1,IF(AC43="E",5,IF(AA42="",AF42,AA42))) -> 19 | AI42: =IF(AU42="","",HYPERLINK(OFFSET(Biblioteca!$B$2,MATCH(AU42,Biblioteca!$A$3:$A$200,0),0),AU42)) | AL42: =Montagem!AU29 | AM42: =Montagem!AV29 | AN42: =Montagem!AW29 | AO42: =Montagem!AX29 | AP42: =Montagem!AY29 | AQ42: =Montagem!AZ29 | AS42: =Montagem!AO29 -> 1 | AT42: =Montagem!BA29 | AU42: =Montagem!AP29 | AV42: =Montagem!BB29 | AW42: =IF(AV42="",AT42,AV42) | AX42: =IF(AT43="C",'Dados de Base'!$D$5*0.1,IF(AT43="E",5,IF(AR42="",AW42,AR42))) | AZ42: =IF(BL42="","",HYPERLINK(OFFSET(Biblioteca!$B$2,MATCH(BL42,Biblioteca!$A$3:$A$200,0),0),BL42)) -> Tríceps Polia | BC42: =Montagem!BJ29 -> Bi-SET | BD42: =Montagem!BK29 -> 4 | BE42: =Montagem!BL29 -> 10 | BF42: =Montagem!BM29 -> 45 | BG42: =Montagem!BN29 -> 1 | BH42: =Montagem!BO29 -> 2 | BJ42: =Montagem!BD29 -> 5 | BK42: =Montagem!BP29 -> 8.0411557 | BL42: =Montagem!BE29 -> Tríceps Polia | BM42: =Montagem!BQ29 | BN42: =IF(BM42="",BK42,BM42) -> 8.0411557 | BO42: =IF(BK43="C",'Dados de Base'!$D$5*0.1,IF(BK43="E",5,IF(BI42="",BN42,BI42))) -> 8.0411557 | BQ42: =IF(CC42="","",HYPERLINK(OFFSET(Biblioteca!$B$2,MATCH(CC42,Biblioteca!$A$3:$A$200,0),0),CC42)) -> Arremesso | BT42: =Montagem!BY29 -> Bi-SET | BU42: =Montagem!BZ29 -> 4 | BV42: =Montagem!CA29 -> 10 | BW42: =Montagem!CB29 | BX42: =Montagem!CC29 -> 1 | BY42: =Montagem!CD29 -> 2 | CA42: =Montagem!BS29 -> 5 | CB42: =Montagem!CE29 -> 7.0536453 | CC42: =Montagem!BT29 -> Arremesso | CD42: =Montagem!CF29 | CE42: =IF(CD42="",CB42,CD42) -> 7.0536453 | CF42: =IF(CB43="C",'Dados de Base'!$D$5*0.1,IF(CB43="E",5,IF(BZ42="",CE42,BZ42))) -> 7.0536453 | CH42: =IF(CT42="","",HYPERLINK(OFFSET(Biblioteca!$B$2,MATCH(CT42,Biblioteca!$A$3:$A$200,0),0),CT42)) | CK42: =Montagem!CN29 | CL42: =Montagem!CO29 | CM42: =Montagem!CP29 | CN42: =Montagem!CQ29 | CO42: =Montagem!CR29 | CP42: =Montagem!CS29 | CR42: =Montagem!CH29 -> 1 | CS42: =Montagem!CT29 | CT42: =Montagem!CI29 | CU42: =Montagem!CU29 | CV42: =IF(CU42="",CS42,CU42) | CW42: =IF(CS43="C",'Dados de Base'!$D$5*0.1,IF(CS43="E",5,IF(CQ42="",CV42,CQ42))) | CY42: =IF(DK42="","",HYPERLINK(OFFSET(Biblioteca!$B$2,MATCH(DK42,Biblioteca!$A$3:$A$200,0),0),DK42)) | DB42: =Montagem!DC29 | DC42: =Montagem!DD29 | DD42: =Montagem!DE29 | DE42: =Montagem!DF29 | DF42: =Montagem!DG29 | DG42: =Montagem!DH29 | DI42: =Montagem!CW29 -> 1 | DJ42: =Montagem!DI29 | DK42: =Montagem!CX29 | DL42: =Montagem!DJ29 | DM42: =IF(DL42="",DJ42,DL42) | DN42: =IF(DJ43="C",'Dados de Base'!$D$5*0.1,IF(DJ43="E",5,IF(DH42="",DM42,DH42)))
A43: =IF(A42="","",IFS(L43="A",Montagem!$C$30,N43="T","Realizar a maior quantidade de repetições por "&F42&" segundos | ",N43="I",IF(M43="U","Manter a posição por "&F42&" segundos de um lado e trocar para o outro na sequência | ","Manter a posição por "&F42&" segundos | "),M43="A","Realizar alternadamente "&F42&" repetições cada lado | ",M43="U","Realizar "&F42&" repetições de um lado e trocar para o outro na sequência | ",L43="P",OFFSET(Biblioteca!$H$2,MATCH(M42,Biblioteca!$A$3:$A$200,0),0),TRUE,"")&IF(N43="R","Ajuste a carga para que tenha "&$K$2&" repetições de reserva","")) -> Ajuste a carga para que tenha 0 a 2 repetições de reserva | E43: =IF(A42="","",IFS(L43="H","Carga Sugerida: "&ROUNDUP(O42/2,0)&" kg de cada lado (Total: "&ROUNDUP(O42/2,0)*2&" kg)",L43="C","Este exercício usa o Peso Corporal como carga",L43="E","Este exercício usa a resistência da banda elástica como carga",L43="O","Carga Sugerida: "&INT(O42)&" kg",TRUE,"")) -> Carga Sugerida: 8 kg | K43: =K42 -> 5 | L43: =LEFT(O43) -> O | M43: =MID(O43,2,1) -> O | N43: =RIGHT(O43) -> R | O43: =IF(M42="","",OFFSET(Biblioteca!$I$2,MATCH(M42,Biblioteca!$A$3:$A$200,0),0)) -> OOR | R43: =IF(R42="","",IFS(AC43="A",Montagem!$D$30,AE43="T","Realizar a maior quantidade de repetições por "&W42&" segundos | ",AE43="I",IF(AD43="U","Manter a posição por "&W42&" segundos de um lado e trocar para o outro na sequência | ","Manter a posição por "&W42&" segundos | "),AD43="A","Realizar alternadamente "&W42&" repetições cada lado | ",AD43="U","Realizar "&W42&" repetições de um lado e trocar para o outro na sequência | ",AC43="P",OFFSET(Biblioteca!$H$2,MATCH(AD42,Biblioteca!$A$3:$A$200,0),0),TRUE,"")&IF(AE43="R","Ajuste a carga para que tenha "&$K$2&" repetições de reserva","")) -> Ajuste a carga para que tenha 0 a 2 repetições de reserva | V43: =IF(R42="","",IFS(AC43="H","Carga Sugerida: "&ROUNDUP(AF42/2,0)&" kg de cada lado (Total: "&ROUNDUP(AF42/2,0)*2&" kg)",AC43="C","Este exercício usa o Peso Corporal como carga",AC43="E","Este exercício usa a resistência da banda elástica como carga",AC43="O","Carga Sugerida: "&INT(AF42)&" kg",TRUE,"")) -> Carga Sugerida: 10 kg de cada lado (Total: 20 kg) | AB43: =AB42 -> 5 | AC43: =LEFT(AF43) -> H | AD43: =MID(AF43,2,1) -> O | AE43: =RIGHT(AF43) -> R | AF43: =IF(AD42="","",OFFSET(Biblioteca!$I$2,MATCH(AD42,Biblioteca!$A$3:$A$200,0),0)) -> HOR | AI43: =IF(AI42="","",IFS(AT43="A",Montagem!$E$30,AV43="T","Realizar a maior quantidade de repetições por "&AN42&" segundos | ",AV43="I",IF(AU43="U","Manter a posição por "&AN42&" segundos de um lado e trocar para o outro na sequência | ","Manter a posição por "&AN42&" segundos | "),AU43="A","Realizar alternadamente "&AN42&" repetições cada lado | ",AU43="U","Realizar "&AN42&" repetições de um lado e trocar para o outro na sequência | ",AT43="P",OFFSET(Biblioteca!$H$2,MATCH(AU42,Biblioteca!$A$3:$A$200,0),0),TRUE,"")&IF(AV43="R","Ajuste a carga para que tenha "&$K$2&" repetições de reserva","")) | AM43: =IF(AI42="","",IFS(AT43="H","Carga Sugerida: "&ROUNDUP(AW42/2,0)&" kg de cada lado (Total: "&ROUNDUP(AW42/2,0)*2&" kg)",AT43="C","Este exercício usa o Peso Corporal como carga",AT43="E","Este exercício usa a resistência da banda elástica como carga",AT43="O","Carga Sugerida: "&INT(AW42)&" kg",TRUE,"")) | AS43: =AS42 -> 1 | AT43: =LEFT(AW43) | AU43: =MID(AW43,2,1) | AV43: =RIGHT(AW43) | AW43: =IF(AU42="","",OFFSET(Biblioteca!$I$2,MATCH(AU42,Biblioteca!$A$3:$A$200,0),0)) | AZ43: =IF(AZ42="","",IFS(BK43="A",Montagem!$F$30,BM43="T","Realizar a maior quantidade de repetições por "&BE42&" segundos | ",BM43="I",IF(BL43="U","Manter a posição por "&BE42&" segundos de um lado e trocar para o outro na sequência | ","Manter a posição por "&BE42&" segundos | "),BL43="A","Realizar alternadamente "&BE42&" repetições cada lado | ",BL43="U","Realizar "&BE42&" repetições de um lado e trocar para o outro na sequência | ",BK43="P",OFFSET(Biblioteca!$H$2,MATCH(BL42,Biblioteca!$A$3:$A$200,0),0),TRUE,"")&IF(BM43="R","Ajuste a carga para que tenha "&$K$2&" repetições de reserva","")) -> Ajuste a carga para que tenha 0 a 2 repetições de reserva | BD43: =IF(AZ42="","",IFS(BK43="H","Carga Sugerida: "&ROUNDUP(BN42/2,0)&" kg de cada lado (Total: "&ROUNDUP(BN42/2,0)*2&" kg)",BK43="C","Este exercício usa o Peso Corporal como carga",BK43="E","Este exercício usa a resistência da banda elástica como carga",BK43="O","Carga Sugerida: "&INT(BN42)&" kg",TRUE,"")) -> Carga Sugerida: 8 kg | BJ43: =BJ42 -> 5 | BK43: =LEFT(BN43) -> O | BL43: =MID(BN43,2,1) -> O | BM43: =RIGHT(BN43) -> R | BN43: =IF(BL42="","",OFFSET(Biblioteca!$I$2,MATCH(BL42,Biblioteca!$A$3:$A$200,0),0)) -> OOR | BQ43: =IF(BQ42="","",IFS(CB43="A",Montagem!$G$30,CD43="T","Realizar a maior quantidade de repetições por "&BV42&" segundos | ",CD43="I",IF(CC43="U","Manter a posição por "&BV42&" segundos de um lado e trocar para o outro na sequência | ","Manter a posição por "&BV42&" segundos | "),CC43="A","Realizar alternadamente "&BV42&" repetições cada lado | ",CC43="U","Realizar "&BV42&" repetições de um lado e trocar para o outro na sequência | ",CB43="P",OFFSET(Biblioteca!$H$2,MATCH(CC42,Biblioteca!$A$3:$A$200,0),0),TRUE,"")&IF(CD43="R","Ajuste a carga para que tenha "&$K$2&" repetições de reserva","")) -> Ajuste a carga para que tenha 0 a 2 repetições de reserva | BU43: =IF(BQ42="","",IFS(CB43="H","Carga Sugerida: "&ROUNDUP(CE42/2,0)&" kg de cada lado (Total: "&ROUNDUP(CE42/2,0)*2&" kg)",CB43="C","Este exercício usa o Peso Corporal como carga",CB43="E","Este exercício usa a resistência da banda elástica como carga",CB43="O","Carga Sugerida: "&INT(CE42)&" kg",TRUE,"")) -> Carga Sugerida: 7 kg | CA43: =CA42 -> 5 | CB43: =LEFT(CE43) -> O | CC43: =MID(CE43,2,1) -> O | CD43: =RIGHT(CE43) -> R | CE43: =IF(CC42="","",OFFSET(Biblioteca!$I$2,MATCH(CC42,Biblioteca!$A$3:$A$200,0),0)) -> OOR | CH43: =IF(CH42="","",IFS(CS43="A",Montagem!$H$30,CU43="T","Realizar a maior quantidade de repetições por "&CM42&" segundos | ",CU43="I",IF(CT43="U","Manter a posição por "&CM42&" segundos de um lado e trocar para o outro na sequência | ","Manter a posição por "&CM42&" segundos | "),CT43="A","Realizar alternadamente "&CM42&" repetições cada lado | ",CT43="U","Realizar "&CM42&" repetições de um lado e trocar para o outro na sequência | ",CS43="P",OFFSET(Biblioteca!$H$2,MATCH(CT42,Biblioteca!$A$3:$A$200,0),0),TRUE,"")&IF(CU43="R","Ajuste a carga para que tenha "&$K$2&" repetições de reserva","")) | CL43: =IF(CH42="","",IFS(CS43="H","Carga Sugerida: "&ROUNDUP(CV42/2,0)&" kg de cada lado (Total: "&ROUNDUP(CV42/2,0)*2&" kg)",CS43="C","Este exercício usa o Peso Corporal como carga",CS43="E","Este exercício usa a resistência da banda elástica como carga",CS43="O","Carga Sugerida: "&INT(CV42)&" kg",TRUE,"")) | CR43: =CR42 -> 1 | CS43: =LEFT(CV43) | CT43: =MID(CV43,2,1) | CU43: =RIGHT(CV43) | CV43: =IF(CT42="","",OFFSET(Biblioteca!$I$2,MATCH(CT42,Biblioteca!$A$3:$A$200,0),0)) | CY43: =IF(CY42="","",IFS(DJ43="A",Montagem!$I$30,DL43="T","Realizar a maior quantidade de repetições por "&DD42&" segundos | ",DL43="I",IF(DK43="U","Manter a posição por "&DD42&" segundos de um lado e trocar para o outro na sequência | ","Manter a posição por "&DD42&" segundos | "),DK43="A","Realizar alternadamente "&DD42&" repetições cada lado | ",DK43="U","Realizar "&DD42&" repetições de um lado e trocar para o outro na sequência | ",DJ43="P",OFFSET(Biblioteca!$H$2,MATCH(DK42,Biblioteca!$A$3:$A$200,0),0),TRUE,"")&IF(DL43="R","Ajuste a carga para que tenha "&$K$2&" repetições de reserva","")) | DC43: =IF(CY42="","",IFS(DJ43="H","Carga Sugerida: "&ROUNDUP(DM42/2,0)&" kg de cada lado (Total: "&ROUNDUP(DM42/2,0)*2&" kg)",DJ43="C","Este exercício usa o Peso Corporal como carga",DJ43="E","Este exercício usa a resistência da banda elástica como carga",DJ43="O","Carga Sugerida: "&INT(DM42)&" kg",TRUE,"")) | DI43: =DI42 -> 1 | DJ43: =LEFT(DM43) | DK43: =MID(DM43,2,1) | DL43: =RIGHT(DM43) | DM43: =IF(DK42="","",OFFSET(Biblioteca!$I$2,MATCH(DK42,Biblioteca!$A$3:$A$200,0),0))
A44: =IF(M44="","",HYPERLINK(OFFSET(Biblioteca!$B$2,MATCH(M44,Biblioteca!$A$3:$A$200,0),0),M44)) -> Rosca Direta | D44: =Montagem!Q30 -> Bi-SET | E44: =Montagem!R30 -> 4 | F44: =Montagem!S30 -> 10 | G44: =Montagem!T30 -> 60 | H44: =Montagem!U30 -> 1 | I44: =Montagem!V30 -> 2 | K44: =Montagem!K30 -> 5 | L44: =Montagem!W30 -> 20 | M44: =Montagem!L30 -> Rosca Direta | N44: =Montagem!X30 | O44: =IF(N44="",L44,N44) -> 20 | P44: =IF(L45="C",'Dados de Base'!$D$5*0.1,IF(L45="E",5,IF(J44="",O44,J44))) -> 20 | R44: =IF(AD44="","",HYPERLINK(OFFSET(Biblioteca!$B$2,MATCH(AD44,Biblioteca!$A$3:$A$200,0),0),AD44)) -> Tríceps Testa polia | U44: =Montagem!AF30 -> Bi-SET | V44: =Montagem!AG30 -> 4 | W44: =Montagem!AH30 -> 10 | X44: =Montagem!AI30 -> 60 | Y44: =Montagem!AJ30 -> 1 | Z44: =Montagem!AK30 -> 2 | AB44: =Montagem!Z30 -> 5 | AC44: =Montagem!AL30 -> 7.6 | AD44: =Montagem!AA30 -> Tríceps Testa polia | AE44: =Montagem!AM30 | AF44: =IF(AE44="",AC44,AE44) -> 7.6 | AG44: =IF(AC45="C",'Dados de Base'!$D$5*0.1,IF(AC45="E",5,IF(AA44="",AF44,AA44))) -> 7.6 | AI44: =IF(AU44="","",HYPERLINK(OFFSET(Biblioteca!$B$2,MATCH(AU44,Biblioteca!$A$3:$A$200,0),0),AU44)) | AL44: =Montagem!AU30 | AM44: =Montagem!AV30 | AN44: =Montagem!AW30 | AO44: =Montagem!AX30 | AP44: =Montagem!AY30 | AQ44: =Montagem!AZ30 | AS44: =Montagem!AO30 -> 1 | AT44: =Montagem!BA30 | AU44: =Montagem!AP30 | AV44: =Montagem!BB30 | AW44: =IF(AV44="",AT44,AV44) | AX44: =IF(AT45="C",'Dados de Base'!$D$5*0.1,IF(AT45="E",5,IF(AR44="",AW44,AR44))) | AZ44: =IF(BL44="","",HYPERLINK(OFFSET(Biblioteca!$B$2,MATCH(BL44,Biblioteca!$A$3:$A$200,0),0),BL44)) -> Flexão de braço na bola | BC44: =Montagem!BJ30 -> Bi-SET | BD44: =Montagem!BK30 -> 4 | BE44: =Montagem!BL30 -> 14 | BF44: =Montagem!BM30 | BG44: =Montagem!BN30 -> 1 | BH44: =Montagem!BO30 -> 2 | BJ44: =Montagem!BD30 -> 6 | BK44: =Montagem!BP30 -> 0 | BL44: =Montagem!BE30 -> Flexão de braço na bola | BM44: =Montagem!BQ30 | BN44: =IF(BM44="",BK44,BM44) -> 0 | BO44: =IF(BK45="C",'Dados de Base'!$D$5*0.1,IF(BK45="E",5,IF(BI44="",BN44,BI44))) -> 6.3 | BQ44: =IF(CC44="","",HYPERLINK(OFFSET(Biblioteca!$B$2,MATCH(CC44,Biblioteca!$A$3:$A$200,0),0),CC44)) -> Rosca Direta | BT44: =Montagem!BY30 -> Bi-SET | BU44: =Montagem!BZ30 -> 4 | BV44: =Montagem!CA30 -> 10 | BW44: =Montagem!CB30 -> 60 | BX44: =Montagem!CC30 -> 1 | BY44: =Montagem!CD30 -> 2 | CA44: =Montagem!BS30 -> 5 | CB44: =Montagem!CE30 -> 20 | CC44: =Montagem!BT30 -> Rosca Direta | CD44: =Montagem!CF30 | CE44: =IF(CD44="",CB44,CD44) -> 20 | CF44: =IF(CB45="C",'Dados de Base'!$D$5*0.1,IF(CB45="E",5,IF(BZ44="",CE44,BZ44))) -> 20 | CH44: =IF(CT44="","",HYPERLINK(OFFSET(Biblioteca!$B$2,MATCH(CT44,Biblioteca!$A$3:$A$200,0),0),CT44)) | CK44: =Montagem!CN30 | CL44: =Montagem!CO30 | CM44: =Montagem!CP30 | CN44: =Montagem!CQ30 | CO44: =Montagem!CR30 | CP44: =Montagem!CS30 | CR44: =Montagem!CH30 -> 1 | CS44: =Montagem!CT30 | CT44: =Montagem!CI30 | CU44: =Montagem!CU30 | CV44: =IF(CU44="",CS44,CU44) | CW44: =IF(CS45="C",'Dados de Base'!$D$5*0.1,IF(CS45="E",5,IF(CQ44="",CV44,CQ44))) | CY44: =IF(DK44="","",HYPERLINK(OFFSET(Biblioteca!$B$2,MATCH(DK44,Biblioteca!$A$3:$A$200,0),0),DK44)) | DB44: =Montagem!DC30 | DC44: =Montagem!DD30 | DD44: =Montagem!DE30 | DE44: =Montagem!DF30 | DF44: =Montagem!DG30 | DG44: =Montagem!DH30 | DI44: =Montagem!CW30 -> 1 | DJ44: =Montagem!DI30 | DK44: =Montagem!CX30 | DL44: =Montagem!DJ30 | DM44: =IF(DL44="",DJ44,DL44) | DN44: =IF(DJ45="C",'Dados de Base'!$D$5*0.1,IF(DJ45="E",5,IF(DH44="",DM44,DH44)))
A45: =IF(A44="","",IFS(L45="A",Montagem!$C$30,N45="T","Realizar a maior quantidade de repetições por "&F44&" segundos | ",N45="I",IF(M45="U","Manter a posição por "&F44&" segundos de um lado e trocar para o outro na sequência | ","Manter a posição por "&F44&" segundos | "),M45="A","Realizar alternadamente "&F44&" repetições cada lado | ",M45="U","Realizar "&F44&" repetições de um lado e trocar para o outro na sequência | ",L45="P",OFFSET(Biblioteca!$H$2,MATCH(M44,Biblioteca!$A$3:$A$200,0),0),TRUE,"")&IF(N45="R","Ajuste a carga para que tenha "&$K$2&" repetições de reserva","")) -> Ajuste a carga para que tenha 0 a 2 repetições de reserva | E45: =IF(A44="","",IFS(L45="H","Carga Sugerida: "&ROUNDUP(O44/2,0)&" kg de cada lado (Total: "&ROUNDUP(O44/2,0)*2&" kg)",L45="C","Este exercício usa o Peso Corporal como carga",L45="E","Este exercício usa a resistência da banda elástica como carga",L45="O","Carga Sugerida: "&INT(O44)&" kg",TRUE,"")) -> Carga Sugerida: 20 kg | K45: =K44 -> 5 | L45: =LEFT(O45) -> O | M45: =MID(O45,2,1) -> O | N45: =RIGHT(O45) -> R | O45: =IF(M44="","",OFFSET(Biblioteca!$I$2,MATCH(M44,Biblioteca!$A$3:$A$200,0),0)) -> OOR | R45: =IF(R44="","",IFS(AC45="A",Montagem!$D$30,AE45="T","Realizar a maior quantidade de repetições por "&W44&" segundos | ",AE45="I",IF(AD45="U","Manter a posição por "&W44&" segundos de um lado e trocar para o outro na sequência | ","Manter a posição por "&W44&" segundos | "),AD45="A","Realizar alternadamente "&W44&" repetições cada lado | ",AD45="U","Realizar "&W44&" repetições de um lado e trocar para o outro na sequência | ",AC45="P",OFFSET(Biblioteca!$H$2,MATCH(AD44,Biblioteca!$A$3:$A$200,0),0),TRUE,"")&IF(AE45="R","Ajuste a carga para que tenha "&$K$2&" repetições de reserva","")) -> Ajuste a carga para que tenha 0 a 2 repetições de reserva | V45: =IF(R44="","",IFS(AC45="H","Carga Sugerida: "&ROUNDUP(AF44/2,0)&" kg de cada lado (Total: "&ROUNDUP(AF44/2,0)*2&" kg)",AC45="C","Este exercício usa o Peso Corporal como carga",AC45="E","Este exercício usa a resistência da banda elástica como carga",AC45="O","Carga Sugerida: "&INT(AF44)&" kg",TRUE,"")) -> Carga Sugerida: 7 kg | AB45: =AB44 -> 5 | AC45: =LEFT(AF45) -> O | AD45: =MID(AF45,2,1) -> O | AE45: =RIGHT(AF45) -> R | AF45: =IF(AD44="","",OFFSET(Biblioteca!$I$2,MATCH(AD44,Biblioteca!$A$3:$A$200,0),0)) -> OOR | AI45: =IF(AI44="","",IFS(AT45="A",Montagem!$E$30,AV45="T","Realizar a maior quantidade de repetições por "&AN44&" segundos | ",AV45="I",IF(AU45="U","Manter a posição por "&AN44&" segundos de um lado e trocar para o outro na sequência | ","Manter a posição por "&AN44&" segundos | "),AU45="A","Realizar alternadamente "&AN44&" repetições cada lado | ",AU45="U","Realizar "&AN44&" repetições de um lado e trocar para o outro na sequência | ",AT45="P",OFFSET(Biblioteca!$H$2,MATCH(AU44,Biblioteca!$A$3:$A$200,0),0),TRUE,"")&IF(AV45="R","Ajuste a carga para que tenha "&$K$2&" repetições de reserva","")) | AM45: =IF(AI44="","",IFS(AT45="H","Carga Sugerida: "&ROUNDUP(AW44/2,0)&" kg de cada lado (Total: "&ROUNDUP(AW44/2,0)*2&" kg)",AT45="C","Este exercício usa o Peso Corporal como carga",AT45="E","Este exercício usa a resistência da banda elástica como carga",AT45="O","Carga Sugerida: "&INT(AW44)&" kg",TRUE,"")) | AS45: =AS44 -> 1 | AT45: =LEFT(AW45) | AU45: =MID(AW45,2,1) | AV45: =RIGHT(AW45) | AW45: =IF(AU44="","",OFFSET(Biblioteca!$I$2,MATCH(AU44,Biblioteca!$A$3:$A$200,0),0)) | AZ45: =IF(AZ44="","",IFS(BK45="A",Montagem!$F$30,BM45="T","Realizar a maior quantidade de repetições por "&BE44&" segundos | ",BM45="I",IF(BL45="U","Manter a posição por "&BE44&" segundos de um lado e trocar para o outro na sequência | ","Manter a posição por "&BE44&" segundos | "),BL45="A","Realizar alternadamente "&BE44&" repetições cada lado | ",BL45="U","Realizar "&BE44&" repetições de um lado e trocar para o outro na sequência | ",BK45="P",OFFSET(Biblioteca!$H$2,MATCH(BL44,Biblioteca!$A$3:$A$200,0),0),TRUE,"")&IF(BM45="R","Ajuste a carga para que tenha "&$K$2&" repetições de reserva","")) -> Ajuste a carga para que tenha 0 a 2 repetições de reserva | BD45: =IF(AZ44="","",IFS(BK45="H","Carga Sugerida: "&ROUNDUP(BN44/2,0)&" kg de cada lado (Total: "&ROUNDUP(BN44/2,0)*2&" kg)",BK45="C","Este exercício usa o Peso Corporal como carga",BK45="E","Este exercício usa a resistência da banda elástica como carga",BK45="O","Carga Sugerida: "&INT(BN44)&" kg",TRUE,"")) -> Este exercício usa o Peso Corporal como carga | BJ45: =BJ44 -> 6 | BK45: =LEFT(BN45) -> C | BL45: =MID(BN45,2,1) -> O | BM45: =RIGHT(BN45) -> R | BN45: =IF(BL44="","",OFFSET(Biblioteca!$I$2,MATCH(BL44,Biblioteca!$A$3:$A$200,0),0)) -> COR | BQ45: =IF(BQ44="","",IFS(CB45="A",Montagem!$G$30,CD45="T","Realizar a maior quantidade de repetições por "&BV44&" segundos | ",CD45="I",IF(CC45="U","Manter a posição por "&BV44&" segundos de um lado e trocar para o outro na sequência | ","Manter a posição por "&BV44&" segundos | "),CC45="A","Realizar alternadamente "&BV44&" repetições cada lado | ",CC45="U","Realizar "&BV44&" repetições de um lado e trocar para o outro na sequência | ",CB45="P",OFFSET(Biblioteca!$H$2,MATCH(CC44,Biblioteca!$A$3:$A$200,0),0),TRUE,"")&IF(CD45="R","Ajuste a carga para que tenha "&$K$2&" repetições de reserva","")) -> Ajuste a carga para que tenha 0 a 2 repetições de reserva | BU45: =IF(BQ44="","",IFS(CB45="H","Carga Sugerida: "&ROUNDUP(CE44/2,0)&" kg de cada lado (Total: "&ROUNDUP(CE44/2,0)*2&" kg)",CB45="C","Este exercício usa o Peso Corporal como carga",CB45="E","Este exercício usa a resistência da banda elástica como carga",CB45="O","Carga Sugerida: "&INT(CE44)&" kg",TRUE,"")) -> Carga Sugerida: 20 kg | CA45: =CA44 -> 5 | CB45: =LEFT(CE45) -> O | CC45: =MID(CE45,2,1) -> O | CD45: =RIGHT(CE45) -> R | CE45: =IF(CC44="","",OFFSET(Biblioteca!$I$2,MATCH(CC44,Biblioteca!$A$3:$A$200,0),0)) -> OOR | CH45: =IF(CH44="","",IFS(CS45="A",Montagem!$H$30,CU45="T","Realizar a maior quantidade de repetições por "&CM44&" segundos | ",CU45="I",IF(CT45="U","Manter a posição por "&CM44&" segundos de um lado e trocar para o outro na sequência | ","Manter a posição por "&CM44&" segundos | "),CT45="A","Realizar alternadamente "&CM44&" repetições cada lado | ",CT45="U","Realizar "&CM44&" repetições de um lado e trocar para o outro na sequência | ",CS45="P",OFFSET(Biblioteca!$H$2,MATCH(CT44,Biblioteca!$A$3:$A$200,0),0),TRUE,"")&IF(CU45="R","Ajuste a carga para que tenha "&$K$2&" repetições de reserva","")) | CL45: =IF(CH44="","",IFS(CS45="H","Carga Sugerida: "&ROUNDUP(CV44/2,0)&" kg de cada lado (Total: "&ROUNDUP(CV44/2,0)*2&" kg)",CS45="C","Este exercício usa o Peso Corporal como carga",CS45="E","Este exercício usa a resistência da banda elástica como carga",CS45="O","Carga Sugerida: "&INT(CV44)&" kg",TRUE,"")) | CR45: =CR44 -> 1 | CS45: =LEFT(CV45) | CT45: =MID(CV45,2,1) | CU45: =RIGHT(CV45) | CV45: =IF(CT44="","",OFFSET(Biblioteca!$I$2,MATCH(CT44,Biblioteca!$A$3:$A$200,0),0)) | CY45: =IF(CY44="","",IFS(DJ45="A",Montagem!$I$30,DL45="T","Realizar a maior quantidade de repetições por "&DD44&" segundos | ",DL45="I",IF(DK45="U","Manter a posição por "&DD44&" segundos de um lado e trocar para o outro na sequência | ","Manter a posição por "&DD44&" segundos | "),DK45="A","Realizar alternadamente "&DD44&" repetições cada lado | ",DK45="U","Realizar "&DD44&" repetições de um lado e trocar para o outro na sequência | ",DJ45="P",OFFSET(Biblioteca!$H$2,MATCH(DK44,Biblioteca!$A$3:$A$200,0),0),TRUE,"")&IF(DL45="R","Ajuste a carga para que tenha "&$K$2&" repetições de reserva","")) | DC45: =IF(CY44="","",IFS(DJ45="H","Carga Sugerida: "&ROUNDUP(DM44/2,0)&" kg de cada lado (Total: "&ROUNDUP(DM44/2,0)*2&" kg)",DJ45="C","Este exercício usa o Peso Corporal como carga",DJ45="E","Este exercício usa a resistência da banda elástica como carga",DJ45="O","Carga Sugerida: "&INT(DM44)&" kg",TRUE,"")) | DI45: =DI44 -> 1 | DJ45: =LEFT(DM45) | DK45: =MID(DM45,2,1) | DL45: =RIGHT(DM45) | DM45: =IF(DK44="","",OFFSET(Biblioteca!$I$2,MATCH(DK44,Biblioteca!$A$3:$A$200,0),0))
A46: =IF(M46="","",HYPERLINK(OFFSET(Biblioteca!$B$2,MATCH(M46,Biblioteca!$A$3:$A$200,0),0),M46)) -> Esteira | D46: =Montagem!Q31 | E46: =Montagem!R31 | F46: =Montagem!S31 | G46: =Montagem!T31 | H46: =Montagem!U31 | I46: =Montagem!V31 | K46: =Montagem!K31 -> 6 | L46: =Montagem!W31 -> 0 | M46: =Montagem!L31 -> Esteira | N46: =Montagem!X31 | O46: =IF(N46="",L46,N46) -> 0 | P46: =IF(L47="C",'Dados de Base'!$D$5*0.1,IF(L47="E",5,IF(J46="",O46,J46))) -> 0 | R46: =IF(AD46="","",HYPERLINK(OFFSET(Biblioteca!$B$2,MATCH(AD46,Biblioteca!$A$3:$A$200,0),0),AD46)) -> Bicicleta | U46: =Montagem!AF31 | V46: =Montagem!AG31 | W46: =Montagem!AH31 | X46: =Montagem!AI31 | Y46: =Montagem!AJ31 | Z46: =Montagem!AK31 | AB46: =Montagem!Z31 -> 6 | AC46: =Montagem!AL31 -> 0 | AD46: =Montagem!AA31 -> Bicicleta | AE46: =Montagem!AM31 | AF46: =IF(AE46="",AC46,AE46) -> 0 | AG46: =IF(AC47="C",'Dados de Base'!$D$5*0.1,IF(AC47="E",5,IF(AA46="",AF46,AA46))) -> 0 | AI46: =IF(AU46="","",HYPERLINK(OFFSET(Biblioteca!$B$2,MATCH(AU46,Biblioteca!$A$3:$A$200,0),0),AU46)) | AL46: =Montagem!AU31 | AM46: =Montagem!AV31 | AN46: =Montagem!AW31 | AO46: =Montagem!AX31 | AP46: =Montagem!AY31 | AQ46: =Montagem!AZ31 | AS46: =Montagem!AO31 -> 1 | AT46: =Montagem!BA31 | AU46: =Montagem!AP31 | AV46: =Montagem!BB31 | AW46: =IF(AV46="",AT46,AV46) | AX46: =IF(AT47="C",'Dados de Base'!$D$5*0.1,IF(AT47="E",5,IF(AR46="",AW46,AR46))) | AZ46: =IF(BL46="","",HYPERLINK(OFFSET(Biblioteca!$B$2,MATCH(BL46,Biblioteca!$A$3:$A$200,0),0),BL46)) -> Remada Horizontal com Movimentação do Tronco | BC46: =Montagem!BJ31 -> Bi-SET | BD46: =Montagem!BK31 -> 4 | BE46: =Montagem!BL31 -> 10 | BF46: =Montagem!BM31 -> 45 | BG46: =Montagem!BN31 -> 1 | BH46: =Montagem!BO31 -> 2 | BJ46: =Montagem!BD31 -> 6 | BK46: =Montagem!BP31 -> 11.025 | BL46: =Montagem!BE31 -> Remada Horizontal com Movimentação do Tronco | BM46: =Montagem!BQ31 | BN46: =IF(BM46="",BK46,BM46) -> 11.025 | BO46: =IF(BK47="C",'Dados de Base'!$D$5*0.1,IF(BK47="E",5,IF(BI46="",BN46,BI46))) -> 11.025 | BQ46: =IF(CC46="","",HYPERLINK(OFFSET(Biblioteca!$B$2,MATCH(CC46,Biblioteca!$A$3:$A$200,0),0),CC46)) -> Esteira | BT46: =Montagem!BY31 | BU46: =Montagem!BZ31 | BV46: =Montagem!CA31 | BW46: =Montagem!CB31 | BX46: =Montagem!CC31 | BY46: =Montagem!CD31 | CA46: =Montagem!BS31 -> 6 | CB46: =Montagem!CE31 -> 0 | CC46: =Montagem!BT31 -> Esteira | CD46: =Montagem!CF31 | CE46: =IF(CD46="",CB46,CD46) -> 0 | CF46: =IF(CB47="C",'Dados de Base'!$D$5*0.1,IF(CB47="E",5,IF(BZ46="",CE46,BZ46))) -> 0 | CH46: =IF(CT46="","",HYPERLINK(OFFSET(Biblioteca!$B$2,MATCH(CT46,Biblioteca!$A$3:$A$200,0),0),CT46)) | CK46: =Montagem!CN31 | CL46: =Montagem!CO31 | CM46: =Montagem!CP31 | CN46: =Montagem!CQ31 | CO46: =Montagem!CR31 | CP46: =Montagem!CS31 | CR46: =Montagem!CH31 -> 1 | CS46: =Montagem!CT31 | CT46: =Montagem!CI31 | CU46: =Montagem!CU31 | CV46: =IF(CU46="",CS46,CU46) | CW46: =IF(CS47="C",'Dados de Base'!$D$5*0.1,IF(CS47="E",5,IF(CQ46="",CV46,CQ46))) | CY46: =IF(DK46="","",HYPERLINK(OFFSET(Biblioteca!$B$2,MATCH(DK46,Biblioteca!$A$3:$A$200,0),0),DK46)) | DB46: =Montagem!DC31 | DC46: =Montagem!DD31 | DD46: =Montagem!DE31 | DE46: =Montagem!DF31 | DF46: =Montagem!DG31 | DG46: =Montagem!DH31 | DI46: =Montagem!CW31 -> 1 | DJ46: =Montagem!DI31 | DK46: =Montagem!CX31 | DL46: =Montagem!DJ31 | DM46: =IF(DL46="",DJ46,DL46) | DN46: =IF(DJ47="C",'Dados de Base'!$D$5*0.1,IF(DJ47="E",5,IF(DH46="",DM46,DH46)))
A47: =IF(A46="","",IFS(L47="A",Montagem!$C$30,N47="T","Realizar a maior quantidade de repetições por "&F46&" segundos | ",N47="I",IF(M47="U","Manter a posição por "&F46&" segundos de um lado e trocar para o outro na sequência | ","Manter a posição por "&F46&" segundos | "),M47="A","Realizar alternadamente "&F46&" repetições cada lado | ",M47="U","Realizar "&F46&" repetições de um lado e trocar para o outro na sequência | ",L47="P",OFFSET(Biblioteca!$H$2,MATCH(M46,Biblioteca!$A$3:$A$200,0),0),TRUE,"")&IF(N47="R","Ajuste a carga para que tenha "&$K$2&" repetições de reserva","")) -> Mantenha 22-25min em intensidade constante com frequência cardíaca entre 105,5 - 116,2 bpm (50 - 60% VO2Máx -> 8,5 - 10,9km/h) | E47: =IF(A46="","",IFS(L47="H","Carga Sugerida: "&ROUNDUP(O46/2,0)&" kg de cada lado (Total: "&ROUNDUP(O46/2,0)*2&" kg)",L47="C","Este exercício usa o Peso Corporal como carga",L47="E","Este exercício usa a resistência da banda elástica como carga",L47="O","Carga Sugerida: "&INT(O46)&" kg",TRUE,"")) | K47: =K46 -> 6 | L47: =LEFT(O47) -> A | M47: =MID(O47,2,1) -> - | N47: =RIGHT(O47) -> - | O47: =IF(M46="","",OFFSET(Biblioteca!$I$2,MATCH(M46,Biblioteca!$A$3:$A$200,0),0)) -> A-- | R47: =IF(R46="","",IFS(AC47="A",Montagem!$D$30,AE47="T","Realizar a maior quantidade de repetições por "&W46&" segundos | ",AE47="I",IF(AD47="U","Manter a posição por "&W46&" segundos de um lado e trocar para o outro na sequência | ","Manter a posição por "&W46&" segundos | "),AD47="A","Realizar alternadamente "&W46&" repetições cada lado | ",AD47="U","Realizar "&W46&" repetições de um lado e trocar para o outro na sequência | ",AC47="P",OFFSET(Biblioteca!$H$2,MATCH(AD46,Biblioteca!$A$3:$A$200,0),0),TRUE,"")&IF(AE47="R","Ajuste a carga para que tenha "&$K$2&" repetições de reserva","")) -> 5x (45s all out + 15s repouso) | V47: =IF(R46="","",IFS(AC47="H","Carga Sugerida: "&ROUNDUP(AF46/2,0)&" kg de cada lado (Total: "&ROUNDUP(AF46/2,0)*2&" kg)",AC47="C","Este exercício usa o Peso Corporal como carga",AC47="E","Este exercício usa a resistência da banda elástica como carga",AC47="O","Carga Sugerida: "&INT(AF46)&" kg",TRUE,"")) | AB47: =AB46 -> 6 | AC47: =LEFT(AF47) -> A | AD47: =MID(AF47,2,1) -> - | AE47: =RIGHT(AF47) -> - | AF47: =IF(AD46="","",OFFSET(Biblioteca!$I$2,MATCH(AD46,Biblioteca!$A$3:$A$200,0),0)) -> A-- | AI47: =IF(AI46="","",IFS(AT47="A",Montagem!$E$30,AV47="T","Realizar a maior quantidade de repetições por "&AN46&" segundos | ",AV47="I",IF(AU47="U","Manter a posição por "&AN46&" segundos de um lado e trocar para o outro na sequência | ","Manter a posição por "&AN46&" segundos | "),AU47="A","Realizar alternadamente "&AN46&" repetições cada lado | ",AU47="U","Realizar "&AN46&" repetições de um lado e trocar para o outro na sequência | ",AT47="P",OFFSET(Biblioteca!$H$2,MATCH(AU46,Biblioteca!$A$3:$A$200,0),0),TRUE,"")&IF(AV47="R","Ajuste a carga para que tenha "&$K$2&" repetições de reserva","")) | AM47: =IF(AI46="","",IFS(AT47="H","Carga Sugerida: "&ROUNDUP(AW46/2,0)&" kg de cada lado (Total: "&ROUNDUP(AW46/2,0)*2&" kg)",AT47="C","Este exercício usa o Peso Corporal como carga",AT47="E","Este exercício usa a resistência da banda elástica como carga",AT47="O","Carga Sugerida: "&INT(AW46)&" kg",TRUE,"")) | AS47: =AS46 -> 1 | AT47: =LEFT(AW47) | AU47: =MID(AW47,2,1) | AV47: =RIGHT(AW47) | AW47: =IF(AU46="","",OFFSET(Biblioteca!$I$2,MATCH(AU46,Biblioteca!$A$3:$A$200,0),0)) | AZ47: =IF(AZ46="","",IFS(BK47="A",Montagem!$F$30,BM47="T","Realizar a maior quantidade de repetições por "&BE46&" segundos | ",BM47="I",IF(BL47="U","Manter a posição por "&BE46&" segundos de um lado e trocar para o outro na sequência | ","Manter a posição por "&BE46&" segundos | "),BL47="A","Realizar alternadamente "&BE46&" repetições cada lado | ",BL47="U","Realizar "&BE46&" repetições de um lado e trocar para o outro na sequência | ",BK47="P",OFFSET(Biblioteca!$H$2,MATCH(BL46,Biblioteca!$A$3:$A$200,0),0),TRUE,"")&IF(BM47="R","Ajuste a carga para que tenha "&$K$2&" repetições de reserva","")) -> Ajuste a carga para que tenha 0 a 2 repetições de reserva | BD47: =IF(AZ46="","",IFS(BK47="H","Carga Sugerida: "&ROUNDUP(BN46/2,0)&" kg de cada lado (Total: "&ROUNDUP(BN46/2,0)*2&" kg)",BK47="C","Este exercício usa o Peso Corporal como carga",BK47="E","Este exercício usa a resistência da banda elástica como carga",BK47="O","Carga Sugerida: "&INT(BN46)&" kg",TRUE,"")) -> Carga Sugerida: 11 kg | BJ47: =BJ46 -> 6 | BK47: =LEFT(BN47) -> O | BL47: =MID(BN47,2,1) -> O | BM47: =RIGHT(BN47) -> R | BN47: =IF(BL46="","",OFFSET(Biblioteca!$I$2,MATCH(BL46,Biblioteca!$A$3:$A$200,0),0)) -> OOR | BQ47: =IF(BQ46="","",IFS(CB47="A",Montagem!$G$30,CD47="T","Realizar a maior quantidade de repetições por "&BV46&" segundos | ",CD47="I",IF(CC47="U","Manter a posição por "&BV46&" segundos de um lado e trocar para o outro na sequência | ","Manter a posição por "&BV46&" segundos | "),CC47="A","Realizar alternadamente "&BV46&" repetições cada lado | ",CC47="U","Realizar "&BV46&" repetições de um lado e trocar para o outro na sequência | ",CB47="P",OFFSET(Biblioteca!$H$2,MATCH(CC46,Biblioteca!$A$3:$A$200,0),0),TRUE,"")&IF(CD47="R","Ajuste a carga para que tenha "&$K$2&" repetições de reserva","")) -> Mantenha 32-35min em intensidade constante com frequência cardíaca entre 105,5 - 116,2 bpm (50 - 60% VO2Máx -> 8,5 - 10,9km/h) | BU47: =IF(BQ46="","",IFS(CB47="H","Carga Sugerida: "&ROUNDUP(CE46/2,0)&" kg de cada lado (Total: "&ROUNDUP(CE46/2,0)*2&" kg)",CB47="C","Este exercício usa o Peso Corporal como carga",CB47="E","Este exercício usa a resistência da banda elástica como carga",CB47="O","Carga Sugerida: "&INT(CE46)&" kg",TRUE,"")) | CA47: =CA46 -> 6 | CB47: =LEFT(CE47) -> A | CC47: =MID(CE47,2,1) -> - | CD47: =RIGHT(CE47) -> - | CE47: =IF(CC46="","",OFFSET(Biblioteca!$I$2,MATCH(CC46,Biblioteca!$A$3:$A$200,0),0)) -> A-- | CH47: =IF(CH46="","",IFS(CS47="A",Montagem!$H$30,CU47="T","Realizar a maior quantidade de repetições por "&CM46&" segundos | ",CU47="I",IF(CT47="U","Manter a posição por "&CM46&" segundos de um lado e trocar para o outro na sequência | ","Manter a posição por "&CM46&" segundos | "),CT47="A","Realizar alternadamente "&CM46&" repetições cada lado | ",CT47="U","Realizar "&CM46&" repetições de um lado e trocar para o outro na sequência | ",CS47="P",OFFSET(Biblioteca!$H$2,MATCH(CT46,Biblioteca!$A$3:$A$200,0),0),TRUE,"")&IF(CU47="R","Ajuste a carga para que tenha "&$K$2&" repetições de reserva","")) | CL47: =IF(CH46="","",IFS(CS47="H","Carga Sugerida: "&ROUNDUP(CV46/2,0)&" kg de cada lado (Total: "&ROUNDUP(CV46/2,0)*2&" kg)",CS47="C","Este exercício usa o Peso Corporal como carga",CS47="E","Este exercício usa a resistência da banda elástica como carga",CS47="O","Carga Sugerida: "&INT(CV46)&" kg",TRUE,"")) | CR47: =CR46 -> 1 | CS47: =LEFT(CV47) | CT47: =MID(CV47,2,1) | CU47: =RIGHT(CV47) | CV47: =IF(CT46="","",OFFSET(Biblioteca!$I$2,MATCH(CT46,Biblioteca!$A$3:$A$200,0),0)) | CY47: =IF(CY46="","",IFS(DJ47="A",Montagem!$I$30,DL47="T","Realizar a maior quantidade de repetições por "&DD46&" segundos | ",DL47="I",IF(DK47="U","Manter a posição por "&DD46&" segundos de um lado e trocar para o outro na sequência | ","Manter a posição por "&DD46&" segundos | "),DK47="A","Realizar alternadamente "&DD46&" repetições cada lado | ",DK47="U","Realizar "&DD46&" repetições de um lado e trocar para o outro na sequência | ",DJ47="P",OFFSET(Biblioteca!$H$2,MATCH(DK46,Biblioteca!$A$3:$A$200,0),0),TRUE,"")&IF(DL47="R","Ajuste a carga para que tenha "&$K$2&" repetições de reserva","")) | DC47: =IF(CY46="","",IFS(DJ47="H","Carga Sugerida: "&ROUNDUP(DM46/2,0)&" kg de cada lado (Total: "&ROUNDUP(DM46/2,0)*2&" kg)",DJ47="C","Este exercício usa o Peso Corporal como carga",DJ47="E","Este exercício usa a resistência da banda elástica como carga",DJ47="O","Carga Sugerida: "&INT(DM46)&" kg",TRUE,"")) | DI47: =DI46 -> 1 | DJ47: =LEFT(DM47) | DK47: =MID(DM47,2,1) | DL47: =RIGHT(DM47) | DM47: =IF(DK46="","",OFFSET(Biblioteca!$I$2,MATCH(DK46,Biblioteca!$A$3:$A$200,0),0))
A48: =IF(M48="","",HYPERLINK(OFFSET(Biblioteca!$B$2,MATCH(M48,Biblioteca!$A$3:$A$200,0),0),M48)) | D48: =Montagem!Q32 | E48: =Montagem!R32 | F48: =Montagem!S32 | G48: =Montagem!T32 | H48: =Montagem!U32 | I48: =Montagem!V32 | K48: =Montagem!K32 -> 6 | L48: =Montagem!W32 | M48: =Montagem!L32 | N48: =Montagem!X32 | O48: =IF(N48="",L48,N48) | P48: =IF(L49="C",'Dados de Base'!$D$5*0.1,IF(L49="E",5,IF(J48="",O48,J48))) | R48: =IF(AD48="","",HYPERLINK(OFFSET(Biblioteca!$B$2,MATCH(AD48,Biblioteca!$A$3:$A$200,0),0),AD48)) | U48: =Montagem!AF32 | V48: =Montagem!AG32 | W48: =Montagem!AH32 | X48: =Montagem!AI32 | Y48: =Montagem!AJ32 | Z48: =Montagem!AK32 | AB48: =Montagem!Z32 -> 6 | AC48: =Montagem!AL32 | AD48: =Montagem!AA32 | AE48: =Montagem!AM32 | AF48: =IF(AE48="",AC48,AE48) | AG48: =IF(AC49="C",'Dados de Base'!$D$5*0.1,IF(AC49="E",5,IF(AA48="",AF48,AA48))) | AI48: =IF(AU48="","",HYPERLINK(OFFSET(Biblioteca!$B$2,MATCH(AU48,Biblioteca!$A$3:$A$200,0),0),AU48)) | AL48: =Montagem!AU32 | AM48: =Montagem!AV32 | AN48: =Montagem!AW32 | AO48: =Montagem!AX32 | AP48: =Montagem!AY32 | AQ48: =Montagem!AZ32 | AS48: =Montagem!AO32 -> 1 | AT48: =Montagem!BA32 | AU48: =Montagem!AP32 | AV48: =Montagem!BB32 | AW48: =IF(AV48="",AT48,AV48) | AX48: =IF(AT49="C",'Dados de Base'!$D$5*0.1,IF(AT49="E",5,IF(AR48="",AW48,AR48))) | AZ48: =IF(BL48="","",HYPERLINK(OFFSET(Biblioteca!$B$2,MATCH(BL48,Biblioteca!$A$3:$A$200,0),0),BL48)) -> Corda | BC48: =Montagem!BJ32 | BD48: =Montagem!BK32 | BE48: =Montagem!BL32 | BF48: =Montagem!BM32 | BG48: =Montagem!BN32 | BH48: =Montagem!BO32 | BJ48: =Montagem!BD32 -> 7 | BK48: =Montagem!BP32 -> 0 | BL48: =Montagem!BE32 -> Corda | BM48: =Montagem!BQ32 | BN48: =IF(BM48="",BK48,BM48) -> 0 | BO48: =IF(BK49="C",'Dados de Base'!$D$5*0.1,IF(BK49="E",5,IF(BI48="",BN48,BI48))) -> 0 | BQ48: =IF(CC48="","",HYPERLINK(OFFSET(Biblioteca!$B$2,MATCH(CC48,Biblioteca!$A$3:$A$200,0),0),CC48)) | BT48: =Montagem!BY32 | BU48: =Montagem!BZ32 | BV48: =Montagem!CA32 | BW48: =Montagem!CB32 | BX48: =Montagem!CC32 | BY48: =Montagem!CD32 | CA48: =Montagem!BS32 -> 6 | CB48: =Montagem!CE32 | CC48: =Montagem!BT32 | CD48: =Montagem!CF32 | CE48: =IF(CD48="",CB48,CD48) | CF48: =IF(CB49="C",'Dados de Base'!$D$5*0.1,IF(CB49="E",5,IF(BZ48="",CE48,BZ48))) | CH48: =IF(CT48="","",HYPERLINK(OFFSET(Biblioteca!$B$2,MATCH(CT48,Biblioteca!$A$3:$A$200,0),0),CT48)) | CK48: =Montagem!CN32 | CL48: =Montagem!CO32 | CM48: =Montagem!CP32 | CN48: =Montagem!CQ32 | CO48: =Montagem!CR32 | CP48: =Montagem!CS32 | CR48: =Montagem!CH32 -> 1 | CS48: =Montagem!CT32 | CT48: =Montagem!CI32 | CU48: =Montagem!CU32 | CV48: =IF(CU48="",CS48,CU48) | CW48: =IF(CS49="C",'Dados de Base'!$D$5*0.1,IF(CS49="E",5,IF(CQ48="",CV48,CQ48))) | CY48: =IF(DK48="","",HYPERLINK(OFFSET(Biblioteca!$B$2,MATCH(DK48,Biblioteca!$A$3:$A$200,0),0),DK48)) | DB48: =Montagem!DC32 | DC48: =Montagem!DD32 | DD48: =Montagem!DE32 | DE48: =Montagem!DF32 | DF48: =Montagem!DG32 | DG48: =Montagem!DH32 | DI48: =Montagem!CW32 -> 1 | DJ48: =Montagem!DI32 | DK48: =Montagem!CX32 | DL48: =Montagem!DJ32 | DM48: =IF(DL48="",DJ48,DL48) | DN48: =IF(DJ49="C",'Dados de Base'!$D$5*0.1,IF(DJ49="E",5,IF(DH48="",DM48,DH48)))
A49: =IF(A48="","",IFS(L49="A",Montagem!$C$30,N49="T","Realizar a maior quantidade de repetições por "&F48&" segundos | ",N49="I",IF(M49="U","Manter a posição por "&F48&" segundos de um lado e trocar para o outro na sequência | ","Manter a posição por "&F48&" segundos | "),M49="A","Realizar alternadamente "&F48&" repetições cada lado | ",M49="U","Realizar "&F48&" repetições de um lado e trocar para o outro na sequência | ",L49="P",OFFSET(Biblioteca!$H$2,MATCH(M48,Biblioteca!$A$3:$A$200,0),0),TRUE,"")&IF(N49="R","Ajuste a carga para que tenha "&$K$2&" repetições de reserva","")) | E49: =IF(A48="","",IFS(L49="H","Carga Sugerida: "&ROUNDUP(O48/2,0)&" kg de cada lado (Total: "&ROUNDUP(O48/2,0)*2&" kg)",L49="C","Este exercício usa o Peso Corporal como carga",L49="E","Este exercício usa a resistência da banda elástica como carga",L49="O","Carga Sugerida: "&INT(O48)&" kg",TRUE,"")) | K49: =K48 -> 6 | L49: =LEFT(O49) | M49: =MID(O49,2,1) | N49: =RIGHT(O49) | O49: =IF(M48="","",OFFSET(Biblioteca!$I$2,MATCH(M48,Biblioteca!$A$3:$A$200,0),0)) | R49: =IF(R48="","",IFS(AC49="A",Montagem!$D$30,AE49="T","Realizar a maior quantidade de repetições por "&W48&" segundos | ",AE49="I",IF(AD49="U","Manter a posição por "&W48&" segundos de um lado e trocar para o outro na sequência | ","Manter a posição por "&W48&" segundos | "),AD49="A","Realizar alternadamente "&W48&" repetições cada lado | ",AD49="U","Realizar "&W48&" repetições de um lado e trocar para o outro na sequência | ",AC49="P",OFFSET(Biblioteca!$H$2,MATCH(AD48,Biblioteca!$A$3:$A$200,0),0),TRUE,"")&IF(AE49="R","Ajuste a carga para que tenha "&$K$2&" repetições de reserva","")) | V49: =IF(R48="","",IFS(AC49="H","Carga Sugerida: "&ROUNDUP(AF48/2,0)&" kg de cada lado (Total: "&ROUNDUP(AF48/2,0)*2&" kg)",AC49="C","Este exercício usa o Peso Corporal como carga",AC49="E","Este exercício usa a resistência da banda elástica como carga",AC49="O","Carga Sugerida: "&INT(AF48)&" kg",TRUE,"")) | AB49: =AB48 -> 6 | AC49: =LEFT(AF49) | AD49: =MID(AF49,2,1) | AE49: =RIGHT(AF49) | AF49: =IF(AD48="","",OFFSET(Biblioteca!$I$2,MATCH(AD48,Biblioteca!$A$3:$A$200,0),0)) | AI49: =IF(AI48="","",IFS(AT49="A",Montagem!$E$30,AV49="T","Realizar a maior quantidade de repetições por "&AN48&" segundos | ",AV49="I",IF(AU49="U","Manter a posição por "&AN48&" segundos de um lado e trocar para o outro na sequência | ","Manter a posição por "&AN48&" segundos | "),AU49="A","Realizar alternadamente "&AN48&" repetições cada lado | ",AU49="U","Realizar "&AN48&" repetições de um lado e trocar para o outro na sequência | ",AT49="P",OFFSET(Biblioteca!$H$2,MATCH(AU48,Biblioteca!$A$3:$A$200,0),0),TRUE,"")&IF(AV49="R","Ajuste a carga para que tenha "&$K$2&" repetições de reserva","")) | AM49: =IF(AI48="","",IFS(AT49="H","Carga Sugerida: "&ROUNDUP(AW48/2,0)&" kg de cada lado (Total: "&ROUNDUP(AW48/2,0)*2&" kg)",AT49="C","Este exercício usa o Peso Corporal como carga",AT49="E","Este exercício usa a resistência da banda elástica como carga",AT49="O","Carga Sugerida: "&INT(AW48)&" kg",TRUE,"")) | AS49: =AS48 -> 1 | AT49: =LEFT(AW49) | AU49: =MID(AW49,2,1) | AV49: =RIGHT(AW49) | AW49: =IF(AU48="","",OFFSET(Biblioteca!$I$2,MATCH(AU48,Biblioteca!$A$3:$A$200,0),0)) | AZ49: =IF(AZ48="","",IFS(BK49="A",Montagem!$F$30,BM49="T","Realizar a maior quantidade de repetições por "&BE48&" segundos | ",BM49="I",IF(BL49="U","Manter a posição por "&BE48&" segundos de um lado e trocar para o outro na sequência | ","Manter a posição por "&BE48&" segundos | "),BL49="A","Realizar alternadamente "&BE48&" repetições cada lado | ",BL49="U","Realizar "&BE48&" repetições de um lado e trocar para o outro na sequência | ",BK49="P",OFFSET(Biblioteca!$H$2,MATCH(BL48,Biblioteca!$A$3:$A$200,0),0),TRUE,"")&IF(BM49="R","Ajuste a carga para que tenha "&$K$2&" repetições de reserva","")) -> 1x (3m all out) | BD49: =IF(AZ48="","",IFS(BK49="H","Carga Sugerida: "&ROUNDUP(BN48/2,0)&" kg de cada lado (Total: "&ROUNDUP(BN48/2,0)*2&" kg)",BK49="C","Este exercício usa o Peso Corporal como carga",BK49="E","Este exercício usa a resistência da banda elástica como carga",BK49="O","Carga Sugerida: "&INT(BN48)&" kg",TRUE,"")) | BJ49: =BJ48 -> 7 | BK49: =LEFT(BN49) -> A | BL49: =MID(BN49,2,1) -> T | BM49: =RIGHT(BN49) -> T | BN49: =IF(BL48="","",OFFSET(Biblioteca!$I$2,MATCH(BL48,Biblioteca!$A$3:$A$200,0),0)) -> AT | BQ49: =IF(BQ48="","",IFS(CB49="A",Montagem!$G$30,CD49="T","Realizar a maior quantidade de repetições por "&BV48&" segundos | ",CD49="I",IF(CC49="U","Manter a posição por "&BV48&" segundos de um lado e trocar para o outro na sequência | ","Manter a posição por "&BV48&" segundos | "),CC49="A","Realizar alternadamente "&BV48&" repetições cada lado | ",CC49="U","Realizar "&BV48&" repetições de um lado e trocar para o outro na sequência | ",CB49="P",OFFSET(Biblioteca!$H$2,MATCH(CC48,Biblioteca!$A$3:$A$200,0),0),TRUE,"")&IF(CD49="R","Ajuste a carga para que tenha "&$K$2&" repetições de reserva","")) | BU49: =IF(BQ48="","",IFS(CB49="H","Carga Sugerida: "&ROUNDUP(CE48/2,0)&" kg de cada lado (Total: "&ROUNDUP(CE48/2,0)*2&" kg)",CB49="C","Este exercício usa o Peso Corporal como carga",CB49="E","Este exercício usa a resistência da banda elástica como carga",CB49="O","Carga Sugerida: "&INT(CE48)&" kg",TRUE,"")) | CA49: =CA48 -> 6 | CB49: =LEFT(CE49) | CC49: =MID(CE49,2,1) | CD49: =RIGHT(CE49) | CE49: =IF(CC48="","",OFFSET(Biblioteca!$I$2,MATCH(CC48,Biblioteca!$A$3:$A$200,0),0)) | CH49: =IF(CH48="","",IFS(CS49="A",Montagem!$H$30,CU49="T","Realizar a maior quantidade de repetições por "&CM48&" segundos | ",CU49="I",IF(CT49="U","Manter a posição por "&CM48&" segundos de um lado e trocar para o outro na sequência | ","Manter a posição por "&CM48&" segundos | "),CT49="A","Realizar alternadamente "&CM48&" repetições cada lado | ",CT49="U","Realizar "&CM48&" repetições de um lado e trocar para o outro na sequência | ",CS49="P",OFFSET(Biblioteca!$H$2,MATCH(CT48,Biblioteca!$A$3:$A$200,0),0),TRUE,"")&IF(CU49="R","Ajuste a carga para que tenha "&$K$2&" repetições de reserva","")) | CL49: =IF(CH48="","",IFS(CS49="H","Carga Sugerida: "&ROUNDUP(CV48/2,0)&" kg de cada lado (Total: "&ROUNDUP(CV48/2,0)*2&" kg)",CS49="C","Este exercício usa o Peso Corporal como carga",CS49="E","Este exercício usa a resistência da banda elástica como carga",CS49="O","Carga Sugerida: "&INT(CV48)&" kg",TRUE,"")) | CR49: =CR48 -> 1 | CS49: =LEFT(CV49) | CT49: =MID(CV49,2,1) | CU49: =RIGHT(CV49) | CV49: =IF(CT48="","",OFFSET(Biblioteca!$I$2,MATCH(CT48,Biblioteca!$A$3:$A$200,0),0)) | CY49: =IF(CY48="","",IFS(DJ49="A",Montagem!$I$30,DL49="T","Realizar a maior quantidade de repetições por "&DD48&" segundos | ",DL49="I",IF(DK49="U","Manter a posição por "&DD48&" segundos de um lado e trocar para o outro na sequência | ","Manter a posição por "&DD48&" segundos | "),DK49="A","Realizar alternadamente "&DD48&" repetições cada lado | ",DK49="U","Realizar "&DD48&" repetições de um lado e trocar para o outro na sequência | ",DJ49="P",OFFSET(Biblioteca!$H$2,MATCH(DK48,Biblioteca!$A$3:$A$200,0),0),TRUE,"")&IF(DL49="R","Ajuste a carga para que tenha "&$K$2&" repetições de reserva","")) | DC49: =IF(CY48="","",IFS(DJ49="H","Carga Sugerida: "&ROUNDUP(DM48/2,0)&" kg de cada lado (Total: "&ROUNDUP(DM48/2,0)*2&" kg)",DJ49="C","Este exercício usa o Peso Corporal como carga",DJ49="E","Este exercício usa a resistência da banda elástica como carga",DJ49="O","Carga Sugerida: "&INT(DM48)&" kg",TRUE,"")) | DI49: =DI48 -> 1 | DJ49: =LEFT(DM49) | DK49: =MID(DM49,2,1) | DL49: =RIGHT(DM49) | DM49: =IF(DK48="","",OFFSET(Biblioteca!$I$2,MATCH(DK48,Biblioteca!$A$3:$A$200,0),0))
